Workbook
Name AdhesiveList: '[1]Raw Material DB'!$Q$2:$Q$5
Name amount: #REF!
Name BagTypeList: '[1]Raw Material DB'!$X$2:$X$26
Name Barier: #REF!
Name Clear: #REF!
Name Config_302FG: #REF!
Name Config_302FGW: #REF!
Name Config_306: #REF!
Name Config_308: #REF!
Name Config_312FG: #REF!
Name Config_312W: #REF!
Name Config_NKR: #REF!
Name Config_PL2021: "'Film Pricing- New'!$AF$10:$AF$20"
Name Config_PL2022: "'Film Pricing- New'!$AG$10:$AG$20"
Name Config_PL2023: "'Film Pricing- New'!$AH$10:$AH$20"
Name Family: #REF!
Name Film_type: '[3]List of names'!$W$15:$W$16
Name FilmList: #REF!
Name GF048.1: #REF!
Name Grouped: #REF!
Name HardenerList: '[1]Raw Material DB'!$U$2:$U$4
Name JOB: OFFSET('[4]GEF063 WP Sales'!B6,0,0,COUNTA('[4]GEF063 WP Sales'!$AS$11:$AS$200),COUNTA('[4]GEF063 WP Sales'!$AS$11:$AT$11))
Name Jobs: '[4]GEF063 WP Sales'!$AS$10:$AS$210+'[4]GEF063 WP Sales'!$AU$10-2
Name Jobss: '[4]GEF063 WP Sales'!XFC2:XFC2+VALUE('[4]GEF063 WP Sales'!$AU$10)
Name Laminate: '[3]List of names'!$P$15:$P$18
Name Laminate_Thickness: #REF!
Name Laminate_type: '[5]List of names'!$P$14:$X$14
Name Laminate106: [3]!Table2[Laminate106]
Name Laminate604: [3]!Table4[Laminate608]
Name Laminate607: [3]!Table6[Laminate607]
Name Laminate607\: [3]!Table6[Laminate607]
Name Laminate608W: [3]!Table3[Laminate608 W]
Name LaminateList: '[1]Raw Material DB'!$M$20:$M$82
Name MATERIAL: '[6]Raw materials prices'!$L$51:$L$61
Name Materials: '[7]list for drop down menu'!$A$1:$A$20
Name Metalize: #REF!
Name NKR: '[1]List of names'!#REF!
Name Paper: #REF!
Name pirce: #REF!
Name PO: #REF!
Name price: #REF!
Name ShippingRoutes: HELPER!$AF$2:$AF$4
Name ThicknessList: #REF!
Name USD: '[3]Raw material summary'!$F$3
Name width: #REF!
Name Film_type: '[2]List of names'!$Y$15:$Y$16
Name Laminate: '[2]List of names'!$P$15:$P$22
Name Laminate_type: '[2]List of names'!$P$14:$X$14
Name Laminate604: [2]!Table4[Laminate618]
Name Laminate608W: [2]!Table3[Laminate608W]
Name USD: '[2]Raw material summary'!$F$3

Sheet Sheet1
A3: Film | B3: Grade | C3: Sum of Price Calculated(€) Thickness & QTY related
A4: TIPA 302FG | B4: S723 | C4: 0.2424
B5: S724 | C5: 0.02352
A6: TIPA 302FG W | B6: S723 | C6: 0.2424
B7: S724 | C7: 0.09408
A8: TIPA 306M | B8: S723 | C8: 0.2424
B9: S724 | C9: 0.0588
A10: TIPA 306W | B10: S723 | C10: 0.2424
B11: S724 | C11: 0.1176
A12: TIPA 312 MFG | B12: S723 | C12: 0.2424
B13: S724 | C13: 0.06762
A14: TIPA 312MFGW | B14: S723 | C14: 0.2424
B15: S724 | C15: 0.06762
A16: Grand Total | C16: 1.88364
A20: Film | B20: Price (€/kg) | C20: Price ($/kg)
A21: PL202.1 | B21: 8.995784 | C21: 10.435109
A22: PL202.2 | B22: 6.73178 | C22: 7.8088648
A23: PL202.3 | B23: 5.74578 | C23: 6.6651048
A24: TIPA 302FG | B24: 3.599712 | C24: 4.1756659
A25: TIPA 302FG W | B25: 3.916872 | C25: 4.5435715
A26: TIPA 306M | B26: 3.520798 | C26: 4.0841257
A27: TIPA 306W | B27: 3.805774 | C27: 4.4146978
A28: TIPA 312 MFG | B28: 2.899978 | C28: 3.3639745
A29: TIPA 312MFGW | B29: 3.178978 | C29: 3.6876145
A32: FILM | B32: Material | C32: % from Total
A33: TIPA 302FG | B33: S723 | C33: =C4/$B$24
B34: S724 | C34: =C5/$B$24
A35: TIPA 302FG W | B35: S723 | C35: =C6/$B$25
B36: S724 | C36: =C7/$B$25
A37: TIPA 306M | B37: S723 | C37: =C8/$B$26
B38: S724 | C38: =C9/$B$26
A39: TIPA 306W | B39: S723 | C39: =C10/$B$27
B40: S724 | C40: =C11/$B$27
A41: TIPA 312 MFG | B41: S723 | C41: =C12/$B$28
B42: S724 | C42: =C13/$B$28
A43: TIPA 312MFGW | B43: S723 | C43: =C14/$B$29
B44: S724 | C44: =C15/$B$29

Sheet Step by Step
B2: 📋 FILM PRICING LIST - STEP BY STEP GUIDE
B3: How to use the Film Pricing calculator
B5: 🔄 PRICING WORKFLOW
B7: STEP 1 | C7: → | D7: STEP 2 | E7: → | F7: STEP 3 | G7: → | H7: STEP 4 | I7: → | J7: STEP 5
B8: 📝 INPUT | D8: ⚙️ SPECS | F8: 💰 COSTS | H8: 📦 SHIP | J8: 💵 PRICE
B11: 📝 DETAILED STEPS
B13: Step | C13: Action | D13: Column | E13: Example | F13: Notes
B14: 1️⃣ | C14: Select Film Type | D14: A | E14: TIPA 302FG | F14: Dropdown list
B15: 2️⃣ | C15: Enter Width | D15: B | E15: 406 mm | F15: Width in mm
B16: 3️⃣ | C16: Enter Thickness | D16: C | E16: 20 µ | F16: Dropdown list
B17: 4️⃣ | C17: Enter Weight | D17: E | E17: 500 Kg | F17: Order qty (Kg)
B18: 5️⃣ | C18: Weight Override | D18: F | E18: 500 Kg | F18: Optional
B19: 6️⃣ | C19: Shipping Dest. | D19: S | E19: EU/USA | F19: Dropdown list
B20: 7️⃣ | C20: Review Price | D20: W | E20: Auto | F20: Final price/Kg
B21: 8️⃣ | C21: Compare Margins | D21: X+ | E21: 25%, 30% | F21: Multiple options
B24: ⚡ AUTO-CALCULATIONS
B26: Calculation | C26: Formula Logic
B27: Length (Mr) | C27: Weight ÷ (Width × Thickness × Density)
B28: Production Cost | C28: Hourly Rate × Production Time
B29: Total Cost | C29: RM + Production + Depreciation + Waste + Ship
B30: Sell Price | C30: Total Cost × (1 + Margin %)
B33: 💡 QUICK TIPS
B35: ✓ Use dropdowns to avoid typos
B36: ✓ Higher weight = lower cost/Kg (economies of scale)
B37: ✓ Compare margin columns for pricing options
B38: ✓ Density auto-fills based on Film Type

Sheet Film -Summary Pricing
A1: Tipa 303B&W | F1: All changes to paramters should be in Film Summary
A2: Tipa302WFG | S2: 0.25
A3: TIPA 303 W | I3: עלויות ייצור | K3: סה"כ | L3: 0.15 | M3: ='[2]Film -Summary'!M3 | S3: 0.225 | T3: =S3/100/(1+S3)
A4: Film | B4: Width (mm) | C4: Length (Mr) | D4: Thickenes (µ) | E4: צפיפות | F4: Total KG in one Meter | G4: Total Kg Produced | H4: Hourly rate | I4: 1Kg production cost | J4: RM cost in 1 Kg | K4: To tal RM and Production | L4: Total Cost and depreciation | M4: Dep | N4: Other costs | O4: Basc Cost | P4: SET UP | Q4: Printing | R4: Shipping & Customs | S4: Total Cost | T4: Selling price | W4: Producer
A5: Tipa302FG | B5: 1800 | C5: 1 | D5: 20 | E5: 1.25 | F5: =C5*E5*(D5/1000)*(B5/1000) | G5: 450 | H5: 510 | I5: =H5/G5+0.2 | J5: =VLOOKUP(A5,'[2]Raw material summary'!A:B,2,0) | K5: =J5+I5 | L5: =K5*(1+$L$3) | M5: 0.15 | N5: =L5*$M$3 | O5: =L5+N5 | P5: =1550*2/60000 | S5: =SUM(O5:R5) | T5: =S5/(1-($S$3)) | U5: =2000*F5 | V5: =U5*T5
A6: Tipa302FG | B6: 1800 | C6: 1 | D6: 25 | E6: 1.25 | F6: =C6*E6*(D6/1000)*(B6/1000) | G6: 500 | H6: =H5 | I6: =H6/G6+0.2 | J6: =VLOOKUP(A6,'[2]Raw material summary'!A:B,2,0) | K6: =J6+I6 | L6: =K6*(1+$L$3) | M6: 0.15 | N6: =L6*$M$3 | O6: =L6+N6 | P6: =1550*2/60000 | S6: =SUM(O6:R6) | T6: =S6/(1-($S$3))
A7: Tipa302FG | B7: 1800 | C7: 1 | D7: 30 | E7: 1.25 | F7: =C7*E7*(D7/1000)*(B7/1000) | G7: 500 | H7: =H6 | I7: =H7/G7+0.2 | J7: =VLOOKUP(A7,'[2]Raw material summary'!A:B,2,0) | K7: =J7+I7 | L7: =K7*(1+$L$3) | M7: 0.15 | N7: =L7*$M$3 | O7: =L7+N7 | P7: =1550*2/60000 | S7: =SUM(O7:R7) | T7: =S7/(1-($S$3)) | U7: =1/F7*25
A8: Tipa302FG | B8: 1800 | C8: 1 | D8: 35 | E8: 1.25 | F8: =C8*E8*(D8/1000)*(B8/1000) | G8: 500 | H8: =H7 | I8: =H8/G8+0.2 | J8: =VLOOKUP(A8,'[2]Raw material summary'!A:B,2,0) | K8: =J8+I8 | L8: =K8*(1+$L$3) | M8: 0.15 | N8: =L8*$M$3 | O8: =L8+N8 | P8: =1550*2/60000 | S8: =SUM(O8:R8) | T8: =S8/(1-($S$3))
A9: Tipa302FG | B9: 1800 | C9: 1 | D9: 40 | E9: 1.25 | F9: =C9*E9*(D9/1000)*(B9/1000) | G9: 500 | H9: =H8 | I9: =H9/G9+0.2 | J9: =VLOOKUP(A9,'[2]Raw material summary'!A:B,2,0) | K9: =J9+I9 | L9: =K9*(1+$L$3) | M9: 0.15 | N9: =L9*$M$3 | O9: =L9+N9 | P9: =1550*2/60000 | S9: =SUM(O9:R9) | T9: =S9/(1-($S$3))
A10: Tipa302FG | B10: 1800 | C10: 1 | D10: 50 | E10: 1.25 | F10: =C10*E10*(D10/1000)*(B10/1000) | G10: 500 | H10: =H9 | I10: =H10/G10+0.2 | J10: =VLOOKUP(A10,'[2]Raw material summary'!A:B,2,0) | K10: =J10+I10 | L10: =K10*(1+$L$3) | M10: 0.15 | N10: =L10*$M$3 | O10: =L10+N10 | P10: =1550*2/60000 | S10: =SUM(O10:R10) | T10: =S10/(1-($S$3))
A11: Tipa302FG | B11: 1800 | C11: 1 | D11: 60 | E11: 1.25 | F11: =C11*E11*(D11/1000)*(B11/1000) | G11: 500 | H11: =H10 | I11: =H11/G11+0.2 | J11: =VLOOKUP(A11,'[2]Raw material summary'!A:B,2,0) | K11: =J11+I11 | L11: =K11*(1+$L$3) | M11: 0.15 | N11: =L11*$M$3 | O11: =L11+N11 | P11: =1550*2/60000 | S11: =SUM(O11:R11) | T11: =S11/(1-($S$3)) | AB11: =19839/5
A12: Tipa302FG | B12: 1800 | C12: 1 | D12: 70 | E12: 1.25 | F12: =C12*E12*(D12/1000)*(B12/1000) | G12: 500 | H12: =H11 | I12: =H12/G12+0.2 | J12: =VLOOKUP(A12,'[2]Raw material summary'!A:B,2,0) | K12: =J12+I12 | L12: =K12*(1+$L$3) | M12: 0.15 | N12: =L12*$M$3 | O12: =L12+N12 | P12: =1550*2/60000 | S12: =SUM(O12:R12) | T12: =S12/(1-($S$3))
A13: Tipa302FG | B13: 1800 | C13: 1 | D13: 80 | E13: 1.25 | F13: =C13*E13*(D13/1000)*(B13/1000) | G13: 500 | H13: =H12 | I13: =H13/G13+0.2 | J13: =VLOOKUP(A13,'[2]Raw material summary'!A:B,2,0) | K13: =J13+I13 | L13: =K13*(1+$L$3) | M13: 0.15 | N13: =L13*$M$3 | O13: =L13+N13 | P13: =1550*2/60000 | R13: 0.2 | S13: =SUM(O13:R13) | T13: =S13/(1-($S$3))
A15: =A25 | B15: =B25 | C15: 1 | D15: =C25 | E15: 1.25 | F15: =C15*E15*(D15/1000)*(B15/1000) | G15: =VLOOKUP(D15,$D$5:$G$13,4,0) | H15: =$H$5 | I15: =IF(W15="Verbano",0.8,IF(W15="Polifilm","X",H15/G15+0.2)) | J15: =VLOOKUP(A15,'[2]Raw material summary'!A:B,2,0) | K15: =J15+I15 | L15: =K15*(1+M15) | M15: =IF(F25>=$D$36,$E$37,IF(F25>=$C$36,$D$37,IF(F25>=$B$36,$C$37,$B$37)))+IF(OR(D15=25,D15=20),$B$41,IF(D15=30,$B$40,0)) | N15: =IF(OR(A15=$A$1,A15=$A$2,A15=$A$3),1500/F25,0)+0.3 | O15: =L15+N15 | P15: =IF(W15="Verbano",30/60*500*K15/20000,(1500+3000)/30000) | Q15: 4 | R15: =9*0.15+3 | S15: =SUM(O15:R15) | T15: =S15/(1-($S$3)) | U15: =1000*F15 | W15: Gefo | Y15: =T15*F25 | AB15: Verbano
A16: =A26 | B16: =B26 | C16: 1 | D16: =C26 | E16: 1.25 | F16: =C16*E16*(D16/1000)*(B16/1000) | G16: =VLOOKUP(D16,$D$5:$G$13,4,0) | H16: =$H$5 | I16: =IF(W16="Verbano",0.8,IF(W16="Polifilm","X",H16/G16+0.2)) | J16: =VLOOKUP(A16,'[2]Raw material summary'!A:B,2,0) | K16: =J16+I16 | L16: =K16*(1+M16) | M16: =IF(F26>=$D$36,$E$37,IF(F26>=$C$36,$D$37,IF(F26>=$B$36,$C$37,$B$37)))+IF(OR(D16=25,D16=20),$B$41,IF(D16=30,$B$40,0)) | N16: =IF(OR(A16=$A$1,A16=$A$2,A16=$A$3),1500/F26,0)+0.3 | O16: =L16+N16 | P16: =IF(W16="Verbano",30/60*500*K16/20000,(1500+3000)/30000) | S16: =SUM(O16:R16) | T16: =S16/(1-($S$3)) | W16: Gefo | Y16: =T16*F26 | AB16: Polifilm
A17: =A27 | B17: =B27 | C17: 1 | D17: =C27 | E17: 1.25 | F17: =C17*E17*(D17/1000)*(B17/1000) | G17: =VLOOKUP(D17,$D$5:$G$13,4,0) | H17: =$H$5 | I17: =IF(W17="Verbano",0.8,IF(W17="Polifilm","X",H17/G17+0.2)) | J17: =VLOOKUP(A17,'[2]Raw material summary'!A:B,2,0) | K17: =J17+I17 | L17: =K17*(1+M17) | M17: =IF(F27>=$D$36,$E$37,IF(F27>=$C$36,$D$37,IF(F27>=$B$36,$C$37,$B$37)))+IF(OR(D17=25,D17=20),$B$41,IF(D17=30,$B$40,0)) | N17: =IF(OR(A17=$A$1,A17=$A$2,A17=$A$3),1500/F27,0)+0.3 | O17: =L17+N17 | P17: =IF(W17="Verbano",30/60*500*K17/20000,(1500+3000)/30000) | S17: =SUM(O17:R17) | T17: =S17/(1-($S$3)) | W17: Gefo | Y17: =T17*F27 | AB17: Gefo
A18: =A28 | B18: =B28 | C18: 1 | D18: =C28 | E18: 1.25 | F18: =C18*E18*(D18/1000)*(B18/1000) | G18: =VLOOKUP(D18,$D$5:$G$13,4,0) | H18: =$H$5 | I18: =IF(W18="Verbano",0.8,IF(W18="Polifilm","X",H18/G18+0.2)) | J18: =VLOOKUP(A18,'[2]Raw material summary'!A:B,2,0) | K18: =J18+I18 | L18: =K18*(1+M18) | M18: =IF(F28>=$D$36,$E$37,IF(F28>=$C$36,$D$37,IF(F28>=$B$36,$C$37,$B$37)))+IF(OR(D18=25,D18=20),$B$41,IF(D18=30,$B$40,0)) | N18: =IF(OR(A18=$A$1,A18=$A$2,A18=$A$3),1500/F28,0)+0.3 | O18: =L18+N18 | P18: =IF(W18="Verbano",30/60*500*K18/20000,(1500+3000)/30000) | S18: =SUM(O18:R18) | T18: =S18/(1-($S$3)) | W18: Gefo
A19: =A29 | B19: =B29 | C19: 1 | D19: =C29 | E19: 1.25 | F19: =C19*E19*(D19/1000)*(B19/1000) | G19: =VLOOKUP(D19,$D$5:$G$13,4,0) | H19: =$H$5 | I19: =IF(W19="Verbano",0.8,IF(W19="Polifilm","X",H19/G19+0.2)) | J19: =VLOOKUP(A19,'[2]Raw material summary'!A:B,2,0) | K19: =J19+I19 | L19: =K19*(1+M19) | M19: =IF(F29>=$D$36,$E$37,IF(F29>=$C$36,$D$37,IF(F29>=$B$36,$C$37,$B$37)))+IF(OR(D19=25,D19=20),$B$41,IF(D19=30,$B$40,0))+1400/B29-1 | N19: =IF(OR(A19=$A$1,A19=$A$2,A19=$A$3),1500/F29,0)+0.3 | O19: =L19+N19 | P19: =IF(W19="Verbano",30/60*500*K19/20000,(1500+3000)/30000) | S19: =SUM(O19:R19) | T19: =S19/(1-($S$3)) | U19: 0.18 | W19: Gefo
A20: =A30 | B20: =B30 | C20: 1 | D20: =C30 | E20: 1.25 | F20: =C20*E20*(D20/1000)*(B20/1000) | G20: =VLOOKUP(D20,$D$5:$G$13,4,0) | H20: =$H$5 | I20: =IF(W20="Verbano",0.8,IF(W20="Polifilm","X",H20/G20+0.2)) | J20: =VLOOKUP(A20,'[2]Raw material summary'!A:B,2,0) | K20: =J20+I20 | L20: =K20*(1+M20) | M20: =IF(F30>=$D$36,$E$37,IF(F30>=$C$36,$D$37,IF(F30>=$B$36,$C$37,$B$37)))+IF(OR(D20=25,D20=20),$B$41,IF(D20=30,$B$40,0))+1400/B30-1 | N20: =IF(OR(A20=$A$1,A20=$A$2,A20=$A$3),1500/F30,0)+0.3 | O20: =L20+N20 | P20: =IF(W20="Verbano",30/60*500*K20/20000,(1500+3000)/30000) | S20: =SUM(O20:R20) | T20: =S20/(1-($S$3)) | W20: Gefo
H22: KG | I22: =+I25*1.08 | L22: ML
H23: Eur | J23: USD | L23: Eur | N23: USD | P23: Impression Prices
A24: Type of film | B24: Width | C24: Thickness | D24: Printed? | E24: Slitting? | F24: Weight | G24: Length | H24: Cost | I24: Price | J24: Cost | K24: Price | L24: Cost | M24: Price | N24: Cost | O24: Price | P24: Repeat | Q24: Impression in ML | R24: Number of Impression | S24: Ml | T24: Cost per Imp | U24: Price per Imp
A25: Tipa302FG | B25: 406 | C25: 35 | D25: Yes | E25: No | F25: =G25*F15 | G25: 1800000 | H25: =S15 | I25: =T15 | J25: =H25*USD | K25: =I25*USD | L25: =H25*$F15 | M25: =I25*$F15 | N25: =L25*USD | O25: =M25*USD | P25: 60 | Q25: =1000/P25 | R25: 30000000 | S25: =R25/Q25 | T25: =L25/Q25 | U25: =M25/Q25 | W25: =F25*K25
A26: Tipa302FG | B26: 434 | C26: 35 | D26: Yes | E26: No | F26: =G26*F16 | G26: =G25/2 | H26: =S16 | I26: =T16 | J26: =H26*USD | K26: =I26*USD | L26: =H26*$F16 | M26: =I26*$F16 | N26: =L26*USD | O26: =M26*USD | P26: 60 | Q26: =1000/P26 | R26: =30000000/2 | S26: =R26/Q26 | T26: =L26/Q26 | U26: =M26/Q26
A27: Tipa312W | B27: 1270 | C27: 35 | D27: No | E27: No | F27: 3000 | G27: =F27/F17 | H27: =S17 | I27: =T17 | J27: =H27*USD | K27: =I27*USD | L27: =H27*$F17 | M27: =I27*$F17 | N27: =L27*USD | O27: =M27*USD | P27: 300 | Q27: =1000/P27 | R27: 2000000 | S27: =R27/Q27 | T27: =L27/Q27 | U27: =M27/Q27
A28: Tipa312W | B28: 750 | C28: 35 | D28: No | E28: No | F28: 7000 | G28: =F28/F18 | H28: =S18 | I28: =T18 | J28: =H28*USD | K28: =I28*USD | L28: =H28*$F18 | M28: =I28*$F18 | N28: =L28*USD | O28: =M28*USD
A29: Tipa312W | B29: 1020 | C29: 35 | D29: No | E29: No | F29: 7000 | G29: =F29/F19 | H29: =S19 | I29: =T19 | J29: =H29*USD | K29: =I29*USD | L29: =H29*$F19 | M29: =I29*$F19 | N29: =L29*USD | O29: =M29*USD
A30: Tipa312W | B30: 1270 | C30: 35 | D30: No | E30: No | F30: 7000 | G30: =F30/F20 | H30: =S20 | I30: =T20 | J30: =H30*USD | K30: =I30*USD | L30: =H30*$F20 | M30: =I30*$F20 | N30: =L30*USD | O30: =M30*USD
B32: =B25*21 | C32: =760/C25 | G32: =G25/C32
A33: Paramters | C33: =760/C26 | G33: =G26/C33
A36: Weight | B36: 1000 | C36: 2000 | D36: 7000
A37: Dep | B37: 0.25 | C37: 0.2 | D37: 0.15 | E37: 0.125
A39: Dep if below 30 Micron
A40: 30 | B40: 0.05
A41: 20,25 | B41: 0.075
A43: Yes
A44: No

Sheet BOM
A1: Film | B1: Ext | C1: Material | D1: Grade | E1: Serial Number | F1: Resin | G1: Thickness (µ) | H1: QTY | I1: Price (€/kg) | J1: Price Calculated(€) Thickness & QTY related | L1: Film | M1: Grade | N1: Serial Number | O1: Price Calculated(€) Thickness & QTY related | Q1: Film | R1: Price (€/kg) | S1: Price ($/kg)
A2: TIPA 302FG | B2: Ext. A (Out - Chillroll) | C2: PBSA | D2: =IF(C2="","",IFERROR(_xlfn.XLOOKUP(C2,HELPER!$A$2:$A$76,HELPER!$B$2:$B$76,""),D2)) | E2: =IFERROR(_xlfn.XLOOKUP(D2,HELPER!$B:$B,HELPER!$C:$C,""),"") | F2: =IFERROR(_xlfn.XLOOKUP(D2,HELPER!$B:$B,HELPER!$D:$D,""),"") | G2: 8 | H2: 0.826 | I2: =IF(AND(H2<>"",IFERROR(_xlfn.XLOOKUP(D2,HELPER!$B:$B,HELPER!$E:$E,""),"")=""),"Missing price",IFERROR(_xlfn.XLOOKUP(D2,HELPER!$B:$B,HELPER!$E:$E,"")," ")) | J2: =IFERROR(H2*(IF(G2=8,I2*HELPER!$G$2,BOM!I2*HELPER!$G$3))," ") | L2: {=IFERROR(_xlfn.LET(_xlpm.pairs,_xlfn._xlws.FILTER($A$2:$D$391,($A$2:$A$391<>"")*(TRIM($D$2:$D$391)<>"")),_xlpm.uniquePairs,_xlfn.UNIQUE(_xlfn.HSTACK(INDEX(_xlpm.pairs,,1),INDEX(_xlpm.pairs,,4))),_xlpm.sortedPairs,_xlfn._xlws.SORT(_xlpm.uniquePairs,1,1),IF(ROW()-1<=ROWS(_xlpm.sortedPairs),INDEX(_xlpm.sortedPairs,ROW()-1,1),"")),"")} | M2: {=IFERROR(_xlfn.LET(_xlpm.pairs,_xlfn._xlws.FILTER($A$2:$D$391,($A$2:$A$391<>"")*(TRIM($D$2:$D$391)<>"")),_xlpm.uniquePairs,_xlfn.UNIQUE(_xlfn.HSTACK(INDEX(_xlpm.pairs,,1),INDEX(_xlpm.pairs,,4))),_xlpm.sortedPairs,_xlfn._xlws.SORT(_xlpm.uniquePairs,1,1),IF(ROW()-1<=ROWS(_xlpm.sortedPairs),INDEX(_xlpm.sortedPairs,ROW()-1,2),"")),"")} | N2: {=IF(OR(L2="",M2=""),"",IFERROR(INDEX($E$2:$E$391,MATCH(1,($A$2:$A$391=L2)*($D$2:$D$391=M2),0)),""))} | O2: =IF(OR(L2="",M2=""),"",SUMIFS($J$2:$J$391,$A$2:$A$391,L2,$D$2:$D$391,M2)) | Q2: {=IFERROR(INDEX($L$2:$L$391,MATCH(0,COUNTIF($Q$1:Q1,$L$2:$L$391)+IF($L$2:$L$391="",1,0),0)),"")} | R2: =IF(Q2="","",SUMIF($L$2:$L$391,Q2,$O$2:$O$391)) | S2: =IFERROR(Table3[[#This Row],[Price (€/kg)]]*HELPER!$AK$2," ")
A3: TIPA 302FG | B3: Ext. A (Out - Chillroll) | C3: PLA | D3: =IF(C3="","",IFERROR(_xlfn.XLOOKUP(C3,HELPER!$A$2:$A$76,HELPER!$B$2:$B$76,""),D3)) | E3: =IFERROR(_xlfn.XLOOKUP(D3,HELPER!$B:$B,HELPER!$C:$C,""),"") | F3: =IFERROR(_xlfn.XLOOKUP(D3,HELPER!$B:$B,HELPER!$D:$D,""),"") | G3: 8 | H3: 0.144 | I3: =IF(AND(H3<>"",IFERROR(_xlfn.XLOOKUP(D3,HELPER!$B:$B,HELPER!$E:$E,""),"")=""),"Missing price",IFERROR(_xlfn.XLOOKUP(D3,HELPER!$B:$B,HELPER!$E:$E,"")," ")) | J3: =IFERROR(H3*(IF(G3=8,I3*HELPER!$G$2,BOM!I3*HELPER!$G$3))," ") | L3: {=IFERROR(_xlfn.LET(_xlpm.pairs,_xlfn._xlws.FILTER($A$2:$D$391,($A$2:$A$391<>"")*(TRIM($D$2:$D$391)<>"")),_xlpm.uniquePairs,_xlfn.UNIQUE(_xlfn.HSTACK(INDEX(_xlpm.pairs,,1),INDEX(_xlpm.pairs,,4))),_xlpm.sortedPairs,_xlfn._xlws.SORT(_xlpm.uniquePairs,1,1),IF(ROW()-1<=ROWS(_xlpm.sortedPairs),INDEX(_xlpm.sortedPairs,ROW()-1,1),"")),"")} | M3: {=IFERROR(_xlfn.LET(_xlpm.pairs,_xlfn._xlws.FILTER($A$2:$D$391,($A$2:$A$391<>"")*(TRIM($D$2:$D$391)<>"")),_xlpm.uniquePairs,_xlfn.UNIQUE(_xlfn.HSTACK(INDEX(_xlpm.pairs,,1),INDEX(_xlpm.pairs,,4))),_xlpm.sortedPairs,_xlfn._xlws.SORT(_xlpm.uniquePairs,1,1),IF(ROW()-1<=ROWS(_xlpm.sortedPairs),INDEX(_xlpm.sortedPairs,ROW()-1,2),"")),"")} | N3: {=IF(OR(L3="",M3=""),"",IFERROR(INDEX($E$2:$E$391,MATCH(1,($A$2:$A$391=L3)*($D$2:$D$391=M3),0)),""))} | O3: =IF(OR(L3="",M3=""),"",SUMIFS($J$2:$J$391,$A$2:$A$391,L3,$D$2:$D$391,M3)) | Q3: {=IFERROR(INDEX($L$2:$L$391,MATCH(0,COUNTIF($Q$1:Q2,$L$2:$L$391)+IF($L$2:$L$391="",1,0),0)),"")} | R3: =IF(Q3="","",SUMIF($L$2:$L$391,Q3,$O$2:$O$391)) | S3: =IFERROR(Table3[[#This Row],[Price (€/kg)]]*HELPER!$AK$2," ")
A4: TIPA 302FG | B4: Ext. A (Out - Chillroll) | C4: AB-PLA | D4: =IF(C4="","",IFERROR(_xlfn.XLOOKUP(C4,HELPER!$A$2:$A$76,HELPER!$B$2:$B$76,""),D4)) | E4: =IFERROR(_xlfn.XLOOKUP(D4,HELPER!$B:$B,HELPER!$C:$C,""),"") | F4: =IFERROR(_xlfn.XLOOKUP(D4,HELPER!$B:$B,HELPER!$D:$D,""),"") | G4: 8 | H4: 0.015 | I4: =IF(AND(H4<>"",IFERROR(_xlfn.XLOOKUP(D4,HELPER!$B:$B,HELPER!$E:$E,""),"")=""),"Missing price",IFERROR(_xlfn.XLOOKUP(D4,HELPER!$B:$B,HELPER!$E:$E,"")," ")) | J4: =IFERROR(H4*(IF(G4=8,I4*HELPER!$G$2,BOM!I4*HELPER!$G$3))," ") | L4: {=IFERROR(_xlfn.LET(_xlpm.pairs,_xlfn._xlws.FILTER($A$2:$D$391,($A$2:$A$391<>"")*(TRIM($D$2:$D$391)<>"")),_xlpm.uniquePairs,_xlfn.UNIQUE(_xlfn.HSTACK(INDEX(_xlpm.pairs,,1),INDEX(_xlpm.pairs,,4))),_xlpm.sortedPairs,_xlfn._xlws.SORT(_xlpm.uniquePairs,1,1),IF(ROW()-1<=ROWS(_xlpm.sortedPairs),INDEX(_xlpm.sortedPairs,ROW()-1,1),"")),"")} | M4: {=IFERROR(_xlfn.LET(_xlpm.pairs,_xlfn._xlws.FILTER($A$2:$D$391,($A$2:$A$391<>"")*(TRIM($D$2:$D$391)<>"")),_xlpm.uniquePairs,_xlfn.UNIQUE(_xlfn.HSTACK(INDEX(_xlpm.pairs,,1),INDEX(_xlpm.pairs,,4))),_xlpm.sortedPairs,_xlfn._xlws.SORT(_xlpm.uniquePairs,1,1),IF(ROW()-1<=ROWS(_xlpm.sortedPairs),INDEX(_xlpm.sortedPairs,ROW()-1,2),"")),"")} | N4: {=IF(OR(L4="",M4=""),"",IFERROR(INDEX($E$2:$E$391,MATCH(1,($A$2:$A$391=L4)*($D$2:$D$391=M4),0)),""))} | O4: =IF(OR(L4="",M4=""),"",SUMIFS($J$2:$J$391,$A$2:$A$391,L4,$D$2:$D$391,M4)) | Q4: {=IFERROR(INDEX($L$2:$L$391,MATCH(0,COUNTIF($Q$1:Q3,$L$2:$L$391)+IF($L$2:$L$391="",1,0),0)),"")} | R4: =IF(Q4="","",SUMIF($L$2:$L$391,Q4,$O$2:$O$391)) | S4: =IFERROR(Table3[[#This Row],[Price (€/kg)]]*HELPER!$AK$2," ")
A5: TIPA 302FG | B5: Ext. A (Out - Chillroll) | C5: AO-PBS | D5: =IF(C5="","",IFERROR(_xlfn.XLOOKUP(C5,HELPER!$A$2:$A$76,HELPER!$B$2:$B$76,""),D5)) | E5: =IFERROR(_xlfn.XLOOKUP(D5,HELPER!$B:$B,HELPER!$C:$C,""),"") | F5: =IFERROR(_xlfn.XLOOKUP(D5,HELPER!$B:$B,HELPER!$D:$D,""),"") | G5: 8 | H5: 0.015 | I5: =IF(AND(H5<>"",IFERROR(_xlfn.XLOOKUP(D5,HELPER!$B:$B,HELPER!$E:$E,""),"")=""),"Missing price",IFERROR(_xlfn.XLOOKUP(D5,HELPER!$B:$B,HELPER!$E:$E,"")," ")) | J5: =IFERROR(H5*(IF(G5=8,I5*HELPER!$G$2,BOM!I5*HELPER!$G$3))," ") | L5: {=IFERROR(_xlfn.LET(_xlpm.pairs,_xlfn._xlws.FILTER($A$2:$D$391,($A$2:$A$391<>"")*(TRIM($D$2:$D$391)<>"")),_xlpm.uniquePairs,_xlfn.UNIQUE(_xlfn.HSTACK(INDEX(_xlpm.pairs,,1),INDEX(_xlpm.pairs,,4))),_xlpm.sortedPairs,_xlfn._xlws.SORT(_xlpm.uniquePairs,1,1),IF(ROW()-1<=ROWS(_xlpm.sortedPairs),INDEX(_xlpm.sortedPairs,ROW()-1,1),"")),"")} | M5: {=IFERROR(_xlfn.LET(_xlpm.pairs,_xlfn._xlws.FILTER($A$2:$D$391,($A$2:$A$391<>"")*(TRIM($D$2:$D$391)<>"")),_xlpm.uniquePairs,_xlfn.UNIQUE(_xlfn.HSTACK(INDEX(_xlpm.pairs,,1),INDEX(_xlpm.pairs,,4))),_xlpm.sortedPairs,_xlfn._xlws.SORT(_xlpm.uniquePairs,1,1),IF(ROW()-1<=ROWS(_xlpm.sortedPairs),INDEX(_xlpm.sortedPairs,ROW()-1,2),"")),"")} | N5: {=IF(OR(L5="",M5=""),"",IFERROR(INDEX($E$2:$E$391,MATCH(1,($A$2:$A$391=L5)*($D$2:$D$391=M5),0)),""))} | O5: =IF(OR(L5="",M5=""),"",SUMIFS($J$2:$J$391,$A$2:$A$391,L5,$D$2:$D$391,M5)) | Q5: {=IFERROR(INDEX($L$2:$L$391,MATCH(0,COUNTIF($Q$1:Q4,$L$2:$L$391)+IF($L$2:$L$391="",1,0),0)),"")} | R5: =IF(Q5="","",SUMIF($L$2:$L$391,Q5,$O$2:$O$391)) | S5: =IFERROR(Table3[[#This Row],[Price (€/kg)]]*HELPER!$AK$2," ")
A6: TIPA 302FG | B6: Ext. A (Out - Chillroll) | D6: =IF(C6="","",IFERROR(_xlfn.XLOOKUP(C6,HELPER!$A$2:$A$76,HELPER!$B$2:$B$76,""),D6)) | E6: =IFERROR(_xlfn.XLOOKUP(D6,HELPER!$B:$B,HELPER!$C:$C,""),"") | F6: =IFERROR(_xlfn.XLOOKUP(D6,HELPER!$B:$B,HELPER!$D:$D,""),"") | G6: 8 | I6: =IF(AND(H6<>"",IFERROR(_xlfn.XLOOKUP(D6,HELPER!$B:$B,HELPER!$E:$E,""),"")=""),"Missing price",IFERROR(_xlfn.XLOOKUP(D6,HELPER!$B:$B,HELPER!$E:$E,"")," ")) | J6: =IFERROR(H6*(IF(G6=8,I6*HELPER!$G$2,BOM!I6*HELPER!$G$3))," ") | L6: {=IFERROR(_xlfn.LET(_xlpm.pairs,_xlfn._xlws.FILTER($A$2:$D$391,($A$2:$A$391<>"")*(TRIM($D$2:$D$391)<>"")),_xlpm.uniquePairs,_xlfn.UNIQUE(_xlfn.HSTACK(INDEX(_xlpm.pairs,,1),INDEX(_xlpm.pairs,,4))),_xlpm.sortedPairs,_xlfn._xlws.SORT(_xlpm.uniquePairs,1,1),IF(ROW()-1<=ROWS(_xlpm.sortedPairs),INDEX(_xlpm.sortedPairs,ROW()-1,1),"")),"")} | M6: {=IFERROR(_xlfn.LET(_xlpm.pairs,_xlfn._xlws.FILTER($A$2:$D$391,($A$2:$A$391<>"")*(TRIM($D$2:$D$391)<>"")),_xlpm.uniquePairs,_xlfn.UNIQUE(_xlfn.HSTACK(INDEX(_xlpm.pairs,,1),INDEX(_xlpm.pairs,,4))),_xlpm.sortedPairs,_xlfn._xlws.SORT(_xlpm.uniquePairs,1,1),IF(ROW()-1<=ROWS(_xlpm.sortedPairs),INDEX(_xlpm.sortedPairs,ROW()-1,2),"")),"")} | N6: {=IF(OR(L6="",M6=""),"",IFERROR(INDEX($E$2:$E$391,MATCH(1,($A$2:$A$391=L6)*($D$2:$D$391=M6),0)),""))} | O6: =IF(OR(L6="",M6=""),"",SUMIFS($J$2:$J$391,$A$2:$A$391,L6,$D$2:$D$391,M6)) | Q6: {=IFERROR(INDEX($L$2:$L$391,MATCH(0,COUNTIF($Q$1:Q5,$L$2:$L$391)+IF($L$2:$L$391="",1,0),0)),"")} | R6: =IF(Q6="","",SUMIF($L$2:$L$391,Q6,$O$2:$O$391)) | S6: =IFERROR(Table3[[#This Row],[Price (€/kg)]]*HELPER!$AK$2," ")
A7: TIPA 302FG | B7: Ext. A (Out - Chillroll) | D7: =IF(C7="","",IFERROR(_xlfn.XLOOKUP(C7,HELPER!$A$2:$A$76,HELPER!$B$2:$B$76,""),D7)) | E7: =IFERROR(_xlfn.XLOOKUP(D7,HELPER!$B:$B,HELPER!$C:$C,""),"") | F7: =IFERROR(_xlfn.XLOOKUP(D7,HELPER!$B:$B,HELPER!$D:$D,""),"") | G7: 8 | I7: =IF(AND(H7<>"",IFERROR(_xlfn.XLOOKUP(D7,HELPER!$B:$B,HELPER!$E:$E,""),"")=""),"Missing price",IFERROR(_xlfn.XLOOKUP(D7,HELPER!$B:$B,HELPER!$E:$E,"")," ")) | J7: =IFERROR(H7*(IF(G7=8,I7*HELPER!$G$2,BOM!I7*HELPER!$G$3))," ") | L7: {=IFERROR(_xlfn.LET(_xlpm.pairs,_xlfn._xlws.FILTER($A$2:$D$391,($A$2:$A$391<>"")*(TRIM($D$2:$D$391)<>"")),_xlpm.uniquePairs,_xlfn.UNIQUE(_xlfn.HSTACK(INDEX(_xlpm.pairs,,1),INDEX(_xlpm.pairs,,4))),_xlpm.sortedPairs,_xlfn._xlws.SORT(_xlpm.uniquePairs,1,1),IF(ROW()-1<=ROWS(_xlpm.sortedPairs),INDEX(_xlpm.sortedPairs,ROW()-1,1),"")),"")} | M7: {=IFERROR(_xlfn.LET(_xlpm.pairs,_xlfn._xlws.FILTER($A$2:$D$391,($A$2:$A$391<>"")*(TRIM($D$2:$D$391)<>"")),_xlpm.uniquePairs,_xlfn.UNIQUE(_xlfn.HSTACK(INDEX(_xlpm.pairs,,1),INDEX(_xlpm.pairs,,4))),_xlpm.sortedPairs,_xlfn._xlws.SORT(_xlpm.uniquePairs,1,1),IF(ROW()-1<=ROWS(_xlpm.sortedPairs),INDEX(_xlpm.sortedPairs,ROW()-1,2),"")),"")} | N7: {=IF(OR(L7="",M7=""),"",IFERROR(INDEX($E$2:$E$391,MATCH(1,($A$2:$A$391=L7)*($D$2:$D$391=M7),0)),""))} | O7: =IF(OR(L7="",M7=""),"",SUMIFS($J$2:$J$391,$A$2:$A$391,L7,$D$2:$D$391,M7)) | Q7: {=IFERROR(INDEX($L$2:$L$391,MATCH(0,COUNTIF($Q$1:Q6,$L$2:$L$391)+IF($L$2:$L$391="",1,0),0)),"")} | R7: =IF(Q7="","",SUMIF($L$2:$L$391,Q7,$O$2:$O$391)) | S7: =IFERROR(Table3[[#This Row],[Price (€/kg)]]*HELPER!$AK$2," ")
A8: TIPA 302FG | B8: Ext. A (Out - Chillroll) | D8: =IF(C8="","",IFERROR(_xlfn.XLOOKUP(C8,HELPER!$A$2:$A$76,HELPER!$B$2:$B$76,""),D8)) | E8: =IFERROR(_xlfn.XLOOKUP(D8,HELPER!$B:$B,HELPER!$C:$C,""),"") | F8: =IFERROR(_xlfn.XLOOKUP(D8,HELPER!$B:$B,HELPER!$D:$D,""),"") | G8: 8 | I8: =IF(AND(H8<>"",IFERROR(_xlfn.XLOOKUP(D8,HELPER!$B:$B,HELPER!$E:$E,""),"")=""),"Missing price",IFERROR(_xlfn.XLOOKUP(D8,HELPER!$B:$B,HELPER!$E:$E,"")," ")) | J8: =IFERROR(H8*(IF(G8=8,I8*HELPER!$G$2,BOM!I8*HELPER!$G$3))," ") | L8: {=IFERROR(_xlfn.LET(_xlpm.pairs,_xlfn._xlws.FILTER($A$2:$D$391,($A$2:$A$391<>"")*(TRIM($D$2:$D$391)<>"")),_xlpm.uniquePairs,_xlfn.UNIQUE(_xlfn.HSTACK(INDEX(_xlpm.pairs,,1),INDEX(_xlpm.pairs,,4))),_xlpm.sortedPairs,_xlfn._xlws.SORT(_xlpm.uniquePairs,1,1),IF(ROW()-1<=ROWS(_xlpm.sortedPairs),INDEX(_xlpm.sortedPairs,ROW()-1,1),"")),"")} | M8: {=IFERROR(_xlfn.LET(_xlpm.pairs,_xlfn._xlws.FILTER($A$2:$D$391,($A$2:$A$391<>"")*(TRIM($D$2:$D$391)<>"")),_xlpm.uniquePairs,_xlfn.UNIQUE(_xlfn.HSTACK(INDEX(_xlpm.pairs,,1),INDEX(_xlpm.pairs,,4))),_xlpm.sortedPairs,_xlfn._xlws.SORT(_xlpm.uniquePairs,1,1),IF(ROW()-1<=ROWS(_xlpm.sortedPairs),INDEX(_xlpm.sortedPairs,ROW()-1,2),"")),"")} | N8: {=IF(OR(L8="",M8=""),"",IFERROR(INDEX($E$2:$E$391,MATCH(1,($A$2:$A$391=L8)*($D$2:$D$391=M8),0)),""))} | O8: =IF(OR(L8="",M8=""),"",SUMIFS($J$2:$J$391,$A$2:$A$391,L8,$D$2:$D$391,M8)) | Q8: {=IFERROR(INDEX($L$2:$L$391,MATCH(0,COUNTIF($Q$1:Q7,$L$2:$L$391)+IF($L$2:$L$391="",1,0),0)),"")} | R8: =IF(Q8="","",SUMIF($L$2:$L$391,Q8,$O$2:$O$391)) | S8: =IFERROR(Table3[[#This Row],[Price (€/kg)]]*HELPER!$AK$2," ")
A9: TIPA 302FG | B9: Ext. A (Out - Chillroll) | D9: =IF(C9="","",IFERROR(_xlfn.XLOOKUP(C9,HELPER!$A$2:$A$76,HELPER!$B$2:$B$76,""),D9)) | E9: =IFERROR(_xlfn.XLOOKUP(D9,HELPER!$B:$B,HELPER!$C:$C,""),"") | F9: =IFERROR(_xlfn.XLOOKUP(D9,HELPER!$B:$B,HELPER!$D:$D,""),"") | G9: 8 | I9: =IF(AND(H9<>"",IFERROR(_xlfn.XLOOKUP(D9,HELPER!$B:$B,HELPER!$E:$E,""),"")=""),"Missing price",IFERROR(_xlfn.XLOOKUP(D9,HELPER!$B:$B,HELPER!$E:$E,"")," ")) | J9: =IFERROR(H9*(IF(G9=8,I9*HELPER!$G$2,BOM!I9*HELPER!$G$3))," ") | L9: {=IFERROR(_xlfn.LET(_xlpm.pairs,_xlfn._xlws.FILTER($A$2:$D$391,($A$2:$A$391<>"")*(TRIM($D$2:$D$391)<>"")),_xlpm.uniquePairs,_xlfn.UNIQUE(_xlfn.HSTACK(INDEX(_xlpm.pairs,,1),INDEX(_xlpm.pairs,,4))),_xlpm.sortedPairs,_xlfn._xlws.SORT(_xlpm.uniquePairs,1,1),IF(ROW()-1<=ROWS(_xlpm.sortedPairs),INDEX(_xlpm.sortedPairs,ROW()-1,1),"")),"")} | M9: {=IFERROR(_xlfn.LET(_xlpm.pairs,_xlfn._xlws.FILTER($A$2:$D$391,($A$2:$A$391<>"")*(TRIM($D$2:$D$391)<>"")),_xlpm.uniquePairs,_xlfn.UNIQUE(_xlfn.HSTACK(INDEX(_xlpm.pairs,,1),INDEX(_xlpm.pairs,,4))),_xlpm.sortedPairs,_xlfn._xlws.SORT(_xlpm.uniquePairs,1,1),IF(ROW()-1<=ROWS(_xlpm.sortedPairs),INDEX(_xlpm.sortedPairs,ROW()-1,2),"")),"")} | N9: {=IF(OR(L9="",M9=""),"",IFERROR(INDEX($E$2:$E$391,MATCH(1,($A$2:$A$391=L9)*($D$2:$D$391=M9),0)),""))} | O9: =IF(OR(L9="",M9=""),"",SUMIFS($J$2:$J$391,$A$2:$A$391,L9,$D$2:$D$391,M9)) | Q9: {=IFERROR(INDEX($L$2:$L$391,MATCH(0,COUNTIF($Q$1:Q8,$L$2:$L$391)+IF($L$2:$L$391="",1,0),0)),"")} | R9: =IF(Q9="","",SUMIF($L$2:$L$391,Q9,$O$2:$O$391)) | S9: =IFERROR(Table3[[#This Row],[Price (€/kg)]]*HELPER!$AK$2," ")
A10: TIPA 302FG | B10: Ext. A (Out - Chillroll) | D10: =IF(C10="","",IFERROR(_xlfn.XLOOKUP(C10,HELPER!$A$2:$A$76,HELPER!$B$2:$B$76,""),D10)) | E10: =IFERROR(_xlfn.XLOOKUP(D10,HELPER!$B:$B,HELPER!$C:$C,""),"") | F10: =IFERROR(_xlfn.XLOOKUP(D10,HELPER!$B:$B,HELPER!$D:$D,""),"") | G10: 8 | I10: =IF(AND(H10<>"",IFERROR(_xlfn.XLOOKUP(D10,HELPER!$B:$B,HELPER!$E:$E,""),"")=""),"Missing price",IFERROR(_xlfn.XLOOKUP(D10,HELPER!$B:$B,HELPER!$E:$E,"")," ")) | J10: =IFERROR(H10*(IF(G10=8,I10*HELPER!$G$2,BOM!I10*HELPER!$G$3))," ") | L10: {=IFERROR(_xlfn.LET(_xlpm.pairs,_xlfn._xlws.FILTER($A$2:$D$391,($A$2:$A$391<>"")*(TRIM($D$2:$D$391)<>"")),_xlpm.uniquePairs,_xlfn.UNIQUE(_xlfn.HSTACK(INDEX(_xlpm.pairs,,1),INDEX(_xlpm.pairs,,4))),_xlpm.sortedPairs,_xlfn._xlws.SORT(_xlpm.uniquePairs,1,1),IF(ROW()-1<=ROWS(_xlpm.sortedPairs),INDEX(_xlpm.sortedPairs,ROW()-1,1),"")),"")} | M10: {=IFERROR(_xlfn.LET(_xlpm.pairs,_xlfn._xlws.FILTER($A$2:$D$391,($A$2:$A$391<>"")*(TRIM($D$2:$D$391)<>"")),_xlpm.uniquePairs,_xlfn.UNIQUE(_xlfn.HSTACK(INDEX(_xlpm.pairs,,1),INDEX(_xlpm.pairs,,4))),_xlpm.sortedPairs,_xlfn._xlws.SORT(_xlpm.uniquePairs,1,1),IF(ROW()-1<=ROWS(_xlpm.sortedPairs),INDEX(_xlpm.sortedPairs,ROW()-1,2),"")),"")} | N10: {=IF(OR(L10="",M10=""),"",IFERROR(INDEX($E$2:$E$391,MATCH(1,($A$2:$A$391=L10)*($D$2:$D$391=M10),0)),""))} | O10: =IF(OR(L10="",M10=""),"",SUMIFS($J$2:$J$391,$A$2:$A$391,L10,$D$2:$D$391,M10)) | Q10: {=IFERROR(INDEX($L$2:$L$391,MATCH(0,COUNTIF($Q$1:Q9,$L$2:$L$391)+IF($L$2:$L$391="",1,0),0)),"")} | R10: =IF(Q10="","",SUMIF($L$2:$L$391,Q10,$O$2:$O$391)) | S10: =IFERROR(Table3[[#This Row],[Price (€/kg)]]*HELPER!$AK$2," ")
A11: TIPA 302FG | B11: Ext. A (Out - Chillroll) | D11: =IF(C11="","",IFERROR(_xlfn.XLOOKUP(C11,HELPER!$A$2:$A$76,HELPER!$B$2:$B$76,""),D11)) | E11: =IFERROR(_xlfn.XLOOKUP(D11,HELPER!$B:$B,HELPER!$C:$C,""),"") | F11: =IFERROR(_xlfn.XLOOKUP(D11,HELPER!$B:$B,HELPER!$D:$D,""),"") | G11: 8 | I11: =IF(AND(H11<>"",IFERROR(_xlfn.XLOOKUP(D11,HELPER!$B:$B,HELPER!$E:$E,""),"")=""),"Missing price",IFERROR(_xlfn.XLOOKUP(D11,HELPER!$B:$B,HELPER!$E:$E,"")," ")) | J11: =IFERROR(H11*(IF(G11=8,I11*HELPER!$G$2,BOM!I11*HELPER!$G$3))," ") | L11: {=IFERROR(_xlfn.LET(_xlpm.pairs,_xlfn._xlws.FILTER($A$2:$D$391,($A$2:$A$391<>"")*(TRIM($D$2:$D$391)<>"")),_xlpm.uniquePairs,_xlfn.UNIQUE(_xlfn.HSTACK(INDEX(_xlpm.pairs,,1),INDEX(_xlpm.pairs,,4))),_xlpm.sortedPairs,_xlfn._xlws.SORT(_xlpm.uniquePairs,1,1),IF(ROW()-1<=ROWS(_xlpm.sortedPairs),INDEX(_xlpm.sortedPairs,ROW()-1,1),"")),"")} | M11: {=IFERROR(_xlfn.LET(_xlpm.pairs,_xlfn._xlws.FILTER($A$2:$D$391,($A$2:$A$391<>"")*(TRIM($D$2:$D$391)<>"")),_xlpm.uniquePairs,_xlfn.UNIQUE(_xlfn.HSTACK(INDEX(_xlpm.pairs,,1),INDEX(_xlpm.pairs,,4))),_xlpm.sortedPairs,_xlfn._xlws.SORT(_xlpm.uniquePairs,1,1),IF(ROW()-1<=ROWS(_xlpm.sortedPairs),INDEX(_xlpm.sortedPairs,ROW()-1,2),"")),"")} | N11: {=IF(OR(L11="",M11=""),"",IFERROR(INDEX($E$2:$E$391,MATCH(1,($A$2:$A$391=L11)*($D$2:$D$391=M11),0)),""))} | O11: =IF(OR(L11="",M11=""),"",SUMIFS($J$2:$J$391,$A$2:$A$391,L11,$D$2:$D$391,M11)) | Q11: {=IFERROR(INDEX($L$2:$L$391,MATCH(0,COUNTIF($Q$1:Q10,$L$2:$L$391)+IF($L$2:$L$391="",1,0),0)),"")} | R11: =IF(Q11="","",SUMIF($L$2:$L$391,Q11,$O$2:$O$391)) | S11: =IFERROR(Table3[[#This Row],[Price (€/kg)]]*HELPER!$AK$2," ")
A12: TIPA 302FG | B12: Ext. B | D12: =IF(C12="","",IFERROR(_xlfn.XLOOKUP(C12,HELPER!$A$2:$A$76,HELPER!$B$2:$B$76,""),D12)) | E12: =IFERROR(_xlfn.XLOOKUP(D12,HELPER!$B:$B,HELPER!$C:$C,""),"") | F12: =IFERROR(_xlfn.XLOOKUP(D12,HELPER!$B:$B,HELPER!$D:$D,""),"") | G12: 8 | I12: =IF(AND(H12<>"",IFERROR(_xlfn.XLOOKUP(D12,HELPER!$B:$B,HELPER!$E:$E,""),"")=""),"Missing price",IFERROR(_xlfn.XLOOKUP(D12,HELPER!$B:$B,HELPER!$E:$E,"")," ")) | J12: =IFERROR(H12*(IF(G12=8,I12*HELPER!$G$2,BOM!I12*HELPER!$G$3))," ") | L12: {=IFERROR(_xlfn.LET(_xlpm.pairs,_xlfn._xlws.FILTER($A$2:$D$391,($A$2:$A$391<>"")*(TRIM($D$2:$D$391)<>"")),_xlpm.uniquePairs,_xlfn.UNIQUE(_xlfn.HSTACK(INDEX(_xlpm.pairs,,1),INDEX(_xlpm.pairs,,4))),_xlpm.sortedPairs,_xlfn._xlws.SORT(_xlpm.uniquePairs,1,1),IF(ROW()-1<=ROWS(_xlpm.sortedPairs),INDEX(_xlpm.sortedPairs,ROW()-1,1),"")),"")} | M12: {=IFERROR(_xlfn.LET(_xlpm.pairs,_xlfn._xlws.FILTER($A$2:$D$391,($A$2:$A$391<>"")*(TRIM($D$2:$D$391)<>"")),_xlpm.uniquePairs,_xlfn.UNIQUE(_xlfn.HSTACK(INDEX(_xlpm.pairs,,1),INDEX(_xlpm.pairs,,4))),_xlpm.sortedPairs,_xlfn._xlws.SORT(_xlpm.uniquePairs,1,1),IF(ROW()-1<=ROWS(_xlpm.sortedPairs),INDEX(_xlpm.sortedPairs,ROW()-1,2),"")),"")} | N12: {=IF(OR(L12="",M12=""),"",IFERROR(INDEX($E$2:$E$391,MATCH(1,($A$2:$A$391=L12)*($D$2:$D$391=M12),0)),""))} | O12: =IF(OR(L12="",M12=""),"",SUMIFS($J$2:$J$391,$A$2:$A$391,L12,$D$2:$D$391,M12)) | Q12: {=IFERROR(INDEX($L$2:$L$391,MATCH(0,COUNTIF($Q$1:Q11,$L$2:$L$391)+IF($L$2:$L$391="",1,0),0)),"")} | R12: =IF(Q12="","",SUMIF($L$2:$L$391,Q12,$O$2:$O$391)) | S12: =IFERROR(Table3[[#This Row],[Price (€/kg)]]*HELPER!$AK$2," ")
A13: TIPA 302FG | B13: Ext. B | D13: =IF(C13="","",IFERROR(_xlfn.XLOOKUP(C13,HELPER!$A$2:$A$76,HELPER!$B$2:$B$76,""),D13)) | E13: =IFERROR(_xlfn.XLOOKUP(D13,HELPER!$B:$B,HELPER!$C:$C,""),"") | F13: =IFERROR(_xlfn.XLOOKUP(D13,HELPER!$B:$B,HELPER!$D:$D,""),"") | G13: 24 | I13: =IF(AND(H13<>"",IFERROR(_xlfn.XLOOKUP(D13,HELPER!$B:$B,HELPER!$E:$E,""),"")=""),"Missing price",IFERROR(_xlfn.XLOOKUP(D13,HELPER!$B:$B,HELPER!$E:$E,"")," ")) | J13: =IFERROR(H13*(IF(G13=8,I13*HELPER!$G$2,BOM!I13*HELPER!$G$3))," ") | L13: {=IFERROR(_xlfn.LET(_xlpm.pairs,_xlfn._xlws.FILTER($A$2:$D$391,($A$2:$A$391<>"")*(TRIM($D$2:$D$391)<>"")),_xlpm.uniquePairs,_xlfn.UNIQUE(_xlfn.HSTACK(INDEX(_xlpm.pairs,,1),INDEX(_xlpm.pairs,,4))),_xlpm.sortedPairs,_xlfn._xlws.SORT(_xlpm.uniquePairs,1,1),IF(ROW()-1<=ROWS(_xlpm.sortedPairs),INDEX(_xlpm.sortedPairs,ROW()-1,1),"")),"")} | M13: {=IFERROR(_xlfn.LET(_xlpm.pairs,_xlfn._xlws.FILTER($A$2:$D$391,($A$2:$A$391<>"")*(TRIM($D$2:$D$391)<>"")),_xlpm.uniquePairs,_xlfn.UNIQUE(_xlfn.HSTACK(INDEX(_xlpm.pairs,,1),INDEX(_xlpm.pairs,,4))),_xlpm.sortedPairs,_xlfn._xlws.SORT(_xlpm.uniquePairs,1,1),IF(ROW()-1<=ROWS(_xlpm.sortedPairs),INDEX(_xlpm.sortedPairs,ROW()-1,2),"")),"")} | N13: {=IF(OR(L13="",M13=""),"",IFERROR(INDEX($E$2:$E$391,MATCH(1,($A$2:$A$391=L13)*($D$2:$D$391=M13),0)),""))} | O13: =IF(OR(L13="",M13=""),"",SUMIFS($J$2:$J$391,$A$2:$A$391,L13,$D$2:$D$391,M13)) | Q13: {=IFERROR(INDEX($L$2:$L$391,MATCH(0,COUNTIF($Q$1:Q12,$L$2:$L$391)+IF($L$2:$L$391="",1,0),0)),"")} | R13: =IF(Q13="","",SUMIF($L$2:$L$391,Q13,$O$2:$O$391)) | S13: =IFERROR(Table3[[#This Row],[Price (€/kg)]]*HELPER!$AK$2," ")
A14: TIPA 302FG | B14: Ext. B | D14: =IF(C14="","",IFERROR(_xlfn.XLOOKUP(C14,HELPER!$A$2:$A$76,HELPER!$B$2:$B$76,""),D14)) | E14: =IFERROR(_xlfn.XLOOKUP(D14,HELPER!$B:$B,HELPER!$C:$C,""),"") | F14: =IFERROR(_xlfn.XLOOKUP(D14,HELPER!$B:$B,HELPER!$D:$D,""),"") | G14: 24 | I14: =IF(AND(H14<>"",IFERROR(_xlfn.XLOOKUP(D14,HELPER!$B:$B,HELPER!$E:$E,""),"")=""),"Missing price",IFERROR(_xlfn.XLOOKUP(D14,HELPER!$B:$B,HELPER!$E:$E,"")," ")) | J14: =IFERROR(H14*(IF(G14=8,I14*HELPER!$G$2,BOM!I14*HELPER!$G$3))," ") | L14: {=IFERROR(_xlfn.LET(_xlpm.pairs,_xlfn._xlws.FILTER($A$2:$D$391,($A$2:$A$391<>"")*(TRIM($D$2:$D$391)<>"")),_xlpm.uniquePairs,_xlfn.UNIQUE(_xlfn.HSTACK(INDEX(_xlpm.pairs,,1),INDEX(_xlpm.pairs,,4))),_xlpm.sortedPairs,_xlfn._xlws.SORT(_xlpm.uniquePairs,1,1),IF(ROW()-1<=ROWS(_xlpm.sortedPairs),INDEX(_xlpm.sortedPairs,ROW()-1,1),"")),"")} | M14: {=IFERROR(_xlfn.LET(_xlpm.pairs,_xlfn._xlws.FILTER($A$2:$D$391,($A$2:$A$391<>"")*(TRIM($D$2:$D$391)<>"")),_xlpm.uniquePairs,_xlfn.UNIQUE(_xlfn.HSTACK(INDEX(_xlpm.pairs,,1),INDEX(_xlpm.pairs,,4))),_xlpm.sortedPairs,_xlfn._xlws.SORT(_xlpm.uniquePairs,1,1),IF(ROW()-1<=ROWS(_xlpm.sortedPairs),INDEX(_xlpm.sortedPairs,ROW()-1,2),"")),"")} | N14: {=IF(OR(L14="",M14=""),"",IFERROR(INDEX($E$2:$E$391,MATCH(1,($A$2:$A$391=L14)*($D$2:$D$391=M14),0)),""))} | O14: =IF(OR(L14="",M14=""),"",SUMIFS($J$2:$J$391,$A$2:$A$391,L14,$D$2:$D$391,M14)) | Q14: {=IFERROR(INDEX($L$2:$L$391,MATCH(0,COUNTIF($Q$1:Q13,$L$2:$L$391)+IF($L$2:$L$391="",1,0),0)),"")} | R14: =IF(Q14="","",SUMIF($L$2:$L$391,Q14,$O$2:$O$391)) | S14: =IFERROR(Table3[[#This Row],[Price (€/kg)]]*HELPER!$AK$2," ")
A15: TIPA 302FG | B15: Ext. B | D15: =IF(C15="","",IFERROR(_xlfn.XLOOKUP(C15,HELPER!$A$2:$A$76,HELPER!$B$2:$B$76,""),D15)) | E15: =IFERROR(_xlfn.XLOOKUP(D15,HELPER!$B:$B,HELPER!$C:$C,""),"") | F15: =IFERROR(_xlfn.XLOOKUP(D15,HELPER!$B:$B,HELPER!$D:$D,""),"") | G15: 24 | I15: =IF(AND(H15<>"",IFERROR(_xlfn.XLOOKUP(D15,HELPER!$B:$B,HELPER!$E:$E,""),"")=""),"Missing price",IFERROR(_xlfn.XLOOKUP(D15,HELPER!$B:$B,HELPER!$E:$E,"")," ")) | J15: =IFERROR(H15*(IF(G15=8,I15*HELPER!$G$2,BOM!I15*HELPER!$G$3))," ") | L15: {=IFERROR(_xlfn.LET(_xlpm.pairs,_xlfn._xlws.FILTER($A$2:$D$391,($A$2:$A$391<>"")*(TRIM($D$2:$D$391)<>"")),_xlpm.uniquePairs,_xlfn.UNIQUE(_xlfn.HSTACK(INDEX(_xlpm.pairs,,1),INDEX(_xlpm.pairs,,4))),_xlpm.sortedPairs,_xlfn._xlws.SORT(_xlpm.uniquePairs,1,1),IF(ROW()-1<=ROWS(_xlpm.sortedPairs),INDEX(_xlpm.sortedPairs,ROW()-1,1),"")),"")} | M15: {=IFERROR(_xlfn.LET(_xlpm.pairs,_xlfn._xlws.FILTER($A$2:$D$391,($A$2:$A$391<>"")*(TRIM($D$2:$D$391)<>"")),_xlpm.uniquePairs,_xlfn.UNIQUE(_xlfn.HSTACK(INDEX(_xlpm.pairs,,1),INDEX(_xlpm.pairs,,4))),_xlpm.sortedPairs,_xlfn._xlws.SORT(_xlpm.uniquePairs,1,1),IF(ROW()-1<=ROWS(_xlpm.sortedPairs),INDEX(_xlpm.sortedPairs,ROW()-1,2),"")),"")} | N15: {=IF(OR(L15="",M15=""),"",IFERROR(INDEX($E$2:$E$391,MATCH(1,($A$2:$A$391=L15)*($D$2:$D$391=M15),0)),""))} | O15: =IF(OR(L15="",M15=""),"",SUMIFS($J$2:$J$391,$A$2:$A$391,L15,$D$2:$D$391,M15)) | Q15: {=IFERROR(INDEX($L$2:$L$391,MATCH(0,COUNTIF($Q$1:Q14,$L$2:$L$391)+IF($L$2:$L$391="",1,0),0)),"")} | R15: =IF(Q15="","",SUMIF($L$2:$L$391,Q15,$O$2:$O$391)) | S15: =IFERROR(Table3[[#This Row],[Price (€/kg)]]*HELPER!$AK$2," ")
A16: TIPA 302FG | B16: Ext. B | C16: AO-PBS | D16: =IF(C16="","",IFERROR(_xlfn.XLOOKUP(C16,HELPER!$A$2:$A$76,HELPER!$B$2:$B$76,""),D16)) | E16: =IFERROR(_xlfn.XLOOKUP(D16,HELPER!$B:$B,HELPER!$C:$C,""),"") | F16: =IFERROR(_xlfn.XLOOKUP(D16,HELPER!$B:$B,HELPER!$D:$D,""),"") | G16: 24 | H16: 0.015 | I16: =IF(AND(H16<>"",IFERROR(_xlfn.XLOOKUP(D16,HELPER!$B:$B,HELPER!$E:$E,""),"")=""),"Missing price",IFERROR(_xlfn.XLOOKUP(D16,HELPER!$B:$B,HELPER!$E:$E,"")," ")) | J16: =IFERROR(H16*(IF(G16=8,I16*HELPER!$G$2,BOM!I16*HELPER!$G$3))," ") | L16: {=IFERROR(_xlfn.LET(_xlpm.pairs,_xlfn._xlws.FILTER($A$2:$D$391,($A$2:$A$391<>"")*(TRIM($D$2:$D$391)<>"")),_xlpm.uniquePairs,_xlfn.UNIQUE(_xlfn.HSTACK(INDEX(_xlpm.pairs,,1),INDEX(_xlpm.pairs,,4))),_xlpm.sortedPairs,_xlfn._xlws.SORT(_xlpm.uniquePairs,1,1),IF(ROW()-1<=ROWS(_xlpm.sortedPairs),INDEX(_xlpm.sortedPairs,ROW()-1,1),"")),"")} | M16: {=IFERROR(_xlfn.LET(_xlpm.pairs,_xlfn._xlws.FILTER($A$2:$D$391,($A$2:$A$391<>"")*(TRIM($D$2:$D$391)<>"")),_xlpm.uniquePairs,_xlfn.UNIQUE(_xlfn.HSTACK(INDEX(_xlpm.pairs,,1),INDEX(_xlpm.pairs,,4))),_xlpm.sortedPairs,_xlfn._xlws.SORT(_xlpm.uniquePairs,1,1),IF(ROW()-1<=ROWS(_xlpm.sortedPairs),INDEX(_xlpm.sortedPairs,ROW()-1,2),"")),"")} | N16: {=IF(OR(L16="",M16=""),"",IFERROR(INDEX($E$2:$E$391,MATCH(1,($A$2:$A$391=L16)*($D$2:$D$391=M16),0)),""))} | O16: =IF(OR(L16="",M16=""),"",SUMIFS($J$2:$J$391,$A$2:$A$391,L16,$D$2:$D$391,M16)) | Q16: {=IFERROR(INDEX($L$2:$L$391,MATCH(0,COUNTIF($Q$1:Q15,$L$2:$L$391)+IF($L$2:$L$391="",1,0),0)),"")} | R16: =IF(Q16="","",SUMIF($L$2:$L$391,Q16,$O$2:$O$391)) | S16: =IFERROR(Table3[[#This Row],[Price (€/kg)]]*HELPER!$AK$2," ")
A17: TIPA 302FG | B17: Ext. B | D17: =IF(C17="","",IFERROR(_xlfn.XLOOKUP(C17,HELPER!$A$2:$A$76,HELPER!$B$2:$B$76,""),D17)) | E17: =IFERROR(_xlfn.XLOOKUP(D17,HELPER!$B:$B,HELPER!$C:$C,""),"") | F17: =IFERROR(_xlfn.XLOOKUP(D17,HELPER!$B:$B,HELPER!$D:$D,""),"") | G17: 24 | I17: =IF(AND(H17<>"",IFERROR(_xlfn.XLOOKUP(D17,HELPER!$B:$B,HELPER!$E:$E,""),"")=""),"Missing price",IFERROR(_xlfn.XLOOKUP(D17,HELPER!$B:$B,HELPER!$E:$E,"")," ")) | J17: =IFERROR(H17*(IF(G17=8,I17*HELPER!$G$2,BOM!I17*HELPER!$G$3))," ") | L17: {=IFERROR(_xlfn.LET(_xlpm.pairs,_xlfn._xlws.FILTER($A$2:$D$391,($A$2:$A$391<>"")*(TRIM($D$2:$D$391)<>"")),_xlpm.uniquePairs,_xlfn.UNIQUE(_xlfn.HSTACK(INDEX(_xlpm.pairs,,1),INDEX(_xlpm.pairs,,4))),_xlpm.sortedPairs,_xlfn._xlws.SORT(_xlpm.uniquePairs,1,1),IF(ROW()-1<=ROWS(_xlpm.sortedPairs),INDEX(_xlpm.sortedPairs,ROW()-1,1),"")),"")} | M17: {=IFERROR(_xlfn.LET(_xlpm.pairs,_xlfn._xlws.FILTER($A$2:$D$391,($A$2:$A$391<>"")*(TRIM($D$2:$D$391)<>"")),_xlpm.uniquePairs,_xlfn.UNIQUE(_xlfn.HSTACK(INDEX(_xlpm.pairs,,1),INDEX(_xlpm.pairs,,4))),_xlpm.sortedPairs,_xlfn._xlws.SORT(_xlpm.uniquePairs,1,1),IF(ROW()-1<=ROWS(_xlpm.sortedPairs),INDEX(_xlpm.sortedPairs,ROW()-1,2),"")),"")} | N17: {=IF(OR(L17="",M17=""),"",IFERROR(INDEX($E$2:$E$391,MATCH(1,($A$2:$A$391=L17)*($D$2:$D$391=M17),0)),""))} | O17: =IF(OR(L17="",M17=""),"",SUMIFS($J$2:$J$391,$A$2:$A$391,L17,$D$2:$D$391,M17)) | Q17: {=IFERROR(INDEX($L$2:$L$391,MATCH(0,COUNTIF($Q$1:Q16,$L$2:$L$391)+IF($L$2:$L$391="",1,0),0)),"")} | R17: =IF(Q17="","",SUMIF($L$2:$L$391,Q17,$O$2:$O$391)) | S17: =IFERROR(Table3[[#This Row],[Price (€/kg)]]*HELPER!$AK$2," ")
A18: TIPA 302FG | B18: Ext. B | C18: PBAT | D18: =IF(C18="","",IFERROR(_xlfn.XLOOKUP(C18,HELPER!$A$2:$A$76,HELPER!$B$2:$B$76,""),D18)) | E18: =IFERROR(_xlfn.XLOOKUP(D18,HELPER!$B:$B,HELPER!$C:$C,""),"") | F18: =IFERROR(_xlfn.XLOOKUP(D18,HELPER!$B:$B,HELPER!$D:$D,""),"") | G18: 24 | H18: 0.985 | I18: =IF(AND(H18<>"",IFERROR(_xlfn.XLOOKUP(D18,HELPER!$B:$B,HELPER!$E:$E,""),"")=""),"Missing price",IFERROR(_xlfn.XLOOKUP(D18,HELPER!$B:$B,HELPER!$E:$E,"")," ")) | J18: =IFERROR(H18*(IF(G18=8,I18*HELPER!$G$2,BOM!I18*HELPER!$G$3))," ") | L18: {=IFERROR(_xlfn.LET(_xlpm.pairs,_xlfn._xlws.FILTER($A$2:$D$391,($A$2:$A$391<>"")*(TRIM($D$2:$D$391)<>"")),_xlpm.uniquePairs,_xlfn.UNIQUE(_xlfn.HSTACK(INDEX(_xlpm.pairs,,1),INDEX(_xlpm.pairs,,4))),_xlpm.sortedPairs,_xlfn._xlws.SORT(_xlpm.uniquePairs,1,1),IF(ROW()-1<=ROWS(_xlpm.sortedPairs),INDEX(_xlpm.sortedPairs,ROW()-1,1),"")),"")} | M18: {=IFERROR(_xlfn.LET(_xlpm.pairs,_xlfn._xlws.FILTER($A$2:$D$391,($A$2:$A$391<>"")*(TRIM($D$2:$D$391)<>"")),_xlpm.uniquePairs,_xlfn.UNIQUE(_xlfn.HSTACK(INDEX(_xlpm.pairs,,1),INDEX(_xlpm.pairs,,4))),_xlpm.sortedPairs,_xlfn._xlws.SORT(_xlpm.uniquePairs,1,1),IF(ROW()-1<=ROWS(_xlpm.sortedPairs),INDEX(_xlpm.sortedPairs,ROW()-1,2),"")),"")} | N18: {=IF(OR(L18="",M18=""),"",IFERROR(INDEX($E$2:$E$391,MATCH(1,($A$2:$A$391=L18)*($D$2:$D$391=M18),0)),""))} | O18: =IF(OR(L18="",M18=""),"",SUMIFS($J$2:$J$391,$A$2:$A$391,L18,$D$2:$D$391,M18)) | Q18: {=IFERROR(INDEX($L$2:$L$391,MATCH(0,COUNTIF($Q$1:Q17,$L$2:$L$391)+IF($L$2:$L$391="",1,0),0)),"")} | R18: =IF(Q18="","",SUMIF($L$2:$L$391,Q18,$O$2:$O$391)) | S18: =IFERROR(Table3[[#This Row],[Price (€/kg)]]*HELPER!$AK$2," ")
A19: TIPA 302FG | B19: Ext. B | D19: =IF(C19="","",IFERROR(_xlfn.XLOOKUP(C19,HELPER!$A$2:$A$76,HELPER!$B$2:$B$76,""),D19)) | E19: =IFERROR(_xlfn.XLOOKUP(D19,HELPER!$B:$B,HELPER!$C:$C,""),"") | F19: =IFERROR(_xlfn.XLOOKUP(D19,HELPER!$B:$B,HELPER!$D:$D,""),"") | G19: 24 | I19: =IF(AND(H19<>"",IFERROR(_xlfn.XLOOKUP(D19,HELPER!$B:$B,HELPER!$E:$E,""),"")=""),"Missing price",IFERROR(_xlfn.XLOOKUP(D19,HELPER!$B:$B,HELPER!$E:$E,"")," ")) | J19: =IFERROR(H19*(IF(G19=8,I19*HELPER!$G$2,BOM!I19*HELPER!$G$3))," ") | L19: {=IFERROR(_xlfn.LET(_xlpm.pairs,_xlfn._xlws.FILTER($A$2:$D$391,($A$2:$A$391<>"")*(TRIM($D$2:$D$391)<>"")),_xlpm.uniquePairs,_xlfn.UNIQUE(_xlfn.HSTACK(INDEX(_xlpm.pairs,,1),INDEX(_xlpm.pairs,,4))),_xlpm.sortedPairs,_xlfn._xlws.SORT(_xlpm.uniquePairs,1,1),IF(ROW()-1<=ROWS(_xlpm.sortedPairs),INDEX(_xlpm.sortedPairs,ROW()-1,1),"")),"")} | M19: {=IFERROR(_xlfn.LET(_xlpm.pairs,_xlfn._xlws.FILTER($A$2:$D$391,($A$2:$A$391<>"")*(TRIM($D$2:$D$391)<>"")),_xlpm.uniquePairs,_xlfn.UNIQUE(_xlfn.HSTACK(INDEX(_xlpm.pairs,,1),INDEX(_xlpm.pairs,,4))),_xlpm.sortedPairs,_xlfn._xlws.SORT(_xlpm.uniquePairs,1,1),IF(ROW()-1<=ROWS(_xlpm.sortedPairs),INDEX(_xlpm.sortedPairs,ROW()-1,2),"")),"")} | N19: {=IF(OR(L19="",M19=""),"",IFERROR(INDEX($E$2:$E$391,MATCH(1,($A$2:$A$391=L19)*($D$2:$D$391=M19),0)),""))} | O19: =IF(OR(L19="",M19=""),"",SUMIFS($J$2:$J$391,$A$2:$A$391,L19,$D$2:$D$391,M19)) | Q19: {=IFERROR(INDEX($L$2:$L$391,MATCH(0,COUNTIF($Q$1:Q18,$L$2:$L$391)+IF($L$2:$L$391="",1,0),0)),"")} | R19: =IF(Q19="","",SUMIF($L$2:$L$391,Q19,$O$2:$O$391)) | S19: =IFERROR(Table3[[#This Row],[Price (€/kg)]]*HELPER!$AK$2," ")
A20: TIPA 302FG | B20: Ext. B | D20: =IF(C20="","",IFERROR(_xlfn.XLOOKUP(C20,HELPER!$A$2:$A$76,HELPER!$B$2:$B$76,""),D20)) | E20: =IFERROR(_xlfn.XLOOKUP(D20,HELPER!$B:$B,HELPER!$C:$C,""),"") | F20: =IFERROR(_xlfn.XLOOKUP(D20,HELPER!$B:$B,HELPER!$D:$D,""),"") | G20: 24 | I20: =IF(AND(H20<>"",IFERROR(_xlfn.XLOOKUP(D20,HELPER!$B:$B,HELPER!$E:$E,""),"")=""),"Missing price",IFERROR(_xlfn.XLOOKUP(D20,HELPER!$B:$B,HELPER!$E:$E,"")," ")) | J20: =IFERROR(H20*(IF(G20=8,I20*HELPER!$G$2,BOM!I20*HELPER!$G$3))," ") | L20: {=IFERROR(_xlfn.LET(_xlpm.pairs,_xlfn._xlws.FILTER($A$2:$D$391,($A$2:$A$391<>"")*(TRIM($D$2:$D$391)<>"")),_xlpm.uniquePairs,_xlfn.UNIQUE(_xlfn.HSTACK(INDEX(_xlpm.pairs,,1),INDEX(_xlpm.pairs,,4))),_xlpm.sortedPairs,_xlfn._xlws.SORT(_xlpm.uniquePairs,1,1),IF(ROW()-1<=ROWS(_xlpm.sortedPairs),INDEX(_xlpm.sortedPairs,ROW()-1,1),"")),"")} | M20: {=IFERROR(_xlfn.LET(_xlpm.pairs,_xlfn._xlws.FILTER($A$2:$D$391,($A$2:$A$391<>"")*(TRIM($D$2:$D$391)<>"")),_xlpm.uniquePairs,_xlfn.UNIQUE(_xlfn.HSTACK(INDEX(_xlpm.pairs,,1),INDEX(_xlpm.pairs,,4))),_xlpm.sortedPairs,_xlfn._xlws.SORT(_xlpm.uniquePairs,1,1),IF(ROW()-1<=ROWS(_xlpm.sortedPairs),INDEX(_xlpm.sortedPairs,ROW()-1,2),"")),"")} | N20: {=IF(OR(L20="",M20=""),"",IFERROR(INDEX($E$2:$E$391,MATCH(1,($A$2:$A$391=L20)*($D$2:$D$391=M20),0)),""))} | O20: =IF(OR(L20="",M20=""),"",SUMIFS($J$2:$J$391,$A$2:$A$391,L20,$D$2:$D$391,M20)) | Q20: {=IFERROR(INDEX($L$2:$L$391,MATCH(0,COUNTIF($Q$1:Q19,$L$2:$L$391)+IF($L$2:$L$391="",1,0),0)),"")} | R20: =IF(Q20="","",SUMIF($L$2:$L$391,Q20,$O$2:$O$391)) | S20: =IFERROR(Table3[[#This Row],[Price (€/kg)]]*HELPER!$AK$2," ")
A21: TIPA 302FG | B21: Ext. B | D21: =IF(C21="","",IFERROR(_xlfn.XLOOKUP(C21,HELPER!$A$2:$A$76,HELPER!$B$2:$B$76,""),D21)) | E21: =IFERROR(_xlfn.XLOOKUP(D21,HELPER!$B:$B,HELPER!$C:$C,""),"") | F21: =IFERROR(_xlfn.XLOOKUP(D21,HELPER!$B:$B,HELPER!$D:$D,""),"") | G21: 24 | I21: =IF(AND(H21<>"",IFERROR(_xlfn.XLOOKUP(D21,HELPER!$B:$B,HELPER!$E:$E,""),"")=""),"Missing price",IFERROR(_xlfn.XLOOKUP(D21,HELPER!$B:$B,HELPER!$E:$E,"")," ")) | J21: =IFERROR(H21*(IF(G21=8,I21*HELPER!$G$2,BOM!I21*HELPER!$G$3))," ") | L21: {=IFERROR(_xlfn.LET(_xlpm.pairs,_xlfn._xlws.FILTER($A$2:$D$391,($A$2:$A$391<>"")*(TRIM($D$2:$D$391)<>"")),_xlpm.uniquePairs,_xlfn.UNIQUE(_xlfn.HSTACK(INDEX(_xlpm.pairs,,1),INDEX(_xlpm.pairs,,4))),_xlpm.sortedPairs,_xlfn._xlws.SORT(_xlpm.uniquePairs,1,1),IF(ROW()-1<=ROWS(_xlpm.sortedPairs),INDEX(_xlpm.sortedPairs,ROW()-1,1),"")),"")} | M21: {=IFERROR(_xlfn.LET(_xlpm.pairs,_xlfn._xlws.FILTER($A$2:$D$391,($A$2:$A$391<>"")*(TRIM($D$2:$D$391)<>"")),_xlpm.uniquePairs,_xlfn.UNIQUE(_xlfn.HSTACK(INDEX(_xlpm.pairs,,1),INDEX(_xlpm.pairs,,4))),_xlpm.sortedPairs,_xlfn._xlws.SORT(_xlpm.uniquePairs,1,1),IF(ROW()-1<=ROWS(_xlpm.sortedPairs),INDEX(_xlpm.sortedPairs,ROW()-1,2),"")),"")} | N21: {=IF(OR(L21="",M21=""),"",IFERROR(INDEX($E$2:$E$391,MATCH(1,($A$2:$A$391=L21)*($D$2:$D$391=M21),0)),""))} | O21: =IF(OR(L21="",M21=""),"",SUMIFS($J$2:$J$391,$A$2:$A$391,L21,$D$2:$D$391,M21)) | Q21: {=IFERROR(INDEX($L$2:$L$391,MATCH(0,COUNTIF($Q$1:Q20,$L$2:$L$391)+IF($L$2:$L$391="",1,0),0)),"")} | R21: =IF(Q21="","",SUMIF($L$2:$L$391,Q21,$O$2:$O$391)) | S21: =IFERROR(Table3[[#This Row],[Price (€/kg)]]*HELPER!$AK$2," ")
A22: TIPA 302FG | B22: Ext. C (In) | C22: PBSA | D22: =IF(C22="","",IFERROR(_xlfn.XLOOKUP(C22,HELPER!$A$2:$A$76,HELPER!$B$2:$B$76,""),D22)) | E22: =IFERROR(_xlfn.XLOOKUP(D22,HELPER!$B:$B,HELPER!$C:$C,""),"") | F22: =IFERROR(_xlfn.XLOOKUP(D22,HELPER!$B:$B,HELPER!$D:$D,""),"") | G22: 8 | H22: 0.818 | I22: =IF(AND(H22<>"",IFERROR(_xlfn.XLOOKUP(D22,HELPER!$B:$B,HELPER!$E:$E,""),"")=""),"Missing price",IFERROR(_xlfn.XLOOKUP(D22,HELPER!$B:$B,HELPER!$E:$E,"")," ")) | J22: =IFERROR(H22*(IF(G22=8,I22*HELPER!$G$2,BOM!I22*HELPER!$G$3))," ") | L22: {=IFERROR(_xlfn.LET(_xlpm.pairs,_xlfn._xlws.FILTER($A$2:$D$391,($A$2:$A$391<>"")*(TRIM($D$2:$D$391)<>"")),_xlpm.uniquePairs,_xlfn.UNIQUE(_xlfn.HSTACK(INDEX(_xlpm.pairs,,1),INDEX(_xlpm.pairs,,4))),_xlpm.sortedPairs,_xlfn._xlws.SORT(_xlpm.uniquePairs,1,1),IF(ROW()-1<=ROWS(_xlpm.sortedPairs),INDEX(_xlpm.sortedPairs,ROW()-1,1),"")),"")} | M22: {=IFERROR(_xlfn.LET(_xlpm.pairs,_xlfn._xlws.FILTER($A$2:$D$391,($A$2:$A$391<>"")*(TRIM($D$2:$D$391)<>"")),_xlpm.uniquePairs,_xlfn.UNIQUE(_xlfn.HSTACK(INDEX(_xlpm.pairs,,1),INDEX(_xlpm.pairs,,4))),_xlpm.sortedPairs,_xlfn._xlws.SORT(_xlpm.uniquePairs,1,1),IF(ROW()-1<=ROWS(_xlpm.sortedPairs),INDEX(_xlpm.sortedPairs,ROW()-1,2),"")),"")} | N22: {=IF(OR(L22="",M22=""),"",IFERROR(INDEX($E$2:$E$391,MATCH(1,($A$2:$A$391=L22)*($D$2:$D$391=M22),0)),""))} | O22: =IF(OR(L22="",M22=""),"",SUMIFS($J$2:$J$391,$A$2:$A$391,L22,$D$2:$D$391,M22)) | Q22: {=IFERROR(INDEX($L$2:$L$391,MATCH(0,COUNTIF($Q$1:Q21,$L$2:$L$391)+IF($L$2:$L$391="",1,0),0)),"")} | R22: =IF(Q22="","",SUMIF($L$2:$L$391,Q22,$O$2:$O$391)) | S22: =IFERROR(Table3[[#This Row],[Price (€/kg)]]*HELPER!$AK$2," ")
A23: TIPA 302FG | B23: Ext. C (In) | C23: PLA | D23: =IF(C23="","",IFERROR(_xlfn.XLOOKUP(C23,HELPER!$A$2:$A$76,HELPER!$B$2:$B$76,""),D23)) | E23: =IFERROR(_xlfn.XLOOKUP(D23,HELPER!$B:$B,HELPER!$C:$C,""),"") | F23: =IFERROR(_xlfn.XLOOKUP(D23,HELPER!$B:$B,HELPER!$D:$D,""),"") | G23: 8 | H23: 0.144 | I23: =IF(AND(H23<>"",IFERROR(_xlfn.XLOOKUP(D23,HELPER!$B:$B,HELPER!$E:$E,""),"")=""),"Missing price",IFERROR(_xlfn.XLOOKUP(D23,HELPER!$B:$B,HELPER!$E:$E,"")," ")) | J23: =IFERROR(H23*(IF(G23=8,I23*HELPER!$G$2,BOM!I23*HELPER!$G$3))," ") | L23: {=IFERROR(_xlfn.LET(_xlpm.pairs,_xlfn._xlws.FILTER($A$2:$D$391,($A$2:$A$391<>"")*(TRIM($D$2:$D$391)<>"")),_xlpm.uniquePairs,_xlfn.UNIQUE(_xlfn.HSTACK(INDEX(_xlpm.pairs,,1),INDEX(_xlpm.pairs,,4))),_xlpm.sortedPairs,_xlfn._xlws.SORT(_xlpm.uniquePairs,1,1),IF(ROW()-1<=ROWS(_xlpm.sortedPairs),INDEX(_xlpm.sortedPairs,ROW()-1,1),"")),"")} | M23: {=IFERROR(_xlfn.LET(_xlpm.pairs,_xlfn._xlws.FILTER($A$2:$D$391,($A$2:$A$391<>"")*(TRIM($D$2:$D$391)<>"")),_xlpm.uniquePairs,_xlfn.UNIQUE(_xlfn.HSTACK(INDEX(_xlpm.pairs,,1),INDEX(_xlpm.pairs,,4))),_xlpm.sortedPairs,_xlfn._xlws.SORT(_xlpm.uniquePairs,1,1),IF(ROW()-1<=ROWS(_xlpm.sortedPairs),INDEX(_xlpm.sortedPairs,ROW()-1,2),"")),"")} | N23: {=IF(OR(L23="",M23=""),"",IFERROR(INDEX($E$2:$E$391,MATCH(1,($A$2:$A$391=L23)*($D$2:$D$391=M23),0)),""))} | O23: =IF(OR(L23="",M23=""),"",SUMIFS($J$2:$J$391,$A$2:$A$391,L23,$D$2:$D$391,M23)) | Q23: {=IFERROR(INDEX($L$2:$L$391,MATCH(0,COUNTIF($Q$1:Q22,$L$2:$L$391)+IF($L$2:$L$391="",1,0),0)),"")} | R23: =IF(Q23="","",SUMIF($L$2:$L$391,Q23,$O$2:$O$391)) | S23: =IFERROR(Table3[[#This Row],[Price (€/kg)]]*HELPER!$AK$2," ")
A24: TIPA 302FG | B24: Ext. C (In) | C24: AB-PLA | D24: =IF(C24="","",IFERROR(_xlfn.XLOOKUP(C24,HELPER!$A$2:$A$76,HELPER!$B$2:$B$76,""),D24)) | E24: =IFERROR(_xlfn.XLOOKUP(D24,HELPER!$B:$B,HELPER!$C:$C,""),"") | F24: =IFERROR(_xlfn.XLOOKUP(D24,HELPER!$B:$B,HELPER!$D:$D,""),"") | G24: 8 | H24: 0.015 | I24: =IF(AND(H24<>"",IFERROR(_xlfn.XLOOKUP(D24,HELPER!$B:$B,HELPER!$E:$E,""),"")=""),"Missing price",IFERROR(_xlfn.XLOOKUP(D24,HELPER!$B:$B,HELPER!$E:$E,"")," ")) | J24: =IFERROR(H24*(IF(G24=8,I24*HELPER!$G$2,BOM!I24*HELPER!$G$3))," ") | L24: {=IFERROR(_xlfn.LET(_xlpm.pairs,_xlfn._xlws.FILTER($A$2:$D$391,($A$2:$A$391<>"")*(TRIM($D$2:$D$391)<>"")),_xlpm.uniquePairs,_xlfn.UNIQUE(_xlfn.HSTACK(INDEX(_xlpm.pairs,,1),INDEX(_xlpm.pairs,,4))),_xlpm.sortedPairs,_xlfn._xlws.SORT(_xlpm.uniquePairs,1,1),IF(ROW()-1<=ROWS(_xlpm.sortedPairs),INDEX(_xlpm.sortedPairs,ROW()-1,1),"")),"")} | M24: {=IFERROR(_xlfn.LET(_xlpm.pairs,_xlfn._xlws.FILTER($A$2:$D$391,($A$2:$A$391<>"")*(TRIM($D$2:$D$391)<>"")),_xlpm.uniquePairs,_xlfn.UNIQUE(_xlfn.HSTACK(INDEX(_xlpm.pairs,,1),INDEX(_xlpm.pairs,,4))),_xlpm.sortedPairs,_xlfn._xlws.SORT(_xlpm.uniquePairs,1,1),IF(ROW()-1<=ROWS(_xlpm.sortedPairs),INDEX(_xlpm.sortedPairs,ROW()-1,2),"")),"")} | N24: {=IF(OR(L24="",M24=""),"",IFERROR(INDEX($E$2:$E$391,MATCH(1,($A$2:$A$391=L24)*($D$2:$D$391=M24),0)),""))} | O24: =IF(OR(L24="",M24=""),"",SUMIFS($J$2:$J$391,$A$2:$A$391,L24,$D$2:$D$391,M24)) | Q24: {=IFERROR(INDEX($L$2:$L$391,MATCH(0,COUNTIF($Q$1:Q23,$L$2:$L$391)+IF($L$2:$L$391="",1,0),0)),"")} | R24: =IF(Q24="","",SUMIF($L$2:$L$391,Q24,$O$2:$O$391)) | S24: =IFERROR(Table3[[#This Row],[Price (€/kg)]]*HELPER!$AK$2," ")
A25: TIPA 302FG | B25: Ext. C (In) | C25: AO-PBS | D25: =IF(C25="","",IFERROR(_xlfn.XLOOKUP(C25,HELPER!$A$2:$A$76,HELPER!$B$2:$B$76,""),D25)) | E25: =IFERROR(_xlfn.XLOOKUP(D25,HELPER!$B:$B,HELPER!$C:$C,""),"") | F25: =IFERROR(_xlfn.XLOOKUP(D25,HELPER!$B:$B,HELPER!$D:$D,""),"") | G25: 8 | H25: 0.015 | I25: =IF(AND(H25<>"",IFERROR(_xlfn.XLOOKUP(D25,HELPER!$B:$B,HELPER!$E:$E,""),"")=""),"Missing price",IFERROR(_xlfn.XLOOKUP(D25,HELPER!$B:$B,HELPER!$E:$E,"")," ")) | J25: =IFERROR(H25*(IF(G25=8,I25*HELPER!$G$2,BOM!I25*HELPER!$G$3))," ") | L25: {=IFERROR(_xlfn.LET(_xlpm.pairs,_xlfn._xlws.FILTER($A$2:$D$391,($A$2:$A$391<>"")*(TRIM($D$2:$D$391)<>"")),_xlpm.uniquePairs,_xlfn.UNIQUE(_xlfn.HSTACK(INDEX(_xlpm.pairs,,1),INDEX(_xlpm.pairs,,4))),_xlpm.sortedPairs,_xlfn._xlws.SORT(_xlpm.uniquePairs,1,1),IF(ROW()-1<=ROWS(_xlpm.sortedPairs),INDEX(_xlpm.sortedPairs,ROW()-1,1),"")),"")} | M25: {=IFERROR(_xlfn.LET(_xlpm.pairs,_xlfn._xlws.FILTER($A$2:$D$391,($A$2:$A$391<>"")*(TRIM($D$2:$D$391)<>"")),_xlpm.uniquePairs,_xlfn.UNIQUE(_xlfn.HSTACK(INDEX(_xlpm.pairs,,1),INDEX(_xlpm.pairs,,4))),_xlpm.sortedPairs,_xlfn._xlws.SORT(_xlpm.uniquePairs,1,1),IF(ROW()-1<=ROWS(_xlpm.sortedPairs),INDEX(_xlpm.sortedPairs,ROW()-1,2),"")),"")} | N25: {=IF(OR(L25="",M25=""),"",IFERROR(INDEX($E$2:$E$391,MATCH(1,($A$2:$A$391=L25)*($D$2:$D$391=M25),0)),""))} | O25: =IF(OR(L25="",M25=""),"",SUMIFS($J$2:$J$391,$A$2:$A$391,L25,$D$2:$D$391,M25)) | Q25: {=IFERROR(INDEX($L$2:$L$391,MATCH(0,COUNTIF($Q$1:Q24,$L$2:$L$391)+IF($L$2:$L$391="",1,0),0)),"")} | R25: =IF(Q25="","",SUMIF($L$2:$L$391,Q25,$O$2:$O$391)) | S25: =IFERROR(Table3[[#This Row],[Price (€/kg)]]*HELPER!$AK$2," ")
A26: TIPA 302FG | B26: Ext. C (In) | C26: SLAB-PBSA | D26: =IF(C26="","",IFERROR(_xlfn.XLOOKUP(C26,HELPER!$A$2:$A$76,HELPER!$B$2:$B$76,""),D26)) | E26: =IFERROR(_xlfn.XLOOKUP(D26,HELPER!$B:$B,HELPER!$C:$C,""),"") | F26: =IFERROR(_xlfn.XLOOKUP(D26,HELPER!$B:$B,HELPER!$D:$D,""),"") | G26: 8 | H26: 0.008 | I26: =IF(AND(H26<>"",IFERROR(_xlfn.XLOOKUP(D26,HELPER!$B:$B,HELPER!$E:$E,""),"")=""),"Missing price",IFERROR(_xlfn.XLOOKUP(D26,HELPER!$B:$B,HELPER!$E:$E,"")," ")) | J26: =IFERROR(H26*(IF(G26=8,I26*HELPER!$G$2,BOM!I26*HELPER!$G$3))," ") | L26: {=IFERROR(_xlfn.LET(_xlpm.pairs,_xlfn._xlws.FILTER($A$2:$D$391,($A$2:$A$391<>"")*(TRIM($D$2:$D$391)<>"")),_xlpm.uniquePairs,_xlfn.UNIQUE(_xlfn.HSTACK(INDEX(_xlpm.pairs,,1),INDEX(_xlpm.pairs,,4))),_xlpm.sortedPairs,_xlfn._xlws.SORT(_xlpm.uniquePairs,1,1),IF(ROW()-1<=ROWS(_xlpm.sortedPairs),INDEX(_xlpm.sortedPairs,ROW()-1,1),"")),"")} | M26: {=IFERROR(_xlfn.LET(_xlpm.pairs,_xlfn._xlws.FILTER($A$2:$D$391,($A$2:$A$391<>"")*(TRIM($D$2:$D$391)<>"")),_xlpm.uniquePairs,_xlfn.UNIQUE(_xlfn.HSTACK(INDEX(_xlpm.pairs,,1),INDEX(_xlpm.pairs,,4))),_xlpm.sortedPairs,_xlfn._xlws.SORT(_xlpm.uniquePairs,1,1),IF(ROW()-1<=ROWS(_xlpm.sortedPairs),INDEX(_xlpm.sortedPairs,ROW()-1,2),"")),"")} | N26: {=IF(OR(L26="",M26=""),"",IFERROR(INDEX($E$2:$E$391,MATCH(1,($A$2:$A$391=L26)*($D$2:$D$391=M26),0)),""))} | O26: =IF(OR(L26="",M26=""),"",SUMIFS($J$2:$J$391,$A$2:$A$391,L26,$D$2:$D$391,M26)) | Q26: {=IFERROR(INDEX($L$2:$L$391,MATCH(0,COUNTIF($Q$1:Q25,$L$2:$L$391)+IF($L$2:$L$391="",1,0),0)),"")} | R26: =IF(Q26="","",SUMIF($L$2:$L$391,Q26,$O$2:$O$391)) | S26: =IFERROR(Table3[[#This Row],[Price (€/kg)]]*HELPER!$AK$2," ")
A27: TIPA 302FG | B27: Ext. C (In) | D27: =IF(C27="","",IFERROR(_xlfn.XLOOKUP(C27,HELPER!$A$2:$A$76,HELPER!$B$2:$B$76,""),D27)) | E27: =IFERROR(_xlfn.XLOOKUP(D27,HELPER!$B:$B,HELPER!$C:$C,""),"") | F27: =IFERROR(_xlfn.XLOOKUP(D27,HELPER!$B:$B,HELPER!$D:$D,""),"") | G27: 8 | I27: =IF(AND(H27<>"",IFERROR(_xlfn.XLOOKUP(D27,HELPER!$B:$B,HELPER!$E:$E,""),"")=""),"Missing price",IFERROR(_xlfn.XLOOKUP(D27,HELPER!$B:$B,HELPER!$E:$E,"")," ")) | J27: =IFERROR(H27*(IF(G27=8,I27*HELPER!$G$2,BOM!I27*HELPER!$G$3))," ") | L27: {=IFERROR(_xlfn.LET(_xlpm.pairs,_xlfn._xlws.FILTER($A$2:$D$391,($A$2:$A$391<>"")*(TRIM($D$2:$D$391)<>"")),_xlpm.uniquePairs,_xlfn.UNIQUE(_xlfn.HSTACK(INDEX(_xlpm.pairs,,1),INDEX(_xlpm.pairs,,4))),_xlpm.sortedPairs,_xlfn._xlws.SORT(_xlpm.uniquePairs,1,1),IF(ROW()-1<=ROWS(_xlpm.sortedPairs),INDEX(_xlpm.sortedPairs,ROW()-1,1),"")),"")} | M27: {=IFERROR(_xlfn.LET(_xlpm.pairs,_xlfn._xlws.FILTER($A$2:$D$391,($A$2:$A$391<>"")*(TRIM($D$2:$D$391)<>"")),_xlpm.uniquePairs,_xlfn.UNIQUE(_xlfn.HSTACK(INDEX(_xlpm.pairs,,1),INDEX(_xlpm.pairs,,4))),_xlpm.sortedPairs,_xlfn._xlws.SORT(_xlpm.uniquePairs,1,1),IF(ROW()-1<=ROWS(_xlpm.sortedPairs),INDEX(_xlpm.sortedPairs,ROW()-1,2),"")),"")} | N27: {=IF(OR(L27="",M27=""),"",IFERROR(INDEX($E$2:$E$391,MATCH(1,($A$2:$A$391=L27)*($D$2:$D$391=M27),0)),""))} | O27: =IF(OR(L27="",M27=""),"",SUMIFS($J$2:$J$391,$A$2:$A$391,L27,$D$2:$D$391,M27)) | Q27: {=IFERROR(INDEX($L$2:$L$391,MATCH(0,COUNTIF($Q$1:Q26,$L$2:$L$391)+IF($L$2:$L$391="",1,0),0)),"")} | R27: =IF(Q27="","",SUMIF($L$2:$L$391,Q27,$O$2:$O$391)) | S27: =IFERROR(Table3[[#This Row],[Price (€/kg)]]*HELPER!$AK$2," ")
A28: TIPA 302FG | B28: Ext. C (In) | D28: =IF(C28="","",IFERROR(_xlfn.XLOOKUP(C28,HELPER!$A$2:$A$76,HELPER!$B$2:$B$76,""),D28)) | E28: =IFERROR(_xlfn.XLOOKUP(D28,HELPER!$B:$B,HELPER!$C:$C,""),"") | F28: =IFERROR(_xlfn.XLOOKUP(D28,HELPER!$B:$B,HELPER!$D:$D,""),"") | G28: 8 | I28: =IF(AND(H28<>"",IFERROR(_xlfn.XLOOKUP(D28,HELPER!$B:$B,HELPER!$E:$E,""),"")=""),"Missing price",IFERROR(_xlfn.XLOOKUP(D28,HELPER!$B:$B,HELPER!$E:$E,"")," ")) | J28: =IFERROR(H28*(IF(G28=8,I28*HELPER!$G$2,BOM!I28*HELPER!$G$3))," ") | L28: {=IFERROR(_xlfn.LET(_xlpm.pairs,_xlfn._xlws.FILTER($A$2:$D$391,($A$2:$A$391<>"")*(TRIM($D$2:$D$391)<>"")),_xlpm.uniquePairs,_xlfn.UNIQUE(_xlfn.HSTACK(INDEX(_xlpm.pairs,,1),INDEX(_xlpm.pairs,,4))),_xlpm.sortedPairs,_xlfn._xlws.SORT(_xlpm.uniquePairs,1,1),IF(ROW()-1<=ROWS(_xlpm.sortedPairs),INDEX(_xlpm.sortedPairs,ROW()-1,1),"")),"")} | M28: {=IFERROR(_xlfn.LET(_xlpm.pairs,_xlfn._xlws.FILTER($A$2:$D$391,($A$2:$A$391<>"")*(TRIM($D$2:$D$391)<>"")),_xlpm.uniquePairs,_xlfn.UNIQUE(_xlfn.HSTACK(INDEX(_xlpm.pairs,,1),INDEX(_xlpm.pairs,,4))),_xlpm.sortedPairs,_xlfn._xlws.SORT(_xlpm.uniquePairs,1,1),IF(ROW()-1<=ROWS(_xlpm.sortedPairs),INDEX(_xlpm.sortedPairs,ROW()-1,2),"")),"")} | N28: {=IF(OR(L28="",M28=""),"",IFERROR(INDEX($E$2:$E$391,MATCH(1,($A$2:$A$391=L28)*($D$2:$D$391=M28),0)),""))} | O28: =IF(OR(L28="",M28=""),"",SUMIFS($J$2:$J$391,$A$2:$A$391,L28,$D$2:$D$391,M28)) | Q28: {=IFERROR(INDEX($L$2:$L$391,MATCH(0,COUNTIF($Q$1:Q27,$L$2:$L$391)+IF($L$2:$L$391="",1,0),0)),"")} | R28: =IF(Q28="","",SUMIF($L$2:$L$391,Q28,$O$2:$O$391)) | S28: =IFERROR(Table3[[#This Row],[Price (€/kg)]]*HELPER!$AK$2," ")
A29: TIPA 302FG | B29: Ext. C (In) | D29: =IF(C29="","",IFERROR(_xlfn.XLOOKUP(C29,HELPER!$A$2:$A$76,HELPER!$B$2:$B$76,""),D29)) | E29: =IFERROR(_xlfn.XLOOKUP(D29,HELPER!$B:$B,HELPER!$C:$C,""),"") | F29: =IFERROR(_xlfn.XLOOKUP(D29,HELPER!$B:$B,HELPER!$D:$D,""),"") | G29: 8 | I29: =IF(AND(H29<>"",IFERROR(_xlfn.XLOOKUP(D29,HELPER!$B:$B,HELPER!$E:$E,""),"")=""),"Missing price",IFERROR(_xlfn.XLOOKUP(D29,HELPER!$B:$B,HELPER!$E:$E,"")," ")) | J29: =IFERROR(H29*(IF(G29=8,I29*HELPER!$G$2,BOM!I29*HELPER!$G$3))," ") | L29: {=IFERROR(_xlfn.LET(_xlpm.pairs,_xlfn._xlws.FILTER($A$2:$D$391,($A$2:$A$391<>"")*(TRIM($D$2:$D$391)<>"")),_xlpm.uniquePairs,_xlfn.UNIQUE(_xlfn.HSTACK(INDEX(_xlpm.pairs,,1),INDEX(_xlpm.pairs,,4))),_xlpm.sortedPairs,_xlfn._xlws.SORT(_xlpm.uniquePairs,1,1),IF(ROW()-1<=ROWS(_xlpm.sortedPairs),INDEX(_xlpm.sortedPairs,ROW()-1,1),"")),"")} | M29: {=IFERROR(_xlfn.LET(_xlpm.pairs,_xlfn._xlws.FILTER($A$2:$D$391,($A$2:$A$391<>"")*(TRIM($D$2:$D$391)<>"")),_xlpm.uniquePairs,_xlfn.UNIQUE(_xlfn.HSTACK(INDEX(_xlpm.pairs,,1),INDEX(_xlpm.pairs,,4))),_xlpm.sortedPairs,_xlfn._xlws.SORT(_xlpm.uniquePairs,1,1),IF(ROW()-1<=ROWS(_xlpm.sortedPairs),INDEX(_xlpm.sortedPairs,ROW()-1,2),"")),"")} | N29: {=IF(OR(L29="",M29=""),"",IFERROR(INDEX($E$2:$E$391,MATCH(1,($A$2:$A$391=L29)*($D$2:$D$391=M29),0)),""))} | O29: =IF(OR(L29="",M29=""),"",SUMIFS($J$2:$J$391,$A$2:$A$391,L29,$D$2:$D$391,M29)) | Q29: {=IFERROR(INDEX($L$2:$L$391,MATCH(0,COUNTIF($Q$1:Q28,$L$2:$L$391)+IF($L$2:$L$391="",1,0),0)),"")} | R29: =IF(Q29="","",SUMIF($L$2:$L$391,Q29,$O$2:$O$391)) | S29: =IFERROR(Table3[[#This Row],[Price (€/kg)]]*HELPER!$AK$2," ")
A30: TIPA 302FG | B30: Ext. C (In) | D30: =IF(C30="","",IFERROR(_xlfn.XLOOKUP(C30,HELPER!$A$2:$A$76,HELPER!$B$2:$B$76,""),D30)) | E30: =IFERROR(_xlfn.XLOOKUP(D30,HELPER!$B:$B,HELPER!$C:$C,""),"") | F30: =IFERROR(_xlfn.XLOOKUP(D30,HELPER!$B:$B,HELPER!$D:$D,""),"") | G30: 8 | I30: =IF(AND(H30<>"",IFERROR(_xlfn.XLOOKUP(D30,HELPER!$B:$B,HELPER!$E:$E,""),"")=""),"Missing price",IFERROR(_xlfn.XLOOKUP(D30,HELPER!$B:$B,HELPER!$E:$E,"")," ")) | J30: =IFERROR(H30*(IF(G30=8,I30*HELPER!$G$2,BOM!I30*HELPER!$G$3))," ") | L30: {=IFERROR(_xlfn.LET(_xlpm.pairs,_xlfn._xlws.FILTER($A$2:$D$391,($A$2:$A$391<>"")*(TRIM($D$2:$D$391)<>"")),_xlpm.uniquePairs,_xlfn.UNIQUE(_xlfn.HSTACK(INDEX(_xlpm.pairs,,1),INDEX(_xlpm.pairs,,4))),_xlpm.sortedPairs,_xlfn._xlws.SORT(_xlpm.uniquePairs,1,1),IF(ROW()-1<=ROWS(_xlpm.sortedPairs),INDEX(_xlpm.sortedPairs,ROW()-1,1),"")),"")} | M30: {=IFERROR(_xlfn.LET(_xlpm.pairs,_xlfn._xlws.FILTER($A$2:$D$391,($A$2:$A$391<>"")*(TRIM($D$2:$D$391)<>"")),_xlpm.uniquePairs,_xlfn.UNIQUE(_xlfn.HSTACK(INDEX(_xlpm.pairs,,1),INDEX(_xlpm.pairs,,4))),_xlpm.sortedPairs,_xlfn._xlws.SORT(_xlpm.uniquePairs,1,1),IF(ROW()-1<=ROWS(_xlpm.sortedPairs),INDEX(_xlpm.sortedPairs,ROW()-1,2),"")),"")} | N30: {=IF(OR(L30="",M30=""),"",IFERROR(INDEX($E$2:$E$391,MATCH(1,($A$2:$A$391=L30)*($D$2:$D$391=M30),0)),""))} | O30: =IF(OR(L30="",M30=""),"",SUMIFS($J$2:$J$391,$A$2:$A$391,L30,$D$2:$D$391,M30)) | Q30: {=IFERROR(INDEX($L$2:$L$391,MATCH(0,COUNTIF($Q$1:Q29,$L$2:$L$391)+IF($L$2:$L$391="",1,0),0)),"")} | R30: =IF(Q30="","",SUMIF($L$2:$L$391,Q30,$O$2:$O$391)) | S30: =IFERROR(Table3[[#This Row],[Price (€/kg)]]*HELPER!$AK$2," ")
A31: TIPA 302FG | B31: Ext. C (In) | D31: =IF(C31="","",IFERROR(_xlfn.XLOOKUP(C31,HELPER!$A$2:$A$76,HELPER!$B$2:$B$76,""),D31)) | E31: =IFERROR(_xlfn.XLOOKUP(D31,HELPER!$B:$B,HELPER!$C:$C,""),"") | F31: =IFERROR(_xlfn.XLOOKUP(D31,HELPER!$B:$B,HELPER!$D:$D,""),"") | G31: 8 | I31: =IF(AND(H31<>"",IFERROR(_xlfn.XLOOKUP(D31,HELPER!$B:$B,HELPER!$E:$E,""),"")=""),"Missing price",IFERROR(_xlfn.XLOOKUP(D31,HELPER!$B:$B,HELPER!$E:$E,"")," ")) | J31: =IFERROR(H31*(IF(G31=8,I31*HELPER!$G$2,BOM!I31*HELPER!$G$3))," ") | L31: {=IFERROR(_xlfn.LET(_xlpm.pairs,_xlfn._xlws.FILTER($A$2:$D$391,($A$2:$A$391<>"")*(TRIM($D$2:$D$391)<>"")),_xlpm.uniquePairs,_xlfn.UNIQUE(_xlfn.HSTACK(INDEX(_xlpm.pairs,,1),INDEX(_xlpm.pairs,,4))),_xlpm.sortedPairs,_xlfn._xlws.SORT(_xlpm.uniquePairs,1,1),IF(ROW()-1<=ROWS(_xlpm.sortedPairs),INDEX(_xlpm.sortedPairs,ROW()-1,1),"")),"")} | M31: {=IFERROR(_xlfn.LET(_xlpm.pairs,_xlfn._xlws.FILTER($A$2:$D$391,($A$2:$A$391<>"")*(TRIM($D$2:$D$391)<>"")),_xlpm.uniquePairs,_xlfn.UNIQUE(_xlfn.HSTACK(INDEX(_xlpm.pairs,,1),INDEX(_xlpm.pairs,,4))),_xlpm.sortedPairs,_xlfn._xlws.SORT(_xlpm.uniquePairs,1,1),IF(ROW()-1<=ROWS(_xlpm.sortedPairs),INDEX(_xlpm.sortedPairs,ROW()-1,2),"")),"")} | N31: {=IF(OR(L31="",M31=""),"",IFERROR(INDEX($E$2:$E$391,MATCH(1,($A$2:$A$391=L31)*($D$2:$D$391=M31),0)),""))} | O31: =IF(OR(L31="",M31=""),"",SUMIFS($J$2:$J$391,$A$2:$A$391,L31,$D$2:$D$391,M31)) | Q31: {=IFERROR(INDEX($L$2:$L$391,MATCH(0,COUNTIF($Q$1:Q30,$L$2:$L$391)+IF($L$2:$L$391="",1,0),0)),"")} | R31: =IF(Q31="","",SUMIF($L$2:$L$391,Q31,$O$2:$O$391)) | S31: =IFERROR(Table3[[#This Row],[Price (€/kg)]]*HELPER!$AK$2," ")
A32: TIPA 302FG W | B32: Ext. A (Out - Chillroll) | C32: PBSA | D32: =IF(C32="","",IFERROR(_xlfn.XLOOKUP(C32,HELPER!$A$2:$A$76,HELPER!$B$2:$B$76,""),D32)) | E32: =IFERROR(_xlfn.XLOOKUP(D32,HELPER!$B:$B,HELPER!$C:$C,""),"") | F32: =IFERROR(_xlfn.XLOOKUP(D32,HELPER!$B:$B,HELPER!$D:$D,""),"") | G32: 8 | H32: 0.81 | I32: =IF(AND(H32<>"",IFERROR(_xlfn.XLOOKUP(D32,HELPER!$B:$B,HELPER!$E:$E,""),"")=""),"Missing price",IFERROR(_xlfn.XLOOKUP(D32,HELPER!$B:$B,HELPER!$E:$E,"")," ")) | J32: =IFERROR(H32*(IF(G32=8,I32*HELPER!$G$2,BOM!I32*HELPER!$G$3))," ") | L32: {=IFERROR(_xlfn.LET(_xlpm.pairs,_xlfn._xlws.FILTER($A$2:$D$391,($A$2:$A$391<>"")*(TRIM($D$2:$D$391)<>"")),_xlpm.uniquePairs,_xlfn.UNIQUE(_xlfn.HSTACK(INDEX(_xlpm.pairs,,1),INDEX(_xlpm.pairs,,4))),_xlpm.sortedPairs,_xlfn._xlws.SORT(_xlpm.uniquePairs,1,1),IF(ROW()-1<=ROWS(_xlpm.sortedPairs),INDEX(_xlpm.sortedPairs,ROW()-1,1),"")),"")} | M32: {=IFERROR(_xlfn.LET(_xlpm.pairs,_xlfn._xlws.FILTER($A$2:$D$391,($A$2:$A$391<>"")*(TRIM($D$2:$D$391)<>"")),_xlpm.uniquePairs,_xlfn.UNIQUE(_xlfn.HSTACK(INDEX(_xlpm.pairs,,1),INDEX(_xlpm.pairs,,4))),_xlpm.sortedPairs,_xlfn._xlws.SORT(_xlpm.uniquePairs,1,1),IF(ROW()-1<=ROWS(_xlpm.sortedPairs),INDEX(_xlpm.sortedPairs,ROW()-1,2),"")),"")} | N32: {=IF(OR(L32="",M32=""),"",IFERROR(INDEX($E$2:$E$391,MATCH(1,($A$2:$A$391=L32)*($D$2:$D$391=M32),0)),""))} | O32: =IF(OR(L32="",M32=""),"",SUMIFS($J$2:$J$391,$A$2:$A$391,L32,$D$2:$D$391,M32)) | Q32: {=IFERROR(INDEX($L$2:$L$391,MATCH(0,COUNTIF($Q$1:Q31,$L$2:$L$391)+IF($L$2:$L$391="",1,0),0)),"")} | R32: =IF(Q32="","",SUMIF($L$2:$L$391,Q32,$O$2:$O$391)) | S32: =IFERROR(Table3[[#This Row],[Price (€/kg)]]*HELPER!$AK$2," ")
A33: TIPA 302FG W | B33: Ext. A (Out - Chillroll) | C33: PLA | D33: =IF(C33="","",IFERROR(_xlfn.XLOOKUP(C33,HELPER!$A$2:$A$76,HELPER!$B$2:$B$76,""),D33)) | E33: =IFERROR(_xlfn.XLOOKUP(D33,HELPER!$B:$B,HELPER!$C:$C,""),"") | F33: =IFERROR(_xlfn.XLOOKUP(D33,HELPER!$B:$B,HELPER!$D:$D,""),"") | G33: 8 | H33: 0.144 | I33: =IF(AND(H33<>"",IFERROR(_xlfn.XLOOKUP(D33,HELPER!$B:$B,HELPER!$E:$E,""),"")=""),"Missing price",IFERROR(_xlfn.XLOOKUP(D33,HELPER!$B:$B,HELPER!$E:$E,"")," ")) | J33: =IFERROR(H33*(IF(G33=8,I33*HELPER!$G$2,BOM!I33*HELPER!$G$3))," ") | L33: {=IFERROR(_xlfn.LET(_xlpm.pairs,_xlfn._xlws.FILTER($A$2:$D$391,($A$2:$A$391<>"")*(TRIM($D$2:$D$391)<>"")),_xlpm.uniquePairs,_xlfn.UNIQUE(_xlfn.HSTACK(INDEX(_xlpm.pairs,,1),INDEX(_xlpm.pairs,,4))),_xlpm.sortedPairs,_xlfn._xlws.SORT(_xlpm.uniquePairs,1,1),IF(ROW()-1<=ROWS(_xlpm.sortedPairs),INDEX(_xlpm.sortedPairs,ROW()-1,1),"")),"")} | M33: {=IFERROR(_xlfn.LET(_xlpm.pairs,_xlfn._xlws.FILTER($A$2:$D$391,($A$2:$A$391<>"")*(TRIM($D$2:$D$391)<>"")),_xlpm.uniquePairs,_xlfn.UNIQUE(_xlfn.HSTACK(INDEX(_xlpm.pairs,,1),INDEX(_xlpm.pairs,,4))),_xlpm.sortedPairs,_xlfn._xlws.SORT(_xlpm.uniquePairs,1,1),IF(ROW()-1<=ROWS(_xlpm.sortedPairs),INDEX(_xlpm.sortedPairs,ROW()-1,2),"")),"")} | N33: {=IF(OR(L33="",M33=""),"",IFERROR(INDEX($E$2:$E$391,MATCH(1,($A$2:$A$391=L33)*($D$2:$D$391=M33),0)),""))} | O33: =IF(OR(L33="",M33=""),"",SUMIFS($J$2:$J$391,$A$2:$A$391,L33,$D$2:$D$391,M33)) | Q33: {=IFERROR(INDEX($L$2:$L$391,MATCH(0,COUNTIF($Q$1:Q32,$L$2:$L$391)+IF($L$2:$L$391="",1,0),0)),"")} | R33: =IF(Q33="","",SUMIF($L$2:$L$391,Q33,$O$2:$O$391)) | S33: =IFERROR(Table3[[#This Row],[Price (€/kg)]]*HELPER!$AK$2," ")
A34: TIPA 302FG W | B34: Ext. A (Out - Chillroll) | C34: AB-PLA | D34: =IF(C34="","",IFERROR(_xlfn.XLOOKUP(C34,HELPER!$A$2:$A$76,HELPER!$B$2:$B$76,""),D34)) | E34: =IFERROR(_xlfn.XLOOKUP(D34,HELPER!$B:$B,HELPER!$C:$C,""),"") | F34: =IFERROR(_xlfn.XLOOKUP(D34,HELPER!$B:$B,HELPER!$D:$D,""),"") | G34: 8 | H34: 0.015 | I34: =IF(AND(H34<>"",IFERROR(_xlfn.XLOOKUP(D34,HELPER!$B:$B,HELPER!$E:$E,""),"")=""),"Missing price",IFERROR(_xlfn.XLOOKUP(D34,HELPER!$B:$B,HELPER!$E:$E,"")," ")) | J34: =IFERROR(H34*(IF(G34=8,I34*HELPER!$G$2,BOM!I34*HELPER!$G$3))," ") | L34: {=IFERROR(_xlfn.LET(_xlpm.pairs,_xlfn._xlws.FILTER($A$2:$D$391,($A$2:$A$391<>"")*(TRIM($D$2:$D$391)<>"")),_xlpm.uniquePairs,_xlfn.UNIQUE(_xlfn.HSTACK(INDEX(_xlpm.pairs,,1),INDEX(_xlpm.pairs,,4))),_xlpm.sortedPairs,_xlfn._xlws.SORT(_xlpm.uniquePairs,1,1),IF(ROW()-1<=ROWS(_xlpm.sortedPairs),INDEX(_xlpm.sortedPairs,ROW()-1,1),"")),"")} | M34: {=IFERROR(_xlfn.LET(_xlpm.pairs,_xlfn._xlws.FILTER($A$2:$D$391,($A$2:$A$391<>"")*(TRIM($D$2:$D$391)<>"")),_xlpm.uniquePairs,_xlfn.UNIQUE(_xlfn.HSTACK(INDEX(_xlpm.pairs,,1),INDEX(_xlpm.pairs,,4))),_xlpm.sortedPairs,_xlfn._xlws.SORT(_xlpm.uniquePairs,1,1),IF(ROW()-1<=ROWS(_xlpm.sortedPairs),INDEX(_xlpm.sortedPairs,ROW()-1,2),"")),"")} | N34: {=IF(OR(L34="",M34=""),"",IFERROR(INDEX($E$2:$E$391,MATCH(1,($A$2:$A$391=L34)*($D$2:$D$391=M34),0)),""))} | O34: =IF(OR(L34="",M34=""),"",SUMIFS($J$2:$J$391,$A$2:$A$391,L34,$D$2:$D$391,M34)) | Q34: {=IFERROR(INDEX($L$2:$L$391,MATCH(0,COUNTIF($Q$1:Q33,$L$2:$L$391)+IF($L$2:$L$391="",1,0),0)),"")} | R34: =IF(Q34="","",SUMIF($L$2:$L$391,Q34,$O$2:$O$391)) | S34: =IFERROR(Table3[[#This Row],[Price (€/kg)]]*HELPER!$AK$2," ")
A35: TIPA 302FG W | B35: Ext. A (Out - Chillroll) | C35: AO-PBS | D35: =IF(C35="","",IFERROR(_xlfn.XLOOKUP(C35,HELPER!$A$2:$A$76,HELPER!$B$2:$B$76,""),D35)) | E35: =IFERROR(_xlfn.XLOOKUP(D35,HELPER!$B:$B,HELPER!$C:$C,""),"") | F35: =IFERROR(_xlfn.XLOOKUP(D35,HELPER!$B:$B,HELPER!$D:$D,""),"") | G35: 8 | H35: 0.015 | I35: =IF(AND(H35<>"",IFERROR(_xlfn.XLOOKUP(D35,HELPER!$B:$B,HELPER!$E:$E,""),"")=""),"Missing price",IFERROR(_xlfn.XLOOKUP(D35,HELPER!$B:$B,HELPER!$E:$E,"")," ")) | J35: =IFERROR(H35*(IF(G35=8,I35*HELPER!$G$2,BOM!I35*HELPER!$G$3))," ") | L35: {=IFERROR(_xlfn.LET(_xlpm.pairs,_xlfn._xlws.FILTER($A$2:$D$391,($A$2:$A$391<>"")*(TRIM($D$2:$D$391)<>"")),_xlpm.uniquePairs,_xlfn.UNIQUE(_xlfn.HSTACK(INDEX(_xlpm.pairs,,1),INDEX(_xlpm.pairs,,4))),_xlpm.sortedPairs,_xlfn._xlws.SORT(_xlpm.uniquePairs,1,1),IF(ROW()-1<=ROWS(_xlpm.sortedPairs),INDEX(_xlpm.sortedPairs,ROW()-1,1),"")),"")} | M35: {=IFERROR(_xlfn.LET(_xlpm.pairs,_xlfn._xlws.FILTER($A$2:$D$391,($A$2:$A$391<>"")*(TRIM($D$2:$D$391)<>"")),_xlpm.uniquePairs,_xlfn.UNIQUE(_xlfn.HSTACK(INDEX(_xlpm.pairs,,1),INDEX(_xlpm.pairs,,4))),_xlpm.sortedPairs,_xlfn._xlws.SORT(_xlpm.uniquePairs,1,1),IF(ROW()-1<=ROWS(_xlpm.sortedPairs),INDEX(_xlpm.sortedPairs,ROW()-1,2),"")),"")} | N35: {=IF(OR(L35="",M35=""),"",IFERROR(INDEX($E$2:$E$391,MATCH(1,($A$2:$A$391=L35)*($D$2:$D$391=M35),0)),""))} | O35: =IF(OR(L35="",M35=""),"",SUMIFS($J$2:$J$391,$A$2:$A$391,L35,$D$2:$D$391,M35)) | Q35: {=IFERROR(INDEX($L$2:$L$391,MATCH(0,COUNTIF($Q$1:Q34,$L$2:$L$391)+IF($L$2:$L$391="",1,0),0)),"")} | R35: =IF(Q35="","",SUMIF($L$2:$L$391,Q35,$O$2:$O$391)) | S35: =IFERROR(Table3[[#This Row],[Price (€/kg)]]*HELPER!$AK$2," ")
A36: TIPA 302FG W | B36: Ext. A (Out - Chillroll) | C36: SLAB-PBSA | D36: =IF(C36="","",IFERROR(_xlfn.XLOOKUP(C36,HELPER!$A$2:$A$76,HELPER!$B$2:$B$76,""),D36)) | E36: =IFERROR(_xlfn.XLOOKUP(D36,HELPER!$B:$B,HELPER!$C:$C,""),"") | F36: =IFERROR(_xlfn.XLOOKUP(D36,HELPER!$B:$B,HELPER!$D:$D,""),"") | G36: 8 | H36: 0.016 | I36: =IF(AND(H36<>"",IFERROR(_xlfn.XLOOKUP(D36,HELPER!$B:$B,HELPER!$E:$E,""),"")=""),"Missing price",IFERROR(_xlfn.XLOOKUP(D36,HELPER!$B:$B,HELPER!$E:$E,"")," ")) | J36: =IFERROR(H36*(IF(G36=8,I36*HELPER!$G$2,BOM!I36*HELPER!$G$3))," ") | L36: {=IFERROR(_xlfn.LET(_xlpm.pairs,_xlfn._xlws.FILTER($A$2:$D$391,($A$2:$A$391<>"")*(TRIM($D$2:$D$391)<>"")),_xlpm.uniquePairs,_xlfn.UNIQUE(_xlfn.HSTACK(INDEX(_xlpm.pairs,,1),INDEX(_xlpm.pairs,,4))),_xlpm.sortedPairs,_xlfn._xlws.SORT(_xlpm.uniquePairs,1,1),IF(ROW()-1<=ROWS(_xlpm.sortedPairs),INDEX(_xlpm.sortedPairs,ROW()-1,1),"")),"")} | M36: {=IFERROR(_xlfn.LET(_xlpm.pairs,_xlfn._xlws.FILTER($A$2:$D$391,($A$2:$A$391<>"")*(TRIM($D$2:$D$391)<>"")),_xlpm.uniquePairs,_xlfn.UNIQUE(_xlfn.HSTACK(INDEX(_xlpm.pairs,,1),INDEX(_xlpm.pairs,,4))),_xlpm.sortedPairs,_xlfn._xlws.SORT(_xlpm.uniquePairs,1,1),IF(ROW()-1<=ROWS(_xlpm.sortedPairs),INDEX(_xlpm.sortedPairs,ROW()-1,2),"")),"")} | N36: {=IF(OR(L36="",M36=""),"",IFERROR(INDEX($E$2:$E$391,MATCH(1,($A$2:$A$391=L36)*($D$2:$D$391=M36),0)),""))} | O36: =IF(OR(L36="",M36=""),"",SUMIFS($J$2:$J$391,$A$2:$A$391,L36,$D$2:$D$391,M36)) | Q36: {=IFERROR(INDEX($L$2:$L$391,MATCH(0,COUNTIF($Q$1:Q35,$L$2:$L$391)+IF($L$2:$L$391="",1,0),0)),"")} | R36: =IF(Q36="","",SUMIF($L$2:$L$391,Q36,$O$2:$O$391)) | S36: =IFERROR(Table3[[#This Row],[Price (€/kg)]]*HELPER!$AK$2," ")
A37: TIPA 302FG W | B37: Ext. A (Out - Chillroll) | D37: =IF(C37="","",IFERROR(_xlfn.XLOOKUP(C37,HELPER!$A$2:$A$76,HELPER!$B$2:$B$76,""),D37)) | E37: =IFERROR(_xlfn.XLOOKUP(D37,HELPER!$B:$B,HELPER!$C:$C,""),"") | F37: =IFERROR(_xlfn.XLOOKUP(D37,HELPER!$B:$B,HELPER!$D:$D,""),"") | G37: 8 | I37: =IF(AND(H37<>"",IFERROR(_xlfn.XLOOKUP(D37,HELPER!$B:$B,HELPER!$E:$E,""),"")=""),"Missing price",IFERROR(_xlfn.XLOOKUP(D37,HELPER!$B:$B,HELPER!$E:$E,"")," ")) | J37: =IFERROR(H37*(IF(G37=8,I37*HELPER!$G$2,BOM!I37*HELPER!$G$3))," ") | L37: {=IFERROR(_xlfn.LET(_xlpm.pairs,_xlfn._xlws.FILTER($A$2:$D$391,($A$2:$A$391<>"")*(TRIM($D$2:$D$391)<>"")),_xlpm.uniquePairs,_xlfn.UNIQUE(_xlfn.HSTACK(INDEX(_xlpm.pairs,,1),INDEX(_xlpm.pairs,,4))),_xlpm.sortedPairs,_xlfn._xlws.SORT(_xlpm.uniquePairs,1,1),IF(ROW()-1<=ROWS(_xlpm.sortedPairs),INDEX(_xlpm.sortedPairs,ROW()-1,1),"")),"")} | M37: {=IFERROR(_xlfn.LET(_xlpm.pairs,_xlfn._xlws.FILTER($A$2:$D$391,($A$2:$A$391<>"")*(TRIM($D$2:$D$391)<>"")),_xlpm.uniquePairs,_xlfn.UNIQUE(_xlfn.HSTACK(INDEX(_xlpm.pairs,,1),INDEX(_xlpm.pairs,,4))),_xlpm.sortedPairs,_xlfn._xlws.SORT(_xlpm.uniquePairs,1,1),IF(ROW()-1<=ROWS(_xlpm.sortedPairs),INDEX(_xlpm.sortedPairs,ROW()-1,2),"")),"")} | N37: {=IF(OR(L37="",M37=""),"",IFERROR(INDEX($E$2:$E$391,MATCH(1,($A$2:$A$391=L37)*($D$2:$D$391=M37),0)),""))} | O37: =IF(OR(L37="",M37=""),"",SUMIFS($J$2:$J$391,$A$2:$A$391,L37,$D$2:$D$391,M37)) | Q37: {=IFERROR(INDEX($L$2:$L$391,MATCH(0,COUNTIF($Q$1:Q36,$L$2:$L$391)+IF($L$2:$L$391="",1,0),0)),"")} | R37: =IF(Q37="","",SUMIF($L$2:$L$391,Q37,$O$2:$O$391)) | S37: =IFERROR(Table3[[#This Row],[Price (€/kg)]]*HELPER!$AK$2," ")
A38: TIPA 302FG W | B38: Ext. A (Out - Chillroll) | D38: =IF(C38="","",IFERROR(_xlfn.XLOOKUP(C38,HELPER!$A$2:$A$76,HELPER!$B$2:$B$76,""),D38)) | E38: =IFERROR(_xlfn.XLOOKUP(D38,HELPER!$B:$B,HELPER!$C:$C,""),"") | F38: =IFERROR(_xlfn.XLOOKUP(D38,HELPER!$B:$B,HELPER!$D:$D,""),"") | G38: 8 | I38: =IF(AND(H38<>"",IFERROR(_xlfn.XLOOKUP(D38,HELPER!$B:$B,HELPER!$E:$E,""),"")=""),"Missing price",IFERROR(_xlfn.XLOOKUP(D38,HELPER!$B:$B,HELPER!$E:$E,"")," ")) | J38: =IFERROR(H38*(IF(G38=8,I38*HELPER!$G$2,BOM!I38*HELPER!$G$3))," ") | L38: {=IFERROR(_xlfn.LET(_xlpm.pairs,_xlfn._xlws.FILTER($A$2:$D$391,($A$2:$A$391<>"")*(TRIM($D$2:$D$391)<>"")),_xlpm.uniquePairs,_xlfn.UNIQUE(_xlfn.HSTACK(INDEX(_xlpm.pairs,,1),INDEX(_xlpm.pairs,,4))),_xlpm.sortedPairs,_xlfn._xlws.SORT(_xlpm.uniquePairs,1,1),IF(ROW()-1<=ROWS(_xlpm.sortedPairs),INDEX(_xlpm.sortedPairs,ROW()-1,1),"")),"")} | M38: {=IFERROR(_xlfn.LET(_xlpm.pairs,_xlfn._xlws.FILTER($A$2:$D$391,($A$2:$A$391<>"")*(TRIM($D$2:$D$391)<>"")),_xlpm.uniquePairs,_xlfn.UNIQUE(_xlfn.HSTACK(INDEX(_xlpm.pairs,,1),INDEX(_xlpm.pairs,,4))),_xlpm.sortedPairs,_xlfn._xlws.SORT(_xlpm.uniquePairs,1,1),IF(ROW()-1<=ROWS(_xlpm.sortedPairs),INDEX(_xlpm.sortedPairs,ROW()-1,2),"")),"")} | N38: {=IF(OR(L38="",M38=""),"",IFERROR(INDEX($E$2:$E$391,MATCH(1,($A$2:$A$391=L38)*($D$2:$D$391=M38),0)),""))} | O38: =IF(OR(L38="",M38=""),"",SUMIFS($J$2:$J$391,$A$2:$A$391,L38,$D$2:$D$391,M38)) | Q38: {=IFERROR(INDEX($L$2:$L$391,MATCH(0,COUNTIF($Q$1:Q37,$L$2:$L$391)+IF($L$2:$L$391="",1,0),0)),"")} | R38: =IF(Q38="","",SUMIF($L$2:$L$391,Q38,$O$2:$O$391)) | S38: =IFERROR(Table3[[#This Row],[Price (€/kg)]]*HELPER!$AK$2," ")
A39: TIPA 302FG W | B39: Ext. A (Out - Chillroll) | D39: =IF(C39="","",IFERROR(_xlfn.XLOOKUP(C39,HELPER!$A$2:$A$76,HELPER!$B$2:$B$76,""),D39)) | E39: =IFERROR(_xlfn.XLOOKUP(D39,HELPER!$B:$B,HELPER!$C:$C,""),"") | F39: =IFERROR(_xlfn.XLOOKUP(D39,HELPER!$B:$B,HELPER!$D:$D,""),"") | G39: 8 | I39: =IF(AND(H39<>"",IFERROR(_xlfn.XLOOKUP(D39,HELPER!$B:$B,HELPER!$E:$E,""),"")=""),"Missing price",IFERROR(_xlfn.XLOOKUP(D39,HELPER!$B:$B,HELPER!$E:$E,"")," ")) | J39: =IFERROR(H39*(IF(G39=8,I39*HELPER!$G$2,BOM!I39*HELPER!$G$3))," ") | L39: {=IFERROR(_xlfn.LET(_xlpm.pairs,_xlfn._xlws.FILTER($A$2:$D$391,($A$2:$A$391<>"")*(TRIM($D$2:$D$391)<>"")),_xlpm.uniquePairs,_xlfn.UNIQUE(_xlfn.HSTACK(INDEX(_xlpm.pairs,,1),INDEX(_xlpm.pairs,,4))),_xlpm.sortedPairs,_xlfn._xlws.SORT(_xlpm.uniquePairs,1,1),IF(ROW()-1<=ROWS(_xlpm.sortedPairs),INDEX(_xlpm.sortedPairs,ROW()-1,1),"")),"")} | M39: {=IFERROR(_xlfn.LET(_xlpm.pairs,_xlfn._xlws.FILTER($A$2:$D$391,($A$2:$A$391<>"")*(TRIM($D$2:$D$391)<>"")),_xlpm.uniquePairs,_xlfn.UNIQUE(_xlfn.HSTACK(INDEX(_xlpm.pairs,,1),INDEX(_xlpm.pairs,,4))),_xlpm.sortedPairs,_xlfn._xlws.SORT(_xlpm.uniquePairs,1,1),IF(ROW()-1<=ROWS(_xlpm.sortedPairs),INDEX(_xlpm.sortedPairs,ROW()-1,2),"")),"")} | N39: {=IF(OR(L39="",M39=""),"",IFERROR(INDEX($E$2:$E$391,MATCH(1,($A$2:$A$391=L39)*($D$2:$D$391=M39),0)),""))} | O39: =IF(OR(L39="",M39=""),"",SUMIFS($J$2:$J$391,$A$2:$A$391,L39,$D$2:$D$391,M39)) | Q39: {=IFERROR(INDEX($L$2:$L$391,MATCH(0,COUNTIF($Q$1:Q38,$L$2:$L$391)+IF($L$2:$L$391="",1,0),0)),"")} | R39: =IF(Q39="","",SUMIF($L$2:$L$391,Q39,$O$2:$O$391)) | S39: =IFERROR(Table3[[#This Row],[Price (€/kg)]]*HELPER!$AK$2," ")
A40: TIPA 302FG W | B40: Ext. A (Out - Chillroll) | D40: =IF(C40="","",IFERROR(_xlfn.XLOOKUP(C40,HELPER!$A$2:$A$76,HELPER!$B$2:$B$76,""),D40)) | E40: =IFERROR(_xlfn.XLOOKUP(D40,HELPER!$B:$B,HELPER!$C:$C,""),"") | F40: =IFERROR(_xlfn.XLOOKUP(D40,HELPER!$B:$B,HELPER!$D:$D,""),"") | G40: 8 | I40: =IF(AND(H40<>"",IFERROR(_xlfn.XLOOKUP(D40,HELPER!$B:$B,HELPER!$E:$E,""),"")=""),"Missing price",IFERROR(_xlfn.XLOOKUP(D40,HELPER!$B:$B,HELPER!$E:$E,"")," ")) | J40: =IFERROR(H40*(IF(G40=8,I40*HELPER!$G$2,BOM!I40*HELPER!$G$3))," ") | L40: {=IFERROR(_xlfn.LET(_xlpm.pairs,_xlfn._xlws.FILTER($A$2:$D$391,($A$2:$A$391<>"")*(TRIM($D$2:$D$391)<>"")),_xlpm.uniquePairs,_xlfn.UNIQUE(_xlfn.HSTACK(INDEX(_xlpm.pairs,,1),INDEX(_xlpm.pairs,,4))),_xlpm.sortedPairs,_xlfn._xlws.SORT(_xlpm.uniquePairs,1,1),IF(ROW()-1<=ROWS(_xlpm.sortedPairs),INDEX(_xlpm.sortedPairs,ROW()-1,1),"")),"")} | M40: {=IFERROR(_xlfn.LET(_xlpm.pairs,_xlfn._xlws.FILTER($A$2:$D$391,($A$2:$A$391<>"")*(TRIM($D$2:$D$391)<>"")),_xlpm.uniquePairs,_xlfn.UNIQUE(_xlfn.HSTACK(INDEX(_xlpm.pairs,,1),INDEX(_xlpm.pairs,,4))),_xlpm.sortedPairs,_xlfn._xlws.SORT(_xlpm.uniquePairs,1,1),IF(ROW()-1<=ROWS(_xlpm.sortedPairs),INDEX(_xlpm.sortedPairs,ROW()-1,2),"")),"")} | N40: {=IF(OR(L40="",M40=""),"",IFERROR(INDEX($E$2:$E$391,MATCH(1,($A$2:$A$391=L40)*($D$2:$D$391=M40),0)),""))} | O40: =IF(OR(L40="",M40=""),"",SUMIFS($J$2:$J$391,$A$2:$A$391,L40,$D$2:$D$391,M40)) | Q40: {=IFERROR(INDEX($L$2:$L$391,MATCH(0,COUNTIF($Q$1:Q39,$L$2:$L$391)+IF($L$2:$L$391="",1,0),0)),"")} | R40: =IF(Q40="","",SUMIF($L$2:$L$391,Q40,$O$2:$O$391)) | S40: =IFERROR(Table3[[#This Row],[Price (€/kg)]]*HELPER!$AK$2," ")
A41: TIPA 302FG W | B41: Ext. A (Out - Chillroll) | D41: =IF(C41="","",IFERROR(_xlfn.XLOOKUP(C41,HELPER!$A$2:$A$76,HELPER!$B$2:$B$76,""),D41)) | E41: =IFERROR(_xlfn.XLOOKUP(D41,HELPER!$B:$B,HELPER!$C:$C,""),"") | F41: =IFERROR(_xlfn.XLOOKUP(D41,HELPER!$B:$B,HELPER!$D:$D,""),"") | G41: 8 | I41: =IF(AND(H41<>"",IFERROR(_xlfn.XLOOKUP(D41,HELPER!$B:$B,HELPER!$E:$E,""),"")=""),"Missing price",IFERROR(_xlfn.XLOOKUP(D41,HELPER!$B:$B,HELPER!$E:$E,"")," ")) | J41: =IFERROR(H41*(IF(G41=8,I41*HELPER!$G$2,BOM!I41*HELPER!$G$3))," ") | L41: {=IFERROR(_xlfn.LET(_xlpm.pairs,_xlfn._xlws.FILTER($A$2:$D$391,($A$2:$A$391<>"")*(TRIM($D$2:$D$391)<>"")),_xlpm.uniquePairs,_xlfn.UNIQUE(_xlfn.HSTACK(INDEX(_xlpm.pairs,,1),INDEX(_xlpm.pairs,,4))),_xlpm.sortedPairs,_xlfn._xlws.SORT(_xlpm.uniquePairs,1,1),IF(ROW()-1<=ROWS(_xlpm.sortedPairs),INDEX(_xlpm.sortedPairs,ROW()-1,1),"")),"")} | M41: {=IFERROR(_xlfn.LET(_xlpm.pairs,_xlfn._xlws.FILTER($A$2:$D$391,($A$2:$A$391<>"")*(TRIM($D$2:$D$391)<>"")),_xlpm.uniquePairs,_xlfn.UNIQUE(_xlfn.HSTACK(INDEX(_xlpm.pairs,,1),INDEX(_xlpm.pairs,,4))),_xlpm.sortedPairs,_xlfn._xlws.SORT(_xlpm.uniquePairs,1,1),IF(ROW()-1<=ROWS(_xlpm.sortedPairs),INDEX(_xlpm.sortedPairs,ROW()-1,2),"")),"")} | N41: {=IF(OR(L41="",M41=""),"",IFERROR(INDEX($E$2:$E$391,MATCH(1,($A$2:$A$391=L41)*($D$2:$D$391=M41),0)),""))} | O41: =IF(OR(L41="",M41=""),"",SUMIFS($J$2:$J$391,$A$2:$A$391,L41,$D$2:$D$391,M41)) | Q41: {=IFERROR(INDEX($L$2:$L$391,MATCH(0,COUNTIF($Q$1:Q40,$L$2:$L$391)+IF($L$2:$L$391="",1,0),0)),"")} | R41: =IF(Q41="","",SUMIF($L$2:$L$391,Q41,$O$2:$O$391)) | S41: =IFERROR(Table3[[#This Row],[Price (€/kg)]]*HELPER!$AK$2," ")
A42: TIPA 302FG W | B42: Ext. B | D42: =IF(C42="","",IFERROR(_xlfn.XLOOKUP(C42,HELPER!$A$2:$A$76,HELPER!$B$2:$B$76,""),D42)) | E42: =IFERROR(_xlfn.XLOOKUP(D42,HELPER!$B:$B,HELPER!$C:$C,""),"") | F42: =IFERROR(_xlfn.XLOOKUP(D42,HELPER!$B:$B,HELPER!$D:$D,""),"") | G42: 24 | I42: =IF(AND(H42<>"",IFERROR(_xlfn.XLOOKUP(D42,HELPER!$B:$B,HELPER!$E:$E,""),"")=""),"Missing price",IFERROR(_xlfn.XLOOKUP(D42,HELPER!$B:$B,HELPER!$E:$E,"")," ")) | J42: =IFERROR(H42*(IF(G42=8,I42*HELPER!$G$2,BOM!I42*HELPER!$G$3))," ") | L42: {=IFERROR(_xlfn.LET(_xlpm.pairs,_xlfn._xlws.FILTER($A$2:$D$391,($A$2:$A$391<>"")*(TRIM($D$2:$D$391)<>"")),_xlpm.uniquePairs,_xlfn.UNIQUE(_xlfn.HSTACK(INDEX(_xlpm.pairs,,1),INDEX(_xlpm.pairs,,4))),_xlpm.sortedPairs,_xlfn._xlws.SORT(_xlpm.uniquePairs,1,1),IF(ROW()-1<=ROWS(_xlpm.sortedPairs),INDEX(_xlpm.sortedPairs,ROW()-1,1),"")),"")} | M42: {=IFERROR(_xlfn.LET(_xlpm.pairs,_xlfn._xlws.FILTER($A$2:$D$391,($A$2:$A$391<>"")*(TRIM($D$2:$D$391)<>"")),_xlpm.uniquePairs,_xlfn.UNIQUE(_xlfn.HSTACK(INDEX(_xlpm.pairs,,1),INDEX(_xlpm.pairs,,4))),_xlpm.sortedPairs,_xlfn._xlws.SORT(_xlpm.uniquePairs,1,1),IF(ROW()-1<=ROWS(_xlpm.sortedPairs),INDEX(_xlpm.sortedPairs,ROW()-1,2),"")),"")} | N42: {=IF(OR(L42="",M42=""),"",IFERROR(INDEX($E$2:$E$391,MATCH(1,($A$2:$A$391=L42)*($D$2:$D$391=M42),0)),""))} | O42: =IF(OR(L42="",M42=""),"",SUMIFS($J$2:$J$391,$A$2:$A$391,L42,$D$2:$D$391,M42)) | Q42: {=IFERROR(INDEX($L$2:$L$391,MATCH(0,COUNTIF($Q$1:Q41,$L$2:$L$391)+IF($L$2:$L$391="",1,0),0)),"")} | R42: =IF(Q42="","",SUMIF($L$2:$L$391,Q42,$O$2:$O$391)) | S42: =IFERROR(Table3[[#This Row],[Price (€/kg)]]*HELPER!$AK$2," ")
A43: TIPA 302FG W | B43: Ext. B | D43: =IF(C43="","",IFERROR(_xlfn.XLOOKUP(C43,HELPER!$A$2:$A$76,HELPER!$B$2:$B$76,""),D43)) | E43: =IFERROR(_xlfn.XLOOKUP(D43,HELPER!$B:$B,HELPER!$C:$C,""),"") | F43: =IFERROR(_xlfn.XLOOKUP(D43,HELPER!$B:$B,HELPER!$D:$D,""),"") | G43: 24 | I43: =IF(AND(H43<>"",IFERROR(_xlfn.XLOOKUP(D43,HELPER!$B:$B,HELPER!$E:$E,""),"")=""),"Missing price",IFERROR(_xlfn.XLOOKUP(D43,HELPER!$B:$B,HELPER!$E:$E,"")," ")) | J43: =IFERROR(H43*(IF(G43=8,I43*HELPER!$G$2,BOM!I43*HELPER!$G$3))," ") | L43: {=IFERROR(_xlfn.LET(_xlpm.pairs,_xlfn._xlws.FILTER($A$2:$D$391,($A$2:$A$391<>"")*(TRIM($D$2:$D$391)<>"")),_xlpm.uniquePairs,_xlfn.UNIQUE(_xlfn.HSTACK(INDEX(_xlpm.pairs,,1),INDEX(_xlpm.pairs,,4))),_xlpm.sortedPairs,_xlfn._xlws.SORT(_xlpm.uniquePairs,1,1),IF(ROW()-1<=ROWS(_xlpm.sortedPairs),INDEX(_xlpm.sortedPairs,ROW()-1,1),"")),"")} | M43: {=IFERROR(_xlfn.LET(_xlpm.pairs,_xlfn._xlws.FILTER($A$2:$D$391,($A$2:$A$391<>"")*(TRIM($D$2:$D$391)<>"")),_xlpm.uniquePairs,_xlfn.UNIQUE(_xlfn.HSTACK(INDEX(_xlpm.pairs,,1),INDEX(_xlpm.pairs,,4))),_xlpm.sortedPairs,_xlfn._xlws.SORT(_xlpm.uniquePairs,1,1),IF(ROW()-1<=ROWS(_xlpm.sortedPairs),INDEX(_xlpm.sortedPairs,ROW()-1,2),"")),"")} | N43: {=IF(OR(L43="",M43=""),"",IFERROR(INDEX($E$2:$E$391,MATCH(1,($A$2:$A$391=L43)*($D$2:$D$391=M43),0)),""))} | O43: =IF(OR(L43="",M43=""),"",SUMIFS($J$2:$J$391,$A$2:$A$391,L43,$D$2:$D$391,M43)) | Q43: {=IFERROR(INDEX($L$2:$L$391,MATCH(0,COUNTIF($Q$1:Q42,$L$2:$L$391)+IF($L$2:$L$391="",1,0),0)),"")} | R43: =IF(Q43="","",SUMIF($L$2:$L$391,Q43,$O$2:$O$391)) | S43: =IFERROR(Table3[[#This Row],[Price (€/kg)]]*HELPER!$AK$2," ")
A44: TIPA 302FG W | B44: Ext. B | D44: =IF(C44="","",IFERROR(_xlfn.XLOOKUP(C44,HELPER!$A$2:$A$76,HELPER!$B$2:$B$76,""),D44)) | E44: =IFERROR(_xlfn.XLOOKUP(D44,HELPER!$B:$B,HELPER!$C:$C,""),"") | F44: =IFERROR(_xlfn.XLOOKUP(D44,HELPER!$B:$B,HELPER!$D:$D,""),"") | G44: 24 | I44: =IF(AND(H44<>"",IFERROR(_xlfn.XLOOKUP(D44,HELPER!$B:$B,HELPER!$E:$E,""),"")=""),"Missing price",IFERROR(_xlfn.XLOOKUP(D44,HELPER!$B:$B,HELPER!$E:$E,"")," ")) | J44: =IFERROR(H44*(IF(G44=8,I44*HELPER!$G$2,BOM!I44*HELPER!$G$3))," ") | L44: {=IFERROR(_xlfn.LET(_xlpm.pairs,_xlfn._xlws.FILTER($A$2:$D$391,($A$2:$A$391<>"")*(TRIM($D$2:$D$391)<>"")),_xlpm.uniquePairs,_xlfn.UNIQUE(_xlfn.HSTACK(INDEX(_xlpm.pairs,,1),INDEX(_xlpm.pairs,,4))),_xlpm.sortedPairs,_xlfn._xlws.SORT(_xlpm.uniquePairs,1,1),IF(ROW()-1<=ROWS(_xlpm.sortedPairs),INDEX(_xlpm.sortedPairs,ROW()-1,1),"")),"")} | M44: {=IFERROR(_xlfn.LET(_xlpm.pairs,_xlfn._xlws.FILTER($A$2:$D$391,($A$2:$A$391<>"")*(TRIM($D$2:$D$391)<>"")),_xlpm.uniquePairs,_xlfn.UNIQUE(_xlfn.HSTACK(INDEX(_xlpm.pairs,,1),INDEX(_xlpm.pairs,,4))),_xlpm.sortedPairs,_xlfn._xlws.SORT(_xlpm.uniquePairs,1,1),IF(ROW()-1<=ROWS(_xlpm.sortedPairs),INDEX(_xlpm.sortedPairs,ROW()-1,2),"")),"")} | N44: {=IF(OR(L44="",M44=""),"",IFERROR(INDEX($E$2:$E$391,MATCH(1,($A$2:$A$391=L44)*($D$2:$D$391=M44),0)),""))} | O44: =IF(OR(L44="",M44=""),"",SUMIFS($J$2:$J$391,$A$2:$A$391,L44,$D$2:$D$391,M44)) | Q44: {=IFERROR(INDEX($L$2:$L$391,MATCH(0,COUNTIF($Q$1:Q43,$L$2:$L$391)+IF($L$2:$L$391="",1,0),0)),"")} | R44: =IF(Q44="","",SUMIF($L$2:$L$391,Q44,$O$2:$O$391)) | S44: =IFERROR(Table3[[#This Row],[Price (€/kg)]]*HELPER!$AK$2," ")
A45: TIPA 302FG W | B45: Ext. B | C45: AO-PBS | D45: =IF(C45="","",IFERROR(_xlfn.XLOOKUP(C45,HELPER!$A$2:$A$76,HELPER!$B$2:$B$76,""),D45)) | E45: =IFERROR(_xlfn.XLOOKUP(D45,HELPER!$B:$B,HELPER!$C:$C,""),"") | F45: =IFERROR(_xlfn.XLOOKUP(D45,HELPER!$B:$B,HELPER!$D:$D,""),"") | G45: 24 | H45: 0.015 | I45: =IF(AND(H45<>"",IFERROR(_xlfn.XLOOKUP(D45,HELPER!$B:$B,HELPER!$E:$E,""),"")=""),"Missing price",IFERROR(_xlfn.XLOOKUP(D45,HELPER!$B:$B,HELPER!$E:$E,"")," ")) | J45: =IFERROR(H45*(IF(G45=8,I45*HELPER!$G$2,BOM!I45*HELPER!$G$3))," ") | L45: {=IFERROR(_xlfn.LET(_xlpm.pairs,_xlfn._xlws.FILTER($A$2:$D$391,($A$2:$A$391<>"")*(TRIM($D$2:$D$391)<>"")),_xlpm.uniquePairs,_xlfn.UNIQUE(_xlfn.HSTACK(INDEX(_xlpm.pairs,,1),INDEX(_xlpm.pairs,,4))),_xlpm.sortedPairs,_xlfn._xlws.SORT(_xlpm.uniquePairs,1,1),IF(ROW()-1<=ROWS(_xlpm.sortedPairs),INDEX(_xlpm.sortedPairs,ROW()-1,1),"")),"")} | M45: {=IFERROR(_xlfn.LET(_xlpm.pairs,_xlfn._xlws.FILTER($A$2:$D$391,($A$2:$A$391<>"")*(TRIM($D$2:$D$391)<>"")),_xlpm.uniquePairs,_xlfn.UNIQUE(_xlfn.HSTACK(INDEX(_xlpm.pairs,,1),INDEX(_xlpm.pairs,,4))),_xlpm.sortedPairs,_xlfn._xlws.SORT(_xlpm.uniquePairs,1,1),IF(ROW()-1<=ROWS(_xlpm.sortedPairs),INDEX(_xlpm.sortedPairs,ROW()-1,2),"")),"")} | N45: {=IF(OR(L45="",M45=""),"",IFERROR(INDEX($E$2:$E$391,MATCH(1,($A$2:$A$391=L45)*($D$2:$D$391=M45),0)),""))} | O45: =IF(OR(L45="",M45=""),"",SUMIFS($J$2:$J$391,$A$2:$A$391,L45,$D$2:$D$391,M45)) | Q45: {=IFERROR(INDEX($L$2:$L$391,MATCH(0,COUNTIF($Q$1:Q44,$L$2:$L$391)+IF($L$2:$L$391="",1,0),0)),"")} | R45: =IF(Q45="","",SUMIF($L$2:$L$391,Q45,$O$2:$O$391)) | S45: =IFERROR(Table3[[#This Row],[Price (€/kg)]]*HELPER!$AK$2," ")
A46: TIPA 302FG W | B46: Ext. B | C46: ECOMP WHITE | D46: =IF(C46="","",IFERROR(_xlfn.XLOOKUP(C46,HELPER!$A$2:$A$76,HELPER!$B$2:$B$76,""),D46)) | E46: =IFERROR(_xlfn.XLOOKUP(D46,HELPER!$B:$B,HELPER!$C:$C,""),"") | F46: =IFERROR(_xlfn.XLOOKUP(D46,HELPER!$B:$B,HELPER!$D:$D,""),"") | G46: 24 | H46: 0.1 | I46: =IF(AND(H46<>"",IFERROR(_xlfn.XLOOKUP(D46,HELPER!$B:$B,HELPER!$E:$E,""),"")=""),"Missing price",IFERROR(_xlfn.XLOOKUP(D46,HELPER!$B:$B,HELPER!$E:$E,"")," ")) | J46: =IFERROR(H46*(IF(G46=8,I46*HELPER!$G$2,BOM!I46*HELPER!$G$3))," ") | L46: {=IFERROR(_xlfn.LET(_xlpm.pairs,_xlfn._xlws.FILTER($A$2:$D$391,($A$2:$A$391<>"")*(TRIM($D$2:$D$391)<>"")),_xlpm.uniquePairs,_xlfn.UNIQUE(_xlfn.HSTACK(INDEX(_xlpm.pairs,,1),INDEX(_xlpm.pairs,,4))),_xlpm.sortedPairs,_xlfn._xlws.SORT(_xlpm.uniquePairs,1,1),IF(ROW()-1<=ROWS(_xlpm.sortedPairs),INDEX(_xlpm.sortedPairs,ROW()-1,1),"")),"")} | M46: {=IFERROR(_xlfn.LET(_xlpm.pairs,_xlfn._xlws.FILTER($A$2:$D$391,($A$2:$A$391<>"")*(TRIM($D$2:$D$391)<>"")),_xlpm.uniquePairs,_xlfn.UNIQUE(_xlfn.HSTACK(INDEX(_xlpm.pairs,,1),INDEX(_xlpm.pairs,,4))),_xlpm.sortedPairs,_xlfn._xlws.SORT(_xlpm.uniquePairs,1,1),IF(ROW()-1<=ROWS(_xlpm.sortedPairs),INDEX(_xlpm.sortedPairs,ROW()-1,2),"")),"")} | N46: {=IF(OR(L46="",M46=""),"",IFERROR(INDEX($E$2:$E$391,MATCH(1,($A$2:$A$391=L46)*($D$2:$D$391=M46),0)),""))} | O46: =IF(OR(L46="",M46=""),"",SUMIFS($J$2:$J$391,$A$2:$A$391,L46,$D$2:$D$391,M46)) | Q46: {=IFERROR(INDEX($L$2:$L$391,MATCH(0,COUNTIF($Q$1:Q45,$L$2:$L$391)+IF($L$2:$L$391="",1,0),0)),"")} | R46: =IF(Q46="","",SUMIF($L$2:$L$391,Q46,$O$2:$O$391)) | S46: =IFERROR(Table3[[#This Row],[Price (€/kg)]]*HELPER!$AK$2," ")
A47: TIPA 302FG W | B47: Ext. B | C47: SLAB-PBSA | D47: =IF(C47="","",IFERROR(_xlfn.XLOOKUP(C47,HELPER!$A$2:$A$76,HELPER!$B$2:$B$76,""),D47)) | E47: =IFERROR(_xlfn.XLOOKUP(D47,HELPER!$B:$B,HELPER!$C:$C,""),"") | F47: =IFERROR(_xlfn.XLOOKUP(D47,HELPER!$B:$B,HELPER!$D:$D,""),"") | G47: 24 | I47: =IF(AND(H47<>"",IFERROR(_xlfn.XLOOKUP(D47,HELPER!$B:$B,HELPER!$E:$E,""),"")=""),"Missing price",IFERROR(_xlfn.XLOOKUP(D47,HELPER!$B:$B,HELPER!$E:$E,"")," ")) | J47: =IFERROR(H47*(IF(G47=8,I47*HELPER!$G$2,BOM!I47*HELPER!$G$3))," ") | L47: {=IFERROR(_xlfn.LET(_xlpm.pairs,_xlfn._xlws.FILTER($A$2:$D$391,($A$2:$A$391<>"")*(TRIM($D$2:$D$391)<>"")),_xlpm.uniquePairs,_xlfn.UNIQUE(_xlfn.HSTACK(INDEX(_xlpm.pairs,,1),INDEX(_xlpm.pairs,,4))),_xlpm.sortedPairs,_xlfn._xlws.SORT(_xlpm.uniquePairs,1,1),IF(ROW()-1<=ROWS(_xlpm.sortedPairs),INDEX(_xlpm.sortedPairs,ROW()-1,1),"")),"")} | M47: {=IFERROR(_xlfn.LET(_xlpm.pairs,_xlfn._xlws.FILTER($A$2:$D$391,($A$2:$A$391<>"")*(TRIM($D$2:$D$391)<>"")),_xlpm.uniquePairs,_xlfn.UNIQUE(_xlfn.HSTACK(INDEX(_xlpm.pairs,,1),INDEX(_xlpm.pairs,,4))),_xlpm.sortedPairs,_xlfn._xlws.SORT(_xlpm.uniquePairs,1,1),IF(ROW()-1<=ROWS(_xlpm.sortedPairs),INDEX(_xlpm.sortedPairs,ROW()-1,2),"")),"")} | N47: {=IF(OR(L47="",M47=""),"",IFERROR(INDEX($E$2:$E$391,MATCH(1,($A$2:$A$391=L47)*($D$2:$D$391=M47),0)),""))} | O47: =IF(OR(L47="",M47=""),"",SUMIFS($J$2:$J$391,$A$2:$A$391,L47,$D$2:$D$391,M47)) | Q47: {=IFERROR(INDEX($L$2:$L$391,MATCH(0,COUNTIF($Q$1:Q46,$L$2:$L$391)+IF($L$2:$L$391="",1,0),0)),"")} | R47: =IF(Q47="","",SUMIF($L$2:$L$391,Q47,$O$2:$O$391)) | S47: =IFERROR(Table3[[#This Row],[Price (€/kg)]]*HELPER!$AK$2," ")
A48: TIPA 302FG W | B48: Ext. B | C48: PBAT | D48: =IF(C48="","",IFERROR(_xlfn.XLOOKUP(C48,HELPER!$A$2:$A$76,HELPER!$B$2:$B$76,""),D48)) | E48: =IFERROR(_xlfn.XLOOKUP(D48,HELPER!$B:$B,HELPER!$C:$C,""),"") | F48: =IFERROR(_xlfn.XLOOKUP(D48,HELPER!$B:$B,HELPER!$D:$D,""),"") | G48: 24 | H48: 0.885 | I48: =IF(AND(H48<>"",IFERROR(_xlfn.XLOOKUP(D48,HELPER!$B:$B,HELPER!$E:$E,""),"")=""),"Missing price",IFERROR(_xlfn.XLOOKUP(D48,HELPER!$B:$B,HELPER!$E:$E,"")," ")) | J48: =IFERROR(H48*(IF(G48=8,I48*HELPER!$G$2,BOM!I48*HELPER!$G$3))," ") | L48: {=IFERROR(_xlfn.LET(_xlpm.pairs,_xlfn._xlws.FILTER($A$2:$D$391,($A$2:$A$391<>"")*(TRIM($D$2:$D$391)<>"")),_xlpm.uniquePairs,_xlfn.UNIQUE(_xlfn.HSTACK(INDEX(_xlpm.pairs,,1),INDEX(_xlpm.pairs,,4))),_xlpm.sortedPairs,_xlfn._xlws.SORT(_xlpm.uniquePairs,1,1),IF(ROW()-1<=ROWS(_xlpm.sortedPairs),INDEX(_xlpm.sortedPairs,ROW()-1,1),"")),"")} | M48: {=IFERROR(_xlfn.LET(_xlpm.pairs,_xlfn._xlws.FILTER($A$2:$D$391,($A$2:$A$391<>"")*(TRIM($D$2:$D$391)<>"")),_xlpm.uniquePairs,_xlfn.UNIQUE(_xlfn.HSTACK(INDEX(_xlpm.pairs,,1),INDEX(_xlpm.pairs,,4))),_xlpm.sortedPairs,_xlfn._xlws.SORT(_xlpm.uniquePairs,1,1),IF(ROW()-1<=ROWS(_xlpm.sortedPairs),INDEX(_xlpm.sortedPairs,ROW()-1,2),"")),"")} | N48: {=IF(OR(L48="",M48=""),"",IFERROR(INDEX($E$2:$E$391,MATCH(1,($A$2:$A$391=L48)*($D$2:$D$391=M48),0)),""))} | O48: =IF(OR(L48="",M48=""),"",SUMIFS($J$2:$J$391,$A$2:$A$391,L48,$D$2:$D$391,M48)) | Q48: {=IFERROR(INDEX($L$2:$L$391,MATCH(0,COUNTIF($Q$1:Q47,$L$2:$L$391)+IF($L$2:$L$391="",1,0),0)),"")} | R48: =IF(Q48="","",SUMIF($L$2:$L$391,Q48,$O$2:$O$391)) | S48: =IFERROR(Table3[[#This Row],[Price (€/kg)]]*HELPER!$AK$2," ")
A49: TIPA 302FG W | B49: Ext. B | D49: =IF(C49="","",IFERROR(_xlfn.XLOOKUP(C49,HELPER!$A$2:$A$76,HELPER!$B$2:$B$76,""),D49)) | E49: =IFERROR(_xlfn.XLOOKUP(D49,HELPER!$B:$B,HELPER!$C:$C,""),"") | F49: =IFERROR(_xlfn.XLOOKUP(D49,HELPER!$B:$B,HELPER!$D:$D,""),"") | G49: 24 | I49: =IF(AND(H49<>"",IFERROR(_xlfn.XLOOKUP(D49,HELPER!$B:$B,HELPER!$E:$E,""),"")=""),"Missing price",IFERROR(_xlfn.XLOOKUP(D49,HELPER!$B:$B,HELPER!$E:$E,"")," ")) | J49: =IFERROR(H49*(IF(G49=8,I49*HELPER!$G$2,BOM!I49*HELPER!$G$3))," ") | L49: {=IFERROR(_xlfn.LET(_xlpm.pairs,_xlfn._xlws.FILTER($A$2:$D$391,($A$2:$A$391<>"")*(TRIM($D$2:$D$391)<>"")),_xlpm.uniquePairs,_xlfn.UNIQUE(_xlfn.HSTACK(INDEX(_xlpm.pairs,,1),INDEX(_xlpm.pairs,,4))),_xlpm.sortedPairs,_xlfn._xlws.SORT(_xlpm.uniquePairs,1,1),IF(ROW()-1<=ROWS(_xlpm.sortedPairs),INDEX(_xlpm.sortedPairs,ROW()-1,1),"")),"")} | M49: {=IFERROR(_xlfn.LET(_xlpm.pairs,_xlfn._xlws.FILTER($A$2:$D$391,($A$2:$A$391<>"")*(TRIM($D$2:$D$391)<>"")),_xlpm.uniquePairs,_xlfn.UNIQUE(_xlfn.HSTACK(INDEX(_xlpm.pairs,,1),INDEX(_xlpm.pairs,,4))),_xlpm.sortedPairs,_xlfn._xlws.SORT(_xlpm.uniquePairs,1,1),IF(ROW()-1<=ROWS(_xlpm.sortedPairs),INDEX(_xlpm.sortedPairs,ROW()-1,2),"")),"")} | N49: {=IF(OR(L49="",M49=""),"",IFERROR(INDEX($E$2:$E$391,MATCH(1,($A$2:$A$391=L49)*($D$2:$D$391=M49),0)),""))} | O49: =IF(OR(L49="",M49=""),"",SUMIFS($J$2:$J$391,$A$2:$A$391,L49,$D$2:$D$391,M49)) | Q49: {=IFERROR(INDEX($L$2:$L$391,MATCH(0,COUNTIF($Q$1:Q48,$L$2:$L$391)+IF($L$2:$L$391="",1,0),0)),"")} | R49: =IF(Q49="","",SUMIF($L$2:$L$391,Q49,$O$2:$O$391)) | S49: =IFERROR(Table3[[#This Row],[Price (€/kg)]]*HELPER!$AK$2," ")
A50: TIPA 302FG W | B50: Ext. B | D50: =IF(C50="","",IFERROR(_xlfn.XLOOKUP(C50,HELPER!$A$2:$A$76,HELPER!$B$2:$B$76,""),D50)) | E50: =IFERROR(_xlfn.XLOOKUP(D50,HELPER!$B:$B,HELPER!$C:$C,""),"") | F50: =IFERROR(_xlfn.XLOOKUP(D50,HELPER!$B:$B,HELPER!$D:$D,""),"") | G50: 24 | I50: =IF(AND(H50<>"",IFERROR(_xlfn.XLOOKUP(D50,HELPER!$B:$B,HELPER!$E:$E,""),"")=""),"Missing price",IFERROR(_xlfn.XLOOKUP(D50,HELPER!$B:$B,HELPER!$E:$E,"")," ")) | J50: =IFERROR(H50*(IF(G50=8,I50*HELPER!$G$2,BOM!I50*HELPER!$G$3))," ") | L50: {=IFERROR(_xlfn.LET(_xlpm.pairs,_xlfn._xlws.FILTER($A$2:$D$391,($A$2:$A$391<>"")*(TRIM($D$2:$D$391)<>"")),_xlpm.uniquePairs,_xlfn.UNIQUE(_xlfn.HSTACK(INDEX(_xlpm.pairs,,1),INDEX(_xlpm.pairs,,4))),_xlpm.sortedPairs,_xlfn._xlws.SORT(_xlpm.uniquePairs,1,1),IF(ROW()-1<=ROWS(_xlpm.sortedPairs),INDEX(_xlpm.sortedPairs,ROW()-1,1),"")),"")} | M50: {=IFERROR(_xlfn.LET(_xlpm.pairs,_xlfn._xlws.FILTER($A$2:$D$391,($A$2:$A$391<>"")*(TRIM($D$2:$D$391)<>"")),_xlpm.uniquePairs,_xlfn.UNIQUE(_xlfn.HSTACK(INDEX(_xlpm.pairs,,1),INDEX(_xlpm.pairs,,4))),_xlpm.sortedPairs,_xlfn._xlws.SORT(_xlpm.uniquePairs,1,1),IF(ROW()-1<=ROWS(_xlpm.sortedPairs),INDEX(_xlpm.sortedPairs,ROW()-1,2),"")),"")} | N50: {=IF(OR(L50="",M50=""),"",IFERROR(INDEX($E$2:$E$391,MATCH(1,($A$2:$A$391=L50)*($D$2:$D$391=M50),0)),""))} | O50: =IF(OR(L50="",M50=""),"",SUMIFS($J$2:$J$391,$A$2:$A$391,L50,$D$2:$D$391,M50)) | Q50: {=IFERROR(INDEX($L$2:$L$391,MATCH(0,COUNTIF($Q$1:Q49,$L$2:$L$391)+IF($L$2:$L$391="",1,0),0)),"")} | R50: =IF(Q50="","",SUMIF($L$2:$L$391,Q50,$O$2:$O$391)) | S50: =IFERROR(Table3[[#This Row],[Price (€/kg)]]*HELPER!$AK$2," ")
A51: TIPA 302FG W | B51: Ext. B | D51: =IF(C51="","",IFERROR(_xlfn.XLOOKUP(C51,HELPER!$A$2:$A$76,HELPER!$B$2:$B$76,""),D51)) | E51: =IFERROR(_xlfn.XLOOKUP(D51,HELPER!$B:$B,HELPER!$C:$C,""),"") | F51: =IFERROR(_xlfn.XLOOKUP(D51,HELPER!$B:$B,HELPER!$D:$D,""),"") | G51: 24 | I51: =IF(AND(H51<>"",IFERROR(_xlfn.XLOOKUP(D51,HELPER!$B:$B,HELPER!$E:$E,""),"")=""),"Missing price",IFERROR(_xlfn.XLOOKUP(D51,HELPER!$B:$B,HELPER!$E:$E,"")," ")) | J51: =IFERROR(H51*(IF(G51=8,I51*HELPER!$G$2,BOM!I51*HELPER!$G$3))," ") | L51: {=IFERROR(_xlfn.LET(_xlpm.pairs,_xlfn._xlws.FILTER($A$2:$D$391,($A$2:$A$391<>"")*(TRIM($D$2:$D$391)<>"")),_xlpm.uniquePairs,_xlfn.UNIQUE(_xlfn.HSTACK(INDEX(_xlpm.pairs,,1),INDEX(_xlpm.pairs,,4))),_xlpm.sortedPairs,_xlfn._xlws.SORT(_xlpm.uniquePairs,1,1),IF(ROW()-1<=ROWS(_xlpm.sortedPairs),INDEX(_xlpm.sortedPairs,ROW()-1,1),"")),"")} | M51: {=IFERROR(_xlfn.LET(_xlpm.pairs,_xlfn._xlws.FILTER($A$2:$D$391,($A$2:$A$391<>"")*(TRIM($D$2:$D$391)<>"")),_xlpm.uniquePairs,_xlfn.UNIQUE(_xlfn.HSTACK(INDEX(_xlpm.pairs,,1),INDEX(_xlpm.pairs,,4))),_xlpm.sortedPairs,_xlfn._xlws.SORT(_xlpm.uniquePairs,1,1),IF(ROW()-1<=ROWS(_xlpm.sortedPairs),INDEX(_xlpm.sortedPairs,ROW()-1,2),"")),"")} | N51: {=IF(OR(L51="",M51=""),"",IFERROR(INDEX($E$2:$E$391,MATCH(1,($A$2:$A$391=L51)*($D$2:$D$391=M51),0)),""))} | O51: =IF(OR(L51="",M51=""),"",SUMIFS($J$2:$J$391,$A$2:$A$391,L51,$D$2:$D$391,M51))
A52: TIPA 302FG W | B52: Ext. C (In) | C52: PBSA | D52: =IF(C52="","",IFERROR(_xlfn.XLOOKUP(C52,HELPER!$A$2:$A$76,HELPER!$B$2:$B$76,""),D52)) | E52: =IFERROR(_xlfn.XLOOKUP(D52,HELPER!$B:$B,HELPER!$C:$C,""),"") | F52: =IFERROR(_xlfn.XLOOKUP(D52,HELPER!$B:$B,HELPER!$D:$D,""),"") | G52: 8 | H52: 0.81 | I52: =IF(AND(H52<>"",IFERROR(_xlfn.XLOOKUP(D52,HELPER!$B:$B,HELPER!$E:$E,""),"")=""),"Missing price",IFERROR(_xlfn.XLOOKUP(D52,HELPER!$B:$B,HELPER!$E:$E,"")," ")) | J52: =IFERROR(H52*(IF(G52=8,I52*HELPER!$G$2,BOM!I52*HELPER!$G$3))," ") | L52: {=IFERROR(_xlfn.LET(_xlpm.pairs,_xlfn._xlws.FILTER($A$2:$D$391,($A$2:$A$391<>"")*(TRIM($D$2:$D$391)<>"")),_xlpm.uniquePairs,_xlfn.UNIQUE(_xlfn.HSTACK(INDEX(_xlpm.pairs,,1),INDEX(_xlpm.pairs,,4))),_xlpm.sortedPairs,_xlfn._xlws.SORT(_xlpm.uniquePairs,1,1),IF(ROW()-1<=ROWS(_xlpm.sortedPairs),INDEX(_xlpm.sortedPairs,ROW()-1,1),"")),"")} | M52: {=IFERROR(_xlfn.LET(_xlpm.pairs,_xlfn._xlws.FILTER($A$2:$D$391,($A$2:$A$391<>"")*(TRIM($D$2:$D$391)<>"")),_xlpm.uniquePairs,_xlfn.UNIQUE(_xlfn.HSTACK(INDEX(_xlpm.pairs,,1),INDEX(_xlpm.pairs,,4))),_xlpm.sortedPairs,_xlfn._xlws.SORT(_xlpm.uniquePairs,1,1),IF(ROW()-1<=ROWS(_xlpm.sortedPairs),INDEX(_xlpm.sortedPairs,ROW()-1,2),"")),"")} | N52: {=IF(OR(L52="",M52=""),"",IFERROR(INDEX($E$2:$E$391,MATCH(1,($A$2:$A$391=L52)*($D$2:$D$391=M52),0)),""))} | O52: =IF(OR(L52="",M52=""),"",SUMIFS($J$2:$J$391,$A$2:$A$391,L52,$D$2:$D$391,M52))
A53: TIPA 302FG W | B53: Ext. C (In) | C53: PLA | D53: =IF(C53="","",IFERROR(_xlfn.XLOOKUP(C53,HELPER!$A$2:$A$76,HELPER!$B$2:$B$76,""),D53)) | E53: =IFERROR(_xlfn.XLOOKUP(D53,HELPER!$B:$B,HELPER!$C:$C,""),"") | F53: =IFERROR(_xlfn.XLOOKUP(D53,HELPER!$B:$B,HELPER!$D:$D,""),"") | G53: 8 | H53: 0.144 | I53: =IF(AND(H53<>"",IFERROR(_xlfn.XLOOKUP(D53,HELPER!$B:$B,HELPER!$E:$E,""),"")=""),"Missing price",IFERROR(_xlfn.XLOOKUP(D53,HELPER!$B:$B,HELPER!$E:$E,"")," ")) | J53: =IFERROR(H53*(IF(G53=8,I53*HELPER!$G$2,BOM!I53*HELPER!$G$3))," ") | L53: {=IFERROR(_xlfn.LET(_xlpm.pairs,_xlfn._xlws.FILTER($A$2:$D$391,($A$2:$A$391<>"")*(TRIM($D$2:$D$391)<>"")),_xlpm.uniquePairs,_xlfn.UNIQUE(_xlfn.HSTACK(INDEX(_xlpm.pairs,,1),INDEX(_xlpm.pairs,,4))),_xlpm.sortedPairs,_xlfn._xlws.SORT(_xlpm.uniquePairs,1,1),IF(ROW()-1<=ROWS(_xlpm.sortedPairs),INDEX(_xlpm.sortedPairs,ROW()-1,1),"")),"")} | M53: {=IFERROR(_xlfn.LET(_xlpm.pairs,_xlfn._xlws.FILTER($A$2:$D$391,($A$2:$A$391<>"")*(TRIM($D$2:$D$391)<>"")),_xlpm.uniquePairs,_xlfn.UNIQUE(_xlfn.HSTACK(INDEX(_xlpm.pairs,,1),INDEX(_xlpm.pairs,,4))),_xlpm.sortedPairs,_xlfn._xlws.SORT(_xlpm.uniquePairs,1,1),IF(ROW()-1<=ROWS(_xlpm.sortedPairs),INDEX(_xlpm.sortedPairs,ROW()-1,2),"")),"")} | N53: {=IF(OR(L53="",M53=""),"",IFERROR(INDEX($E$2:$E$391,MATCH(1,($A$2:$A$391=L53)*($D$2:$D$391=M53),0)),""))} | O53: =IF(OR(L53="",M53=""),"",SUMIFS($J$2:$J$391,$A$2:$A$391,L53,$D$2:$D$391,M53))
A54: TIPA 302FG W | B54: Ext. C (In) | C54: AB-PLA | D54: =IF(C54="","",IFERROR(_xlfn.XLOOKUP(C54,HELPER!$A$2:$A$76,HELPER!$B$2:$B$76,""),D54)) | E54: =IFERROR(_xlfn.XLOOKUP(D54,HELPER!$B:$B,HELPER!$C:$C,""),"") | F54: =IFERROR(_xlfn.XLOOKUP(D54,HELPER!$B:$B,HELPER!$D:$D,""),"") | G54: 8 | H54: 0.015 | I54: =IF(AND(H54<>"",IFERROR(_xlfn.XLOOKUP(D54,HELPER!$B:$B,HELPER!$E:$E,""),"")=""),"Missing price",IFERROR(_xlfn.XLOOKUP(D54,HELPER!$B:$B,HELPER!$E:$E,"")," ")) | J54: =IFERROR(H54*(IF(G54=8,I54*HELPER!$G$2,BOM!I54*HELPER!$G$3))," ") | L54: {=IFERROR(_xlfn.LET(_xlpm.pairs,_xlfn._xlws.FILTER($A$2:$D$391,($A$2:$A$391<>"")*(TRIM($D$2:$D$391)<>"")),_xlpm.uniquePairs,_xlfn.UNIQUE(_xlfn.HSTACK(INDEX(_xlpm.pairs,,1),INDEX(_xlpm.pairs,,4))),_xlpm.sortedPairs,_xlfn._xlws.SORT(_xlpm.uniquePairs,1,1),IF(ROW()-1<=ROWS(_xlpm.sortedPairs),INDEX(_xlpm.sortedPairs,ROW()-1,1),"")),"")} | M54: {=IFERROR(_xlfn.LET(_xlpm.pairs,_xlfn._xlws.FILTER($A$2:$D$391,($A$2:$A$391<>"")*(TRIM($D$2:$D$391)<>"")),_xlpm.uniquePairs,_xlfn.UNIQUE(_xlfn.HSTACK(INDEX(_xlpm.pairs,,1),INDEX(_xlpm.pairs,,4))),_xlpm.sortedPairs,_xlfn._xlws.SORT(_xlpm.uniquePairs,1,1),IF(ROW()-1<=ROWS(_xlpm.sortedPairs),INDEX(_xlpm.sortedPairs,ROW()-1,2),"")),"")} | N54: {=IF(OR(L54="",M54=""),"",IFERROR(INDEX($E$2:$E$391,MATCH(1,($A$2:$A$391=L54)*($D$2:$D$391=M54),0)),""))} | O54: =IF(OR(L54="",M54=""),"",SUMIFS($J$2:$J$391,$A$2:$A$391,L54,$D$2:$D$391,M54))
A55: TIPA 302FG W | B55: Ext. C (In) | C55: AO-PBS | D55: =IF(C55="","",IFERROR(_xlfn.XLOOKUP(C55,HELPER!$A$2:$A$76,HELPER!$B$2:$B$76,""),D55)) | E55: =IFERROR(_xlfn.XLOOKUP(D55,HELPER!$B:$B,HELPER!$C:$C,""),"") | F55: =IFERROR(_xlfn.XLOOKUP(D55,HELPER!$B:$B,HELPER!$D:$D,""),"") | G55: 8 | H55: 0.015 | I55: =IF(AND(H55<>"",IFERROR(_xlfn.XLOOKUP(D55,HELPER!$B:$B,HELPER!$E:$E,""),"")=""),"Missing price",IFERROR(_xlfn.XLOOKUP(D55,HELPER!$B:$B,HELPER!$E:$E,"")," ")) | J55: =IFERROR(H55*(IF(G55=8,I55*HELPER!$G$2,BOM!I55*HELPER!$G$3))," ") | L55: {=IFERROR(_xlfn.LET(_xlpm.pairs,_xlfn._xlws.FILTER($A$2:$D$391,($A$2:$A$391<>"")*(TRIM($D$2:$D$391)<>"")),_xlpm.uniquePairs,_xlfn.UNIQUE(_xlfn.HSTACK(INDEX(_xlpm.pairs,,1),INDEX(_xlpm.pairs,,4))),_xlpm.sortedPairs,_xlfn._xlws.SORT(_xlpm.uniquePairs,1,1),IF(ROW()-1<=ROWS(_xlpm.sortedPairs),INDEX(_xlpm.sortedPairs,ROW()-1,1),"")),"")} | M55: {=IFERROR(_xlfn.LET(_xlpm.pairs,_xlfn._xlws.FILTER($A$2:$D$391,($A$2:$A$391<>"")*(TRIM($D$2:$D$391)<>"")),_xlpm.uniquePairs,_xlfn.UNIQUE(_xlfn.HSTACK(INDEX(_xlpm.pairs,,1),INDEX(_xlpm.pairs,,4))),_xlpm.sortedPairs,_xlfn._xlws.SORT(_xlpm.uniquePairs,1,1),IF(ROW()-1<=ROWS(_xlpm.sortedPairs),INDEX(_xlpm.sortedPairs,ROW()-1,2),"")),"")} | N55: {=IF(OR(L55="",M55=""),"",IFERROR(INDEX($E$2:$E$391,MATCH(1,($A$2:$A$391=L55)*($D$2:$D$391=M55),0)),""))} | O55: =IF(OR(L55="",M55=""),"",SUMIFS($J$2:$J$391,$A$2:$A$391,L55,$D$2:$D$391,M55))
A56: TIPA 302FG W | B56: Ext. C (In) | C56: SLAB-PBSA | D56: =IF(C56="","",IFERROR(_xlfn.XLOOKUP(C56,HELPER!$A$2:$A$76,HELPER!$B$2:$B$76,""),D56)) | E56: =IFERROR(_xlfn.XLOOKUP(D56,HELPER!$B:$B,HELPER!$C:$C,""),"") | F56: =IFERROR(_xlfn.XLOOKUP(D56,HELPER!$B:$B,HELPER!$D:$D,""),"") | G56: 8 | H56: 0.016 | I56: =IF(AND(H56<>"",IFERROR(_xlfn.XLOOKUP(D56,HELPER!$B:$B,HELPER!$E:$E,""),"")=""),"Missing price",IFERROR(_xlfn.XLOOKUP(D56,HELPER!$B:$B,HELPER!$E:$E,"")," ")) | J56: =IFERROR(H56*(IF(G56=8,I56*HELPER!$G$2,BOM!I56*HELPER!$G$3))," ") | L56: {=IFERROR(_xlfn.LET(_xlpm.pairs,_xlfn._xlws.FILTER($A$2:$D$391,($A$2:$A$391<>"")*(TRIM($D$2:$D$391)<>"")),_xlpm.uniquePairs,_xlfn.UNIQUE(_xlfn.HSTACK(INDEX(_xlpm.pairs,,1),INDEX(_xlpm.pairs,,4))),_xlpm.sortedPairs,_xlfn._xlws.SORT(_xlpm.uniquePairs,1,1),IF(ROW()-1<=ROWS(_xlpm.sortedPairs),INDEX(_xlpm.sortedPairs,ROW()-1,1),"")),"")} | M56: {=IFERROR(_xlfn.LET(_xlpm.pairs,_xlfn._xlws.FILTER($A$2:$D$391,($A$2:$A$391<>"")*(TRIM($D$2:$D$391)<>"")),_xlpm.uniquePairs,_xlfn.UNIQUE(_xlfn.HSTACK(INDEX(_xlpm.pairs,,1),INDEX(_xlpm.pairs,,4))),_xlpm.sortedPairs,_xlfn._xlws.SORT(_xlpm.uniquePairs,1,1),IF(ROW()-1<=ROWS(_xlpm.sortedPairs),INDEX(_xlpm.sortedPairs,ROW()-1,2),"")),"")} | N56: {=IF(OR(L56="",M56=""),"",IFERROR(INDEX($E$2:$E$391,MATCH(1,($A$2:$A$391=L56)*($D$2:$D$391=M56),0)),""))} | O56: =IF(OR(L56="",M56=""),"",SUMIFS($J$2:$J$391,$A$2:$A$391,L56,$D$2:$D$391,M56))
A57: TIPA 302FG W | B57: Ext. C (In) | D57: =IF(C57="","",IFERROR(_xlfn.XLOOKUP(C57,HELPER!$A$2:$A$76,HELPER!$B$2:$B$76,""),D57)) | E57: =IFERROR(_xlfn.XLOOKUP(D57,HELPER!$B:$B,HELPER!$C:$C,""),"") | F57: =IFERROR(_xlfn.XLOOKUP(D57,HELPER!$B:$B,HELPER!$D:$D,""),"") | G57: 8 | I57: =IF(AND(H57<>"",IFERROR(_xlfn.XLOOKUP(D57,HELPER!$B:$B,HELPER!$E:$E,""),"")=""),"Missing price",IFERROR(_xlfn.XLOOKUP(D57,HELPER!$B:$B,HELPER!$E:$E,"")," ")) | J57: =IFERROR(H57*(IF(G57=8,I57*HELPER!$G$2,BOM!I57*HELPER!$G$3))," ") | L57: {=IFERROR(_xlfn.LET(_xlpm.pairs,_xlfn._xlws.FILTER($A$2:$D$391,($A$2:$A$391<>"")*(TRIM($D$2:$D$391)<>"")),_xlpm.uniquePairs,_xlfn.UNIQUE(_xlfn.HSTACK(INDEX(_xlpm.pairs,,1),INDEX(_xlpm.pairs,,4))),_xlpm.sortedPairs,_xlfn._xlws.SORT(_xlpm.uniquePairs,1,1),IF(ROW()-1<=ROWS(_xlpm.sortedPairs),INDEX(_xlpm.sortedPairs,ROW()-1,1),"")),"")} | M57: {=IFERROR(_xlfn.LET(_xlpm.pairs,_xlfn._xlws.FILTER($A$2:$D$391,($A$2:$A$391<>"")*(TRIM($D$2:$D$391)<>"")),_xlpm.uniquePairs,_xlfn.UNIQUE(_xlfn.HSTACK(INDEX(_xlpm.pairs,,1),INDEX(_xlpm.pairs,,4))),_xlpm.sortedPairs,_xlfn._xlws.SORT(_xlpm.uniquePairs,1,1),IF(ROW()-1<=ROWS(_xlpm.sortedPairs),INDEX(_xlpm.sortedPairs,ROW()-1,2),"")),"")} | N57: {=IF(OR(L57="",M57=""),"",IFERROR(INDEX($E$2:$E$391,MATCH(1,($A$2:$A$391=L57)*($D$2:$D$391=M57),0)),""))} | O57: =IF(OR(L57="",M57=""),"",SUMIFS($J$2:$J$391,$A$2:$A$391,L57,$D$2:$D$391,M57))
A58: TIPA 302FG W | B58: Ext. C (In) | D58: =IF(C58="","",IFERROR(_xlfn.XLOOKUP(C58,HELPER!$A$2:$A$76,HELPER!$B$2:$B$76,""),D58)) | E58: =IFERROR(_xlfn.XLOOKUP(D58,HELPER!$B:$B,HELPER!$C:$C,""),"") | F58: =IFERROR(_xlfn.XLOOKUP(D58,HELPER!$B:$B,HELPER!$D:$D,""),"") | G58: 8 | I58: =IF(AND(H58<>"",IFERROR(_xlfn.XLOOKUP(D58,HELPER!$B:$B,HELPER!$E:$E,""),"")=""),"Missing price",IFERROR(_xlfn.XLOOKUP(D58,HELPER!$B:$B,HELPER!$E:$E,"")," ")) | J58: =IFERROR(H58*(IF(G58=8,I58*HELPER!$G$2,BOM!I58*HELPER!$G$3))," ") | L58: {=IFERROR(_xlfn.LET(_xlpm.pairs,_xlfn._xlws.FILTER($A$2:$D$391,($A$2:$A$391<>"")*(TRIM($D$2:$D$391)<>"")),_xlpm.uniquePairs,_xlfn.UNIQUE(_xlfn.HSTACK(INDEX(_xlpm.pairs,,1),INDEX(_xlpm.pairs,,4))),_xlpm.sortedPairs,_xlfn._xlws.SORT(_xlpm.uniquePairs,1,1),IF(ROW()-1<=ROWS(_xlpm.sortedPairs),INDEX(_xlpm.sortedPairs,ROW()-1,1),"")),"")} | M58: {=IFERROR(_xlfn.LET(_xlpm.pairs,_xlfn._xlws.FILTER($A$2:$D$391,($A$2:$A$391<>"")*(TRIM($D$2:$D$391)<>"")),_xlpm.uniquePairs,_xlfn.UNIQUE(_xlfn.HSTACK(INDEX(_xlpm.pairs,,1),INDEX(_xlpm.pairs,,4))),_xlpm.sortedPairs,_xlfn._xlws.SORT(_xlpm.uniquePairs,1,1),IF(ROW()-1<=ROWS(_xlpm.sortedPairs),INDEX(_xlpm.sortedPairs,ROW()-1,2),"")),"")} | N58: {=IF(OR(L58="",M58=""),"",IFERROR(INDEX($E$2:$E$391,MATCH(1,($A$2:$A$391=L58)*($D$2:$D$391=M58),0)),""))} | O58: =IF(OR(L58="",M58=""),"",SUMIFS($J$2:$J$391,$A$2:$A$391,L58,$D$2:$D$391,M58))
A59: TIPA 302FG W | B59: Ext. C (In) | D59: =IF(C59="","",IFERROR(_xlfn.XLOOKUP(C59,HELPER!$A$2:$A$76,HELPER!$B$2:$B$76,""),D59)) | E59: =IFERROR(_xlfn.XLOOKUP(D59,HELPER!$B:$B,HELPER!$C:$C,""),"") | F59: =IFERROR(_xlfn.XLOOKUP(D59,HELPER!$B:$B,HELPER!$D:$D,""),"") | G59: 8 | I59: =IF(AND(H59<>"",IFERROR(_xlfn.XLOOKUP(D59,HELPER!$B:$B,HELPER!$E:$E,""),"")=""),"Missing price",IFERROR(_xlfn.XLOOKUP(D59,HELPER!$B:$B,HELPER!$E:$E,"")," ")) | J59: =IFERROR(H59*(IF(G59=8,I59*HELPER!$G$2,BOM!I59*HELPER!$G$3))," ") | L59: {=IFERROR(_xlfn.LET(_xlpm.pairs,_xlfn._xlws.FILTER($A$2:$D$391,($A$2:$A$391<>"")*(TRIM($D$2:$D$391)<>"")),_xlpm.uniquePairs,_xlfn.UNIQUE(_xlfn.HSTACK(INDEX(_xlpm.pairs,,1),INDEX(_xlpm.pairs,,4))),_xlpm.sortedPairs,_xlfn._xlws.SORT(_xlpm.uniquePairs,1,1),IF(ROW()-1<=ROWS(_xlpm.sortedPairs),INDEX(_xlpm.sortedPairs,ROW()-1,1),"")),"")} | M59: {=IFERROR(_xlfn.LET(_xlpm.pairs,_xlfn._xlws.FILTER($A$2:$D$391,($A$2:$A$391<>"")*(TRIM($D$2:$D$391)<>"")),_xlpm.uniquePairs,_xlfn.UNIQUE(_xlfn.HSTACK(INDEX(_xlpm.pairs,,1),INDEX(_xlpm.pairs,,4))),_xlpm.sortedPairs,_xlfn._xlws.SORT(_xlpm.uniquePairs,1,1),IF(ROW()-1<=ROWS(_xlpm.sortedPairs),INDEX(_xlpm.sortedPairs,ROW()-1,2),"")),"")} | N59: {=IF(OR(L59="",M59=""),"",IFERROR(INDEX($E$2:$E$391,MATCH(1,($A$2:$A$391=L59)*($D$2:$D$391=M59),0)),""))} | O59: =IF(OR(L59="",M59=""),"",SUMIFS($J$2:$J$391,$A$2:$A$391,L59,$D$2:$D$391,M59))
A60: TIPA 302FG W | B60: Ext. C (In) | D60: =IF(C60="","",IFERROR(_xlfn.XLOOKUP(C60,HELPER!$A$2:$A$76,HELPER!$B$2:$B$76,""),D60)) | E60: =IFERROR(_xlfn.XLOOKUP(D60,HELPER!$B:$B,HELPER!$C:$C,""),"") | F60: =IFERROR(_xlfn.XLOOKUP(D60,HELPER!$B:$B,HELPER!$D:$D,""),"") | G60: 8 | I60: =IF(AND(H60<>"",IFERROR(_xlfn.XLOOKUP(D60,HELPER!$B:$B,HELPER!$E:$E,""),"")=""),"Missing price",IFERROR(_xlfn.XLOOKUP(D60,HELPER!$B:$B,HELPER!$E:$E,"")," ")) | J60: =IFERROR(H60*(IF(G60=8,I60*HELPER!$G$2,BOM!I60*HELPER!$G$3))," ") | L60: {=IFERROR(_xlfn.LET(_xlpm.pairs,_xlfn._xlws.FILTER($A$2:$D$391,($A$2:$A$391<>"")*(TRIM($D$2:$D$391)<>"")),_xlpm.uniquePairs,_xlfn.UNIQUE(_xlfn.HSTACK(INDEX(_xlpm.pairs,,1),INDEX(_xlpm.pairs,,4))),_xlpm.sortedPairs,_xlfn._xlws.SORT(_xlpm.uniquePairs,1,1),IF(ROW()-1<=ROWS(_xlpm.sortedPairs),INDEX(_xlpm.sortedPairs,ROW()-1,1),"")),"")} | M60: {=IFERROR(_xlfn.LET(_xlpm.pairs,_xlfn._xlws.FILTER($A$2:$D$391,($A$2:$A$391<>"")*(TRIM($D$2:$D$391)<>"")),_xlpm.uniquePairs,_xlfn.UNIQUE(_xlfn.HSTACK(INDEX(_xlpm.pairs,,1),INDEX(_xlpm.pairs,,4))),_xlpm.sortedPairs,_xlfn._xlws.SORT(_xlpm.uniquePairs,1,1),IF(ROW()-1<=ROWS(_xlpm.sortedPairs),INDEX(_xlpm.sortedPairs,ROW()-1,2),"")),"")} | N60: {=IF(OR(L60="",M60=""),"",IFERROR(INDEX($E$2:$E$391,MATCH(1,($A$2:$A$391=L60)*($D$2:$D$391=M60),0)),""))} | O60: =IF(OR(L60="",M60=""),"",SUMIFS($J$2:$J$391,$A$2:$A$391,L60,$D$2:$D$391,M60))
A61: TIPA 302FG W | B61: Ext. C (In) | D61: =IF(C61="","",IFERROR(_xlfn.XLOOKUP(C61,HELPER!$A$2:$A$76,HELPER!$B$2:$B$76,""),D61)) | E61: =IFERROR(_xlfn.XLOOKUP(D61,HELPER!$B:$B,HELPER!$C:$C,""),"") | F61: =IFERROR(_xlfn.XLOOKUP(D61,HELPER!$B:$B,HELPER!$D:$D,""),"") | G61: 8 | I61: =IF(AND(H61<>"",IFERROR(_xlfn.XLOOKUP(D61,HELPER!$B:$B,HELPER!$E:$E,""),"")=""),"Missing price",IFERROR(_xlfn.XLOOKUP(D61,HELPER!$B:$B,HELPER!$E:$E,"")," ")) | J61: =IFERROR(H61*(IF(G61=8,I61*HELPER!$G$2,BOM!I61*HELPER!$G$3))," ") | L61: {=IFERROR(_xlfn.LET(_xlpm.pairs,_xlfn._xlws.FILTER($A$2:$D$391,($A$2:$A$391<>"")*(TRIM($D$2:$D$391)<>"")),_xlpm.uniquePairs,_xlfn.UNIQUE(_xlfn.HSTACK(INDEX(_xlpm.pairs,,1),INDEX(_xlpm.pairs,,4))),_xlpm.sortedPairs,_xlfn._xlws.SORT(_xlpm.uniquePairs,1,1),IF(ROW()-1<=ROWS(_xlpm.sortedPairs),INDEX(_xlpm.sortedPairs,ROW()-1,1),"")),"")} | M61: {=IFERROR(_xlfn.LET(_xlpm.pairs,_xlfn._xlws.FILTER($A$2:$D$391,($A$2:$A$391<>"")*(TRIM($D$2:$D$391)<>"")),_xlpm.uniquePairs,_xlfn.UNIQUE(_xlfn.HSTACK(INDEX(_xlpm.pairs,,1),INDEX(_xlpm.pairs,,4))),_xlpm.sortedPairs,_xlfn._xlws.SORT(_xlpm.uniquePairs,1,1),IF(ROW()-1<=ROWS(_xlpm.sortedPairs),INDEX(_xlpm.sortedPairs,ROW()-1,2),"")),"")} | N61: {=IF(OR(L61="",M61=""),"",IFERROR(INDEX($E$2:$E$391,MATCH(1,($A$2:$A$391=L61)*($D$2:$D$391=M61),0)),""))} | O61: =IF(OR(L61="",M61=""),"",SUMIFS($J$2:$J$391,$A$2:$A$391,L61,$D$2:$D$391,M61))
A62: TIPA 312 MFG | B62: Ext. A (Out - Chillroll) | C62: PLA | D62: =IF(C62="","",IFERROR(_xlfn.XLOOKUP(C62,HELPER!$A$2:$A$76,HELPER!$B$2:$B$76,""),D62)) | E62: =IFERROR(_xlfn.XLOOKUP(D62,HELPER!$B:$B,HELPER!$C:$C,""),"") | F62: =IFERROR(_xlfn.XLOOKUP(D62,HELPER!$B:$B,HELPER!$D:$D,""),"") | G62: 8 | H62: 0.795 | I62: =IF(AND(H62<>"",IFERROR(_xlfn.XLOOKUP(D62,HELPER!$B:$B,HELPER!$E:$E,""),"")=""),"Missing price",IFERROR(_xlfn.XLOOKUP(D62,HELPER!$B:$B,HELPER!$E:$E,"")," ")) | J62: =IFERROR(H62*(IF(G62=8,I62*HELPER!$G$2,BOM!I62*HELPER!$G$3))," ") | L62: {=IFERROR(_xlfn.LET(_xlpm.pairs,_xlfn._xlws.FILTER($A$2:$D$391,($A$2:$A$391<>"")*(TRIM($D$2:$D$391)<>"")),_xlpm.uniquePairs,_xlfn.UNIQUE(_xlfn.HSTACK(INDEX(_xlpm.pairs,,1),INDEX(_xlpm.pairs,,4))),_xlpm.sortedPairs,_xlfn._xlws.SORT(_xlpm.uniquePairs,1,1),IF(ROW()-1<=ROWS(_xlpm.sortedPairs),INDEX(_xlpm.sortedPairs,ROW()-1,1),"")),"")} | M62: {=IFERROR(_xlfn.LET(_xlpm.pairs,_xlfn._xlws.FILTER($A$2:$D$391,($A$2:$A$391<>"")*(TRIM($D$2:$D$391)<>"")),_xlpm.uniquePairs,_xlfn.UNIQUE(_xlfn.HSTACK(INDEX(_xlpm.pairs,,1),INDEX(_xlpm.pairs,,4))),_xlpm.sortedPairs,_xlfn._xlws.SORT(_xlpm.uniquePairs,1,1),IF(ROW()-1<=ROWS(_xlpm.sortedPairs),INDEX(_xlpm.sortedPairs,ROW()-1,2),"")),"")} | N62: {=IF(OR(L62="",M62=""),"",IFERROR(INDEX($E$2:$E$391,MATCH(1,($A$2:$A$391=L62)*($D$2:$D$391=M62),0)),""))} | O62: =IF(OR(L62="",M62=""),"",SUMIFS($J$2:$J$391,$A$2:$A$391,L62,$D$2:$D$391,M62))
A63: TIPA 312 MFG | B63: Ext. A (Out - Chillroll) | C63: PCL | D63: =IF(C63="","",IFERROR(_xlfn.XLOOKUP(C63,HELPER!$A$2:$A$76,HELPER!$B$2:$B$76,""),D63)) | E63: =IFERROR(_xlfn.XLOOKUP(D63,HELPER!$B:$B,HELPER!$C:$C,""),"") | F63: =IFERROR(_xlfn.XLOOKUP(D63,HELPER!$B:$B,HELPER!$D:$D,""),"") | G63: 8 | H63: 0.19 | I63: =IF(AND(H63<>"",IFERROR(_xlfn.XLOOKUP(D63,HELPER!$B:$B,HELPER!$E:$E,""),"")=""),"Missing price",IFERROR(_xlfn.XLOOKUP(D63,HELPER!$B:$B,HELPER!$E:$E,"")," ")) | J63: =IFERROR(H63*(IF(G63=8,I63*HELPER!$G$2,BOM!I63*HELPER!$G$3))," ") | L63: {=IFERROR(_xlfn.LET(_xlpm.pairs,_xlfn._xlws.FILTER($A$2:$D$391,($A$2:$A$391<>"")*(TRIM($D$2:$D$391)<>"")),_xlpm.uniquePairs,_xlfn.UNIQUE(_xlfn.HSTACK(INDEX(_xlpm.pairs,,1),INDEX(_xlpm.pairs,,4))),_xlpm.sortedPairs,_xlfn._xlws.SORT(_xlpm.uniquePairs,1,1),IF(ROW()-1<=ROWS(_xlpm.sortedPairs),INDEX(_xlpm.sortedPairs,ROW()-1,1),"")),"")} | M63: {=IFERROR(_xlfn.LET(_xlpm.pairs,_xlfn._xlws.FILTER($A$2:$D$391,($A$2:$A$391<>"")*(TRIM($D$2:$D$391)<>"")),_xlpm.uniquePairs,_xlfn.UNIQUE(_xlfn.HSTACK(INDEX(_xlpm.pairs,,1),INDEX(_xlpm.pairs,,4))),_xlpm.sortedPairs,_xlfn._xlws.SORT(_xlpm.uniquePairs,1,1),IF(ROW()-1<=ROWS(_xlpm.sortedPairs),INDEX(_xlpm.sortedPairs,ROW()-1,2),"")),"")} | N63: {=IF(OR(L63="",M63=""),"",IFERROR(INDEX($E$2:$E$391,MATCH(1,($A$2:$A$391=L63)*($D$2:$D$391=M63),0)),""))} | O63: =IF(OR(L63="",M63=""),"",SUMIFS($J$2:$J$391,$A$2:$A$391,L63,$D$2:$D$391,M63))
A64: TIPA 312 MFG | B64: Ext. A (Out - Chillroll) | C64: AO-PBS | D64: =IF(C64="","",IFERROR(_xlfn.XLOOKUP(C64,HELPER!$A$2:$A$76,HELPER!$B$2:$B$76,""),D64)) | E64: =IFERROR(_xlfn.XLOOKUP(D64,HELPER!$B:$B,HELPER!$C:$C,""),"") | F64: =IFERROR(_xlfn.XLOOKUP(D64,HELPER!$B:$B,HELPER!$D:$D,""),"") | G64: 8 | H64: 0.015 | I64: =IF(AND(H64<>"",IFERROR(_xlfn.XLOOKUP(D64,HELPER!$B:$B,HELPER!$E:$E,""),"")=""),"Missing price",IFERROR(_xlfn.XLOOKUP(D64,HELPER!$B:$B,HELPER!$E:$E,"")," ")) | J64: =IFERROR(H64*(IF(G64=8,I64*HELPER!$G$2,BOM!I64*HELPER!$G$3))," ") | L64: {=IFERROR(_xlfn.LET(_xlpm.pairs,_xlfn._xlws.FILTER($A$2:$D$391,($A$2:$A$391<>"")*(TRIM($D$2:$D$391)<>"")),_xlpm.uniquePairs,_xlfn.UNIQUE(_xlfn.HSTACK(INDEX(_xlpm.pairs,,1),INDEX(_xlpm.pairs,,4))),_xlpm.sortedPairs,_xlfn._xlws.SORT(_xlpm.uniquePairs,1,1),IF(ROW()-1<=ROWS(_xlpm.sortedPairs),INDEX(_xlpm.sortedPairs,ROW()-1,1),"")),"")} | M64: {=IFERROR(_xlfn.LET(_xlpm.pairs,_xlfn._xlws.FILTER($A$2:$D$391,($A$2:$A$391<>"")*(TRIM($D$2:$D$391)<>"")),_xlpm.uniquePairs,_xlfn.UNIQUE(_xlfn.HSTACK(INDEX(_xlpm.pairs,,1),INDEX(_xlpm.pairs,,4))),_xlpm.sortedPairs,_xlfn._xlws.SORT(_xlpm.uniquePairs,1,1),IF(ROW()-1<=ROWS(_xlpm.sortedPairs),INDEX(_xlpm.sortedPairs,ROW()-1,2),"")),"")} | N64: {=IF(OR(L64="",M64=""),"",IFERROR(INDEX($E$2:$E$391,MATCH(1,($A$2:$A$391=L64)*($D$2:$D$391=M64),0)),""))} | O64: =IF(OR(L64="",M64=""),"",SUMIFS($J$2:$J$391,$A$2:$A$391,L64,$D$2:$D$391,M64))
A65: TIPA 312 MFG | B65: Ext. A (Out - Chillroll) | D65: =IF(C65="","",IFERROR(_xlfn.XLOOKUP(C65,HELPER!$A$2:$A$76,HELPER!$B$2:$B$76,""),D65)) | E65: =IFERROR(_xlfn.XLOOKUP(D65,HELPER!$B:$B,HELPER!$C:$C,""),"") | F65: =IFERROR(_xlfn.XLOOKUP(D65,HELPER!$B:$B,HELPER!$D:$D,""),"") | G65: 8 | I65: =IF(AND(H65<>"",IFERROR(_xlfn.XLOOKUP(D65,HELPER!$B:$B,HELPER!$E:$E,""),"")=""),"Missing price",IFERROR(_xlfn.XLOOKUP(D65,HELPER!$B:$B,HELPER!$E:$E,"")," ")) | J65: =IFERROR(H65*(IF(G65=8,I65*HELPER!$G$2,BOM!I65*HELPER!$G$3))," ") | L65: {=IFERROR(_xlfn.LET(_xlpm.pairs,_xlfn._xlws.FILTER($A$2:$D$391,($A$2:$A$391<>"")*(TRIM($D$2:$D$391)<>"")),_xlpm.uniquePairs,_xlfn.UNIQUE(_xlfn.HSTACK(INDEX(_xlpm.pairs,,1),INDEX(_xlpm.pairs,,4))),_xlpm.sortedPairs,_xlfn._xlws.SORT(_xlpm.uniquePairs,1,1),IF(ROW()-1<=ROWS(_xlpm.sortedPairs),INDEX(_xlpm.sortedPairs,ROW()-1,1),"")),"")} | M65: {=IFERROR(_xlfn.LET(_xlpm.pairs,_xlfn._xlws.FILTER($A$2:$D$391,($A$2:$A$391<>"")*(TRIM($D$2:$D$391)<>"")),_xlpm.uniquePairs,_xlfn.UNIQUE(_xlfn.HSTACK(INDEX(_xlpm.pairs,,1),INDEX(_xlpm.pairs,,4))),_xlpm.sortedPairs,_xlfn._xlws.SORT(_xlpm.uniquePairs,1,1),IF(ROW()-1<=ROWS(_xlpm.sortedPairs),INDEX(_xlpm.sortedPairs,ROW()-1,2),"")),"")} | N65: {=IF(OR(L65="",M65=""),"",IFERROR(INDEX($E$2:$E$391,MATCH(1,($A$2:$A$391=L65)*($D$2:$D$391=M65),0)),""))} | O65: =IF(OR(L65="",M65=""),"",SUMIFS($J$2:$J$391,$A$2:$A$391,L65,$D$2:$D$391,M65))
A66: TIPA 312 MFG | B66: Ext. A (Out - Chillroll) | D66: =IF(C66="","",IFERROR(_xlfn.XLOOKUP(C66,HELPER!$A$2:$A$76,HELPER!$B$2:$B$76,""),D66)) | E66: =IFERROR(_xlfn.XLOOKUP(D66,HELPER!$B:$B,HELPER!$C:$C,""),"") | F66: =IFERROR(_xlfn.XLOOKUP(D66,HELPER!$B:$B,HELPER!$D:$D,""),"") | G66: 8 | I66: =IF(AND(H66<>"",IFERROR(_xlfn.XLOOKUP(D66,HELPER!$B:$B,HELPER!$E:$E,""),"")=""),"Missing price",IFERROR(_xlfn.XLOOKUP(D66,HELPER!$B:$B,HELPER!$E:$E,"")," ")) | J66: =IFERROR(H66*(IF(G66=8,I66*HELPER!$G$2,BOM!I66*HELPER!$G$3))," ") | L66: {=IFERROR(_xlfn.LET(_xlpm.pairs,_xlfn._xlws.FILTER($A$2:$D$391,($A$2:$A$391<>"")*(TRIM($D$2:$D$391)<>"")),_xlpm.uniquePairs,_xlfn.UNIQUE(_xlfn.HSTACK(INDEX(_xlpm.pairs,,1),INDEX(_xlpm.pairs,,4))),_xlpm.sortedPairs,_xlfn._xlws.SORT(_xlpm.uniquePairs,1,1),IF(ROW()-1<=ROWS(_xlpm.sortedPairs),INDEX(_xlpm.sortedPairs,ROW()-1,1),"")),"")} | M66: {=IFERROR(_xlfn.LET(_xlpm.pairs,_xlfn._xlws.FILTER($A$2:$D$391,($A$2:$A$391<>"")*(TRIM($D$2:$D$391)<>"")),_xlpm.uniquePairs,_xlfn.UNIQUE(_xlfn.HSTACK(INDEX(_xlpm.pairs,,1),INDEX(_xlpm.pairs,,4))),_xlpm.sortedPairs,_xlfn._xlws.SORT(_xlpm.uniquePairs,1,1),IF(ROW()-1<=ROWS(_xlpm.sortedPairs),INDEX(_xlpm.sortedPairs,ROW()-1,2),"")),"")} | N66: {=IF(OR(L66="",M66=""),"",IFERROR(INDEX($E$2:$E$391,MATCH(1,($A$2:$A$391=L66)*($D$2:$D$391=M66),0)),""))} | O66: =IF(OR(L66="",M66=""),"",SUMIFS($J$2:$J$391,$A$2:$A$391,L66,$D$2:$D$391,M66))
A67: TIPA 312 MFG | B67: Ext. A (Out - Chillroll) | D67: =IF(C67="","",IFERROR(_xlfn.XLOOKUP(C67,HELPER!$A$2:$A$76,HELPER!$B$2:$B$76,""),D67)) | E67: =IFERROR(_xlfn.XLOOKUP(D67,HELPER!$B:$B,HELPER!$C:$C,""),"") | F67: =IFERROR(_xlfn.XLOOKUP(D67,HELPER!$B:$B,HELPER!$D:$D,""),"") | G67: 8 | I67: =IF(AND(H67<>"",IFERROR(_xlfn.XLOOKUP(D67,HELPER!$B:$B,HELPER!$E:$E,""),"")=""),"Missing price",IFERROR(_xlfn.XLOOKUP(D67,HELPER!$B:$B,HELPER!$E:$E,"")," ")) | J67: =IFERROR(H67*(IF(G67=8,I67*HELPER!$G$2,BOM!I67*HELPER!$G$3))," ") | L67: {=IFERROR(_xlfn.LET(_xlpm.pairs,_xlfn._xlws.FILTER($A$2:$D$391,($A$2:$A$391<>"")*(TRIM($D$2:$D$391)<>"")),_xlpm.uniquePairs,_xlfn.UNIQUE(_xlfn.HSTACK(INDEX(_xlpm.pairs,,1),INDEX(_xlpm.pairs,,4))),_xlpm.sortedPairs,_xlfn._xlws.SORT(_xlpm.uniquePairs,1,1),IF(ROW()-1<=ROWS(_xlpm.sortedPairs),INDEX(_xlpm.sortedPairs,ROW()-1,1),"")),"")} | M67: {=IFERROR(_xlfn.LET(_xlpm.pairs,_xlfn._xlws.FILTER($A$2:$D$391,($A$2:$A$391<>"")*(TRIM($D$2:$D$391)<>"")),_xlpm.uniquePairs,_xlfn.UNIQUE(_xlfn.HSTACK(INDEX(_xlpm.pairs,,1),INDEX(_xlpm.pairs,,4))),_xlpm.sortedPairs,_xlfn._xlws.SORT(_xlpm.uniquePairs,1,1),IF(ROW()-1<=ROWS(_xlpm.sortedPairs),INDEX(_xlpm.sortedPairs,ROW()-1,2),"")),"")} | N67: {=IF(OR(L67="",M67=""),"",IFERROR(INDEX($E$2:$E$391,MATCH(1,($A$2:$A$391=L67)*($D$2:$D$391=M67),0)),""))} | O67: =IF(OR(L67="",M67=""),"",SUMIFS($J$2:$J$391,$A$2:$A$391,L67,$D$2:$D$391,M67))
A68: TIPA 312 MFG | B68: Ext. A (Out - Chillroll) | D68: =IF(C68="","",IFERROR(_xlfn.XLOOKUP(C68,HELPER!$A$2:$A$76,HELPER!$B$2:$B$76,""),D68)) | E68: =IFERROR(_xlfn.XLOOKUP(D68,HELPER!$B:$B,HELPER!$C:$C,""),"") | F68: =IFERROR(_xlfn.XLOOKUP(D68,HELPER!$B:$B,HELPER!$D:$D,""),"") | G68: 8 | I68: =IF(AND(H68<>"",IFERROR(_xlfn.XLOOKUP(D68,HELPER!$B:$B,HELPER!$E:$E,""),"")=""),"Missing price",IFERROR(_xlfn.XLOOKUP(D68,HELPER!$B:$B,HELPER!$E:$E,"")," ")) | J68: =IFERROR(H68*(IF(G68=8,I68*HELPER!$G$2,BOM!I68*HELPER!$G$3))," ") | L68: {=IFERROR(_xlfn.LET(_xlpm.pairs,_xlfn._xlws.FILTER($A$2:$D$391,($A$2:$A$391<>"")*(TRIM($D$2:$D$391)<>"")),_xlpm.uniquePairs,_xlfn.UNIQUE(_xlfn.HSTACK(INDEX(_xlpm.pairs,,1),INDEX(_xlpm.pairs,,4))),_xlpm.sortedPairs,_xlfn._xlws.SORT(_xlpm.uniquePairs,1,1),IF(ROW()-1<=ROWS(_xlpm.sortedPairs),INDEX(_xlpm.sortedPairs,ROW()-1,1),"")),"")} | M68: {=IFERROR(_xlfn.LET(_xlpm.pairs,_xlfn._xlws.FILTER($A$2:$D$391,($A$2:$A$391<>"")*(TRIM($D$2:$D$391)<>"")),_xlpm.uniquePairs,_xlfn.UNIQUE(_xlfn.HSTACK(INDEX(_xlpm.pairs,,1),INDEX(_xlpm.pairs,,4))),_xlpm.sortedPairs,_xlfn._xlws.SORT(_xlpm.uniquePairs,1,1),IF(ROW()-1<=ROWS(_xlpm.sortedPairs),INDEX(_xlpm.sortedPairs,ROW()-1,2),"")),"")} | N68: {=IF(OR(L68="",M68=""),"",IFERROR(INDEX($E$2:$E$391,MATCH(1,($A$2:$A$391=L68)*($D$2:$D$391=M68),0)),""))} | O68: =IF(OR(L68="",M68=""),"",SUMIFS($J$2:$J$391,$A$2:$A$391,L68,$D$2:$D$391,M68))
A69: TIPA 312 MFG | B69: Ext. A (Out - Chillroll) | D69: =IF(C69="","",IFERROR(_xlfn.XLOOKUP(C69,HELPER!$A$2:$A$76,HELPER!$B$2:$B$76,""),D69)) | E69: =IFERROR(_xlfn.XLOOKUP(D69,HELPER!$B:$B,HELPER!$C:$C,""),"") | F69: =IFERROR(_xlfn.XLOOKUP(D69,HELPER!$B:$B,HELPER!$D:$D,""),"") | G69: 8 | I69: =IF(AND(H69<>"",IFERROR(_xlfn.XLOOKUP(D69,HELPER!$B:$B,HELPER!$E:$E,""),"")=""),"Missing price",IFERROR(_xlfn.XLOOKUP(D69,HELPER!$B:$B,HELPER!$E:$E,"")," ")) | J69: =IFERROR(H69*(IF(G69=8,I69*HELPER!$G$2,BOM!I69*HELPER!$G$3))," ") | L69: {=IFERROR(_xlfn.LET(_xlpm.pairs,_xlfn._xlws.FILTER($A$2:$D$391,($A$2:$A$391<>"")*(TRIM($D$2:$D$391)<>"")),_xlpm.uniquePairs,_xlfn.UNIQUE(_xlfn.HSTACK(INDEX(_xlpm.pairs,,1),INDEX(_xlpm.pairs,,4))),_xlpm.sortedPairs,_xlfn._xlws.SORT(_xlpm.uniquePairs,1,1),IF(ROW()-1<=ROWS(_xlpm.sortedPairs),INDEX(_xlpm.sortedPairs,ROW()-1,1),"")),"")} | M69: {=IFERROR(_xlfn.LET(_xlpm.pairs,_xlfn._xlws.FILTER($A$2:$D$391,($A$2:$A$391<>"")*(TRIM($D$2:$D$391)<>"")),_xlpm.uniquePairs,_xlfn.UNIQUE(_xlfn.HSTACK(INDEX(_xlpm.pairs,,1),INDEX(_xlpm.pairs,,4))),_xlpm.sortedPairs,_xlfn._xlws.SORT(_xlpm.uniquePairs,1,1),IF(ROW()-1<=ROWS(_xlpm.sortedPairs),INDEX(_xlpm.sortedPairs,ROW()-1,2),"")),"")} | N69: {=IF(OR(L69="",M69=""),"",IFERROR(INDEX($E$2:$E$391,MATCH(1,($A$2:$A$391=L69)*($D$2:$D$391=M69),0)),""))} | O69: =IF(OR(L69="",M69=""),"",SUMIFS($J$2:$J$391,$A$2:$A$391,L69,$D$2:$D$391,M69))
A70: TIPA 312 MFG | B70: Ext. A (Out - Chillroll) | D70: =IF(C70="","",IFERROR(_xlfn.XLOOKUP(C70,HELPER!$A$2:$A$76,HELPER!$B$2:$B$76,""),D70)) | E70: =IFERROR(_xlfn.XLOOKUP(D70,HELPER!$B:$B,HELPER!$C:$C,""),"") | F70: =IFERROR(_xlfn.XLOOKUP(D70,HELPER!$B:$B,HELPER!$D:$D,""),"") | G70: 8 | I70: =IF(AND(H70<>"",IFERROR(_xlfn.XLOOKUP(D70,HELPER!$B:$B,HELPER!$E:$E,""),"")=""),"Missing price",IFERROR(_xlfn.XLOOKUP(D70,HELPER!$B:$B,HELPER!$E:$E,"")," ")) | J70: =IFERROR(H70*(IF(G70=8,I70*HELPER!$G$2,BOM!I70*HELPER!$G$3))," ") | L70: {=IFERROR(_xlfn.LET(_xlpm.pairs,_xlfn._xlws.FILTER($A$2:$D$391,($A$2:$A$391<>"")*(TRIM($D$2:$D$391)<>"")),_xlpm.uniquePairs,_xlfn.UNIQUE(_xlfn.HSTACK(INDEX(_xlpm.pairs,,1),INDEX(_xlpm.pairs,,4))),_xlpm.sortedPairs,_xlfn._xlws.SORT(_xlpm.uniquePairs,1,1),IF(ROW()-1<=ROWS(_xlpm.sortedPairs),INDEX(_xlpm.sortedPairs,ROW()-1,1),"")),"")} | M70: {=IFERROR(_xlfn.LET(_xlpm.pairs,_xlfn._xlws.FILTER($A$2:$D$391,($A$2:$A$391<>"")*(TRIM($D$2:$D$391)<>"")),_xlpm.uniquePairs,_xlfn.UNIQUE(_xlfn.HSTACK(INDEX(_xlpm.pairs,,1),INDEX(_xlpm.pairs,,4))),_xlpm.sortedPairs,_xlfn._xlws.SORT(_xlpm.uniquePairs,1,1),IF(ROW()-1<=ROWS(_xlpm.sortedPairs),INDEX(_xlpm.sortedPairs,ROW()-1,2),"")),"")} | N70: {=IF(OR(L70="",M70=""),"",IFERROR(INDEX($E$2:$E$391,MATCH(1,($A$2:$A$391=L70)*($D$2:$D$391=M70),0)),""))} | O70: =IF(OR(L70="",M70=""),"",SUMIFS($J$2:$J$391,$A$2:$A$391,L70,$D$2:$D$391,M70))
A71: TIPA 312 MFG | B71: Ext. A (Out - Chillroll) | D71: =IF(C71="","",IFERROR(_xlfn.XLOOKUP(C71,HELPER!$A$2:$A$76,HELPER!$B$2:$B$76,""),D71)) | E71: =IFERROR(_xlfn.XLOOKUP(D71,HELPER!$B:$B,HELPER!$C:$C,""),"") | F71: =IFERROR(_xlfn.XLOOKUP(D71,HELPER!$B:$B,HELPER!$D:$D,""),"") | G71: 8 | I71: =IF(AND(H71<>"",IFERROR(_xlfn.XLOOKUP(D71,HELPER!$B:$B,HELPER!$E:$E,""),"")=""),"Missing price",IFERROR(_xlfn.XLOOKUP(D71,HELPER!$B:$B,HELPER!$E:$E,"")," ")) | J71: =IFERROR(H71*(IF(G71=8,I71*HELPER!$G$2,BOM!I71*HELPER!$G$3))," ") | L71: {=IFERROR(_xlfn.LET(_xlpm.pairs,_xlfn._xlws.FILTER($A$2:$D$391,($A$2:$A$391<>"")*(TRIM($D$2:$D$391)<>"")),_xlpm.uniquePairs,_xlfn.UNIQUE(_xlfn.HSTACK(INDEX(_xlpm.pairs,,1),INDEX(_xlpm.pairs,,4))),_xlpm.sortedPairs,_xlfn._xlws.SORT(_xlpm.uniquePairs,1,1),IF(ROW()-1<=ROWS(_xlpm.sortedPairs),INDEX(_xlpm.sortedPairs,ROW()-1,1),"")),"")} | M71: {=IFERROR(_xlfn.LET(_xlpm.pairs,_xlfn._xlws.FILTER($A$2:$D$391,($A$2:$A$391<>"")*(TRIM($D$2:$D$391)<>"")),_xlpm.uniquePairs,_xlfn.UNIQUE(_xlfn.HSTACK(INDEX(_xlpm.pairs,,1),INDEX(_xlpm.pairs,,4))),_xlpm.sortedPairs,_xlfn._xlws.SORT(_xlpm.uniquePairs,1,1),IF(ROW()-1<=ROWS(_xlpm.sortedPairs),INDEX(_xlpm.sortedPairs,ROW()-1,2),"")),"")} | N71: {=IF(OR(L71="",M71=""),"",IFERROR(INDEX($E$2:$E$391,MATCH(1,($A$2:$A$391=L71)*($D$2:$D$391=M71),0)),""))} | O71: =IF(OR(L71="",M71=""),"",SUMIFS($J$2:$J$391,$A$2:$A$391,L71,$D$2:$D$391,M71))
A72: TIPA 312 MFG | B72: Ext. B | D72: =IF(C72="","",IFERROR(_xlfn.XLOOKUP(C72,HELPER!$A$2:$A$76,HELPER!$B$2:$B$76,""),D72)) | E72: =IFERROR(_xlfn.XLOOKUP(D72,HELPER!$B:$B,HELPER!$C:$C,""),"") | F72: =IFERROR(_xlfn.XLOOKUP(D72,HELPER!$B:$B,HELPER!$D:$D,""),"") | G72: 24 | I72: =IF(AND(H72<>"",IFERROR(_xlfn.XLOOKUP(D72,HELPER!$B:$B,HELPER!$E:$E,""),"")=""),"Missing price",IFERROR(_xlfn.XLOOKUP(D72,HELPER!$B:$B,HELPER!$E:$E,"")," ")) | J72: =IFERROR(H72*(IF(G72=8,I72*HELPER!$G$2,BOM!I72*HELPER!$G$3))," ") | L72: {=IFERROR(_xlfn.LET(_xlpm.pairs,_xlfn._xlws.FILTER($A$2:$D$391,($A$2:$A$391<>"")*(TRIM($D$2:$D$391)<>"")),_xlpm.uniquePairs,_xlfn.UNIQUE(_xlfn.HSTACK(INDEX(_xlpm.pairs,,1),INDEX(_xlpm.pairs,,4))),_xlpm.sortedPairs,_xlfn._xlws.SORT(_xlpm.uniquePairs,1,1),IF(ROW()-1<=ROWS(_xlpm.sortedPairs),INDEX(_xlpm.sortedPairs,ROW()-1,1),"")),"")} | M72: {=IFERROR(_xlfn.LET(_xlpm.pairs,_xlfn._xlws.FILTER($A$2:$D$391,($A$2:$A$391<>"")*(TRIM($D$2:$D$391)<>"")),_xlpm.uniquePairs,_xlfn.UNIQUE(_xlfn.HSTACK(INDEX(_xlpm.pairs,,1),INDEX(_xlpm.pairs,,4))),_xlpm.sortedPairs,_xlfn._xlws.SORT(_xlpm.uniquePairs,1,1),IF(ROW()-1<=ROWS(_xlpm.sortedPairs),INDEX(_xlpm.sortedPairs,ROW()-1,2),"")),"")} | N72: {=IF(OR(L72="",M72=""),"",IFERROR(INDEX($E$2:$E$391,MATCH(1,($A$2:$A$391=L72)*($D$2:$D$391=M72),0)),""))} | O72: =IF(OR(L72="",M72=""),"",SUMIFS($J$2:$J$391,$A$2:$A$391,L72,$D$2:$D$391,M72))
A73: TIPA 312 MFG | B73: Ext. B | D73: =IF(C73="","",IFERROR(_xlfn.XLOOKUP(C73,HELPER!$A$2:$A$76,HELPER!$B$2:$B$76,""),D73)) | E73: =IFERROR(_xlfn.XLOOKUP(D73,HELPER!$B:$B,HELPER!$C:$C,""),"") | F73: =IFERROR(_xlfn.XLOOKUP(D73,HELPER!$B:$B,HELPER!$D:$D,""),"") | G73: 24 | I73: =IF(AND(H73<>"",IFERROR(_xlfn.XLOOKUP(D73,HELPER!$B:$B,HELPER!$E:$E,""),"")=""),"Missing price",IFERROR(_xlfn.XLOOKUP(D73,HELPER!$B:$B,HELPER!$E:$E,"")," ")) | J73: =IFERROR(H73*(IF(G73=8,I73*HELPER!$G$2,BOM!I73*HELPER!$G$3))," ") | L73: {=IFERROR(_xlfn.LET(_xlpm.pairs,_xlfn._xlws.FILTER($A$2:$D$391,($A$2:$A$391<>"")*(TRIM($D$2:$D$391)<>"")),_xlpm.uniquePairs,_xlfn.UNIQUE(_xlfn.HSTACK(INDEX(_xlpm.pairs,,1),INDEX(_xlpm.pairs,,4))),_xlpm.sortedPairs,_xlfn._xlws.SORT(_xlpm.uniquePairs,1,1),IF(ROW()-1<=ROWS(_xlpm.sortedPairs),INDEX(_xlpm.sortedPairs,ROW()-1,1),"")),"")} | M73: {=IFERROR(_xlfn.LET(_xlpm.pairs,_xlfn._xlws.FILTER($A$2:$D$391,($A$2:$A$391<>"")*(TRIM($D$2:$D$391)<>"")),_xlpm.uniquePairs,_xlfn.UNIQUE(_xlfn.HSTACK(INDEX(_xlpm.pairs,,1),INDEX(_xlpm.pairs,,4))),_xlpm.sortedPairs,_xlfn._xlws.SORT(_xlpm.uniquePairs,1,1),IF(ROW()-1<=ROWS(_xlpm.sortedPairs),INDEX(_xlpm.sortedPairs,ROW()-1,2),"")),"")} | N73: {=IF(OR(L73="",M73=""),"",IFERROR(INDEX($E$2:$E$391,MATCH(1,($A$2:$A$391=L73)*($D$2:$D$391=M73),0)),""))} | O73: =IF(OR(L73="",M73=""),"",SUMIFS($J$2:$J$391,$A$2:$A$391,L73,$D$2:$D$391,M73))
A74: TIPA 312 MFG | B74: Ext. B | D74: =IF(C74="","",IFERROR(_xlfn.XLOOKUP(C74,HELPER!$A$2:$A$76,HELPER!$B$2:$B$76,""),D74)) | E74: =IFERROR(_xlfn.XLOOKUP(D74,HELPER!$B:$B,HELPER!$C:$C,""),"") | F74: =IFERROR(_xlfn.XLOOKUP(D74,HELPER!$B:$B,HELPER!$D:$D,""),"") | G74: 24 | I74: =IF(AND(H74<>"",IFERROR(_xlfn.XLOOKUP(D74,HELPER!$B:$B,HELPER!$E:$E,""),"")=""),"Missing price",IFERROR(_xlfn.XLOOKUP(D74,HELPER!$B:$B,HELPER!$E:$E,"")," ")) | J74: =IFERROR(H74*(IF(G74=8,I74*HELPER!$G$2,BOM!I74*HELPER!$G$3))," ") | L74: {=IFERROR(_xlfn.LET(_xlpm.pairs,_xlfn._xlws.FILTER($A$2:$D$391,($A$2:$A$391<>"")*(TRIM($D$2:$D$391)<>"")),_xlpm.uniquePairs,_xlfn.UNIQUE(_xlfn.HSTACK(INDEX(_xlpm.pairs,,1),INDEX(_xlpm.pairs,,4))),_xlpm.sortedPairs,_xlfn._xlws.SORT(_xlpm.uniquePairs,1,1),IF(ROW()-1<=ROWS(_xlpm.sortedPairs),INDEX(_xlpm.sortedPairs,ROW()-1,1),"")),"")} | M74: {=IFERROR(_xlfn.LET(_xlpm.pairs,_xlfn._xlws.FILTER($A$2:$D$391,($A$2:$A$391<>"")*(TRIM($D$2:$D$391)<>"")),_xlpm.uniquePairs,_xlfn.UNIQUE(_xlfn.HSTACK(INDEX(_xlpm.pairs,,1),INDEX(_xlpm.pairs,,4))),_xlpm.sortedPairs,_xlfn._xlws.SORT(_xlpm.uniquePairs,1,1),IF(ROW()-1<=ROWS(_xlpm.sortedPairs),INDEX(_xlpm.sortedPairs,ROW()-1,2),"")),"")} | N74: {=IF(OR(L74="",M74=""),"",IFERROR(INDEX($E$2:$E$391,MATCH(1,($A$2:$A$391=L74)*($D$2:$D$391=M74),0)),""))} | O74: =IF(OR(L74="",M74=""),"",SUMIFS($J$2:$J$391,$A$2:$A$391,L74,$D$2:$D$391,M74))
A75: TIPA 312 MFG | B75: Ext. B | D75: =IF(C75="","",IFERROR(_xlfn.XLOOKUP(C75,HELPER!$A$2:$A$76,HELPER!$B$2:$B$76,""),D75)) | E75: =IFERROR(_xlfn.XLOOKUP(D75,HELPER!$B:$B,HELPER!$C:$C,""),"") | F75: =IFERROR(_xlfn.XLOOKUP(D75,HELPER!$B:$B,HELPER!$D:$D,""),"") | G75: 24 | I75: =IF(AND(H75<>"",IFERROR(_xlfn.XLOOKUP(D75,HELPER!$B:$B,HELPER!$E:$E,""),"")=""),"Missing price",IFERROR(_xlfn.XLOOKUP(D75,HELPER!$B:$B,HELPER!$E:$E,"")," ")) | J75: =IFERROR(H75*(IF(G75=8,I75*HELPER!$G$2,BOM!I75*HELPER!$G$3))," ") | L75: {=IFERROR(_xlfn.LET(_xlpm.pairs,_xlfn._xlws.FILTER($A$2:$D$391,($A$2:$A$391<>"")*(TRIM($D$2:$D$391)<>"")),_xlpm.uniquePairs,_xlfn.UNIQUE(_xlfn.HSTACK(INDEX(_xlpm.pairs,,1),INDEX(_xlpm.pairs,,4))),_xlpm.sortedPairs,_xlfn._xlws.SORT(_xlpm.uniquePairs,1,1),IF(ROW()-1<=ROWS(_xlpm.sortedPairs),INDEX(_xlpm.sortedPairs,ROW()-1,1),"")),"")} | M75: {=IFERROR(_xlfn.LET(_xlpm.pairs,_xlfn._xlws.FILTER($A$2:$D$391,($A$2:$A$391<>"")*(TRIM($D$2:$D$391)<>"")),_xlpm.uniquePairs,_xlfn.UNIQUE(_xlfn.HSTACK(INDEX(_xlpm.pairs,,1),INDEX(_xlpm.pairs,,4))),_xlpm.sortedPairs,_xlfn._xlws.SORT(_xlpm.uniquePairs,1,1),IF(ROW()-1<=ROWS(_xlpm.sortedPairs),INDEX(_xlpm.sortedPairs,ROW()-1,2),"")),"")} | N75: {=IF(OR(L75="",M75=""),"",IFERROR(INDEX($E$2:$E$391,MATCH(1,($A$2:$A$391=L75)*($D$2:$D$391=M75),0)),""))} | O75: =IF(OR(L75="",M75=""),"",SUMIFS($J$2:$J$391,$A$2:$A$391,L75,$D$2:$D$391,M75))
A76: TIPA 312 MFG | B76: Ext. B | C76: AO-PBS | D76: =IF(C76="","",IFERROR(_xlfn.XLOOKUP(C76,HELPER!$A$2:$A$76,HELPER!$B$2:$B$76,""),D76)) | E76: =IFERROR(_xlfn.XLOOKUP(D76,HELPER!$B:$B,HELPER!$C:$C,""),"") | F76: =IFERROR(_xlfn.XLOOKUP(D76,HELPER!$B:$B,HELPER!$D:$D,""),"") | G76: 24 | H76: 0.015 | I76: =IF(AND(H76<>"",IFERROR(_xlfn.XLOOKUP(D76,HELPER!$B:$B,HELPER!$E:$E,""),"")=""),"Missing price",IFERROR(_xlfn.XLOOKUP(D76,HELPER!$B:$B,HELPER!$E:$E,"")," ")) | J76: =IFERROR(H76*(IF(G76=8,I76*HELPER!$G$2,BOM!I76*HELPER!$G$3))," ") | L76: {=IFERROR(_xlfn.LET(_xlpm.pairs,_xlfn._xlws.FILTER($A$2:$D$391,($A$2:$A$391<>"")*(TRIM($D$2:$D$391)<>"")),_xlpm.uniquePairs,_xlfn.UNIQUE(_xlfn.HSTACK(INDEX(_xlpm.pairs,,1),INDEX(_xlpm.pairs,,4))),_xlpm.sortedPairs,_xlfn._xlws.SORT(_xlpm.uniquePairs,1,1),IF(ROW()-1<=ROWS(_xlpm.sortedPairs),INDEX(_xlpm.sortedPairs,ROW()-1,1),"")),"")} | M76: {=IFERROR(_xlfn.LET(_xlpm.pairs,_xlfn._xlws.FILTER($A$2:$D$391,($A$2:$A$391<>"")*(TRIM($D$2:$D$391)<>"")),_xlpm.uniquePairs,_xlfn.UNIQUE(_xlfn.HSTACK(INDEX(_xlpm.pairs,,1),INDEX(_xlpm.pairs,,4))),_xlpm.sortedPairs,_xlfn._xlws.SORT(_xlpm.uniquePairs,1,1),IF(ROW()-1<=ROWS(_xlpm.sortedPairs),INDEX(_xlpm.sortedPairs,ROW()-1,2),"")),"")} | N76: {=IF(OR(L76="",M76=""),"",IFERROR(INDEX($E$2:$E$391,MATCH(1,($A$2:$A$391=L76)*($D$2:$D$391=M76),0)),""))} | O76: =IF(OR(L76="",M76=""),"",SUMIFS($J$2:$J$391,$A$2:$A$391,L76,$D$2:$D$391,M76))
A77: TIPA 312 MFG | B77: Ext. B | D77: =IF(C77="","",IFERROR(_xlfn.XLOOKUP(C77,HELPER!$A$2:$A$76,HELPER!$B$2:$B$76,""),D77)) | E77: =IFERROR(_xlfn.XLOOKUP(D77,HELPER!$B:$B,HELPER!$C:$C,""),"") | F77: =IFERROR(_xlfn.XLOOKUP(D77,HELPER!$B:$B,HELPER!$D:$D,""),"") | G77: 24 | I77: =IF(AND(H77<>"",IFERROR(_xlfn.XLOOKUP(D77,HELPER!$B:$B,HELPER!$E:$E,""),"")=""),"Missing price",IFERROR(_xlfn.XLOOKUP(D77,HELPER!$B:$B,HELPER!$E:$E,"")," ")) | J77: =IFERROR(H77*(IF(G77=8,I77*HELPER!$G$2,BOM!I77*HELPER!$G$3))," ") | L77: {=IFERROR(_xlfn.LET(_xlpm.pairs,_xlfn._xlws.FILTER($A$2:$D$391,($A$2:$A$391<>"")*(TRIM($D$2:$D$391)<>"")),_xlpm.uniquePairs,_xlfn.UNIQUE(_xlfn.HSTACK(INDEX(_xlpm.pairs,,1),INDEX(_xlpm.pairs,,4))),_xlpm.sortedPairs,_xlfn._xlws.SORT(_xlpm.uniquePairs,1,1),IF(ROW()-1<=ROWS(_xlpm.sortedPairs),INDEX(_xlpm.sortedPairs,ROW()-1,1),"")),"")} | M77: {=IFERROR(_xlfn.LET(_xlpm.pairs,_xlfn._xlws.FILTER($A$2:$D$391,($A$2:$A$391<>"")*(TRIM($D$2:$D$391)<>"")),_xlpm.uniquePairs,_xlfn.UNIQUE(_xlfn.HSTACK(INDEX(_xlpm.pairs,,1),INDEX(_xlpm.pairs,,4))),_xlpm.sortedPairs,_xlfn._xlws.SORT(_xlpm.uniquePairs,1,1),IF(ROW()-1<=ROWS(_xlpm.sortedPairs),INDEX(_xlpm.sortedPairs,ROW()-1,2),"")),"")} | N77: {=IF(OR(L77="",M77=""),"",IFERROR(INDEX($E$2:$E$391,MATCH(1,($A$2:$A$391=L77)*($D$2:$D$391=M77),0)),""))} | O77: =IF(OR(L77="",M77=""),"",SUMIFS($J$2:$J$391,$A$2:$A$391,L77,$D$2:$D$391,M77))
A78: TIPA 312 MFG | B78: Ext. B | D78: =IF(C78="","",IFERROR(_xlfn.XLOOKUP(C78,HELPER!$A$2:$A$76,HELPER!$B$2:$B$76,""),D78)) | E78: =IFERROR(_xlfn.XLOOKUP(D78,HELPER!$B:$B,HELPER!$C:$C,""),"") | F78: =IFERROR(_xlfn.XLOOKUP(D78,HELPER!$B:$B,HELPER!$D:$D,""),"") | G78: 24 | I78: =IF(AND(H78<>"",IFERROR(_xlfn.XLOOKUP(D78,HELPER!$B:$B,HELPER!$E:$E,""),"")=""),"Missing price",IFERROR(_xlfn.XLOOKUP(D78,HELPER!$B:$B,HELPER!$E:$E,"")," ")) | J78: =IFERROR(H78*(IF(G78=8,I78*HELPER!$G$2,BOM!I78*HELPER!$G$3))," ") | L78: {=IFERROR(_xlfn.LET(_xlpm.pairs,_xlfn._xlws.FILTER($A$2:$D$391,($A$2:$A$391<>"")*(TRIM($D$2:$D$391)<>"")),_xlpm.uniquePairs,_xlfn.UNIQUE(_xlfn.HSTACK(INDEX(_xlpm.pairs,,1),INDEX(_xlpm.pairs,,4))),_xlpm.sortedPairs,_xlfn._xlws.SORT(_xlpm.uniquePairs,1,1),IF(ROW()-1<=ROWS(_xlpm.sortedPairs),INDEX(_xlpm.sortedPairs,ROW()-1,1),"")),"")} | M78: {=IFERROR(_xlfn.LET(_xlpm.pairs,_xlfn._xlws.FILTER($A$2:$D$391,($A$2:$A$391<>"")*(TRIM($D$2:$D$391)<>"")),_xlpm.uniquePairs,_xlfn.UNIQUE(_xlfn.HSTACK(INDEX(_xlpm.pairs,,1),INDEX(_xlpm.pairs,,4))),_xlpm.sortedPairs,_xlfn._xlws.SORT(_xlpm.uniquePairs,1,1),IF(ROW()-1<=ROWS(_xlpm.sortedPairs),INDEX(_xlpm.sortedPairs,ROW()-1,2),"")),"")} | N78: {=IF(OR(L78="",M78=""),"",IFERROR(INDEX($E$2:$E$391,MATCH(1,($A$2:$A$391=L78)*($D$2:$D$391=M78),0)),""))} | O78: =IF(OR(L78="",M78=""),"",SUMIFS($J$2:$J$391,$A$2:$A$391,L78,$D$2:$D$391,M78))
A79: TIPA 312 MFG | B79: Ext. B | C79: PBAT | D79: =IF(C79="","",IFERROR(_xlfn.XLOOKUP(C79,HELPER!$A$2:$A$76,HELPER!$B$2:$B$76,""),D79)) | E79: =IFERROR(_xlfn.XLOOKUP(D79,HELPER!$B:$B,HELPER!$C:$C,""),"") | F79: =IFERROR(_xlfn.XLOOKUP(D79,HELPER!$B:$B,HELPER!$D:$D,""),"") | G79: 24 | H79: 0.985 | I79: =IF(AND(H79<>"",IFERROR(_xlfn.XLOOKUP(D79,HELPER!$B:$B,HELPER!$E:$E,""),"")=""),"Missing price",IFERROR(_xlfn.XLOOKUP(D79,HELPER!$B:$B,HELPER!$E:$E,"")," ")) | J79: =IFERROR(H79*(IF(G79=8,I79*HELPER!$G$2,BOM!I79*HELPER!$G$3))," ") | L79: {=IFERROR(_xlfn.LET(_xlpm.pairs,_xlfn._xlws.FILTER($A$2:$D$391,($A$2:$A$391<>"")*(TRIM($D$2:$D$391)<>"")),_xlpm.uniquePairs,_xlfn.UNIQUE(_xlfn.HSTACK(INDEX(_xlpm.pairs,,1),INDEX(_xlpm.pairs,,4))),_xlpm.sortedPairs,_xlfn._xlws.SORT(_xlpm.uniquePairs,1,1),IF(ROW()-1<=ROWS(_xlpm.sortedPairs),INDEX(_xlpm.sortedPairs,ROW()-1,1),"")),"")} | M79: {=IFERROR(_xlfn.LET(_xlpm.pairs,_xlfn._xlws.FILTER($A$2:$D$391,($A$2:$A$391<>"")*(TRIM($D$2:$D$391)<>"")),_xlpm.uniquePairs,_xlfn.UNIQUE(_xlfn.HSTACK(INDEX(_xlpm.pairs,,1),INDEX(_xlpm.pairs,,4))),_xlpm.sortedPairs,_xlfn._xlws.SORT(_xlpm.uniquePairs,1,1),IF(ROW()-1<=ROWS(_xlpm.sortedPairs),INDEX(_xlpm.sortedPairs,ROW()-1,2),"")),"")} | N79: {=IF(OR(L79="",M79=""),"",IFERROR(INDEX($E$2:$E$391,MATCH(1,($A$2:$A$391=L79)*($D$2:$D$391=M79),0)),""))} | O79: =IF(OR(L79="",M79=""),"",SUMIFS($J$2:$J$391,$A$2:$A$391,L79,$D$2:$D$391,M79))
A80: TIPA 312 MFG | B80: Ext. B | D80: =IF(C80="","",IFERROR(_xlfn.XLOOKUP(C80,HELPER!$A$2:$A$76,HELPER!$B$2:$B$76,""),D80)) | E80: =IFERROR(_xlfn.XLOOKUP(D80,HELPER!$B:$B,HELPER!$C:$C,""),"") | F80: =IFERROR(_xlfn.XLOOKUP(D80,HELPER!$B:$B,HELPER!$D:$D,""),"") | G80: 24 | I80: =IF(AND(H80<>"",IFERROR(_xlfn.XLOOKUP(D80,HELPER!$B:$B,HELPER!$E:$E,""),"")=""),"Missing price",IFERROR(_xlfn.XLOOKUP(D80,HELPER!$B:$B,HELPER!$E:$E,"")," ")) | J80: =IFERROR(H80*(IF(G80=8,I80*HELPER!$G$2,BOM!I80*HELPER!$G$3))," ") | L80: {=IFERROR(_xlfn.LET(_xlpm.pairs,_xlfn._xlws.FILTER($A$2:$D$391,($A$2:$A$391<>"")*(TRIM($D$2:$D$391)<>"")),_xlpm.uniquePairs,_xlfn.UNIQUE(_xlfn.HSTACK(INDEX(_xlpm.pairs,,1),INDEX(_xlpm.pairs,,4))),_xlpm.sortedPairs,_xlfn._xlws.SORT(_xlpm.uniquePairs,1,1),IF(ROW()-1<=ROWS(_xlpm.sortedPairs),INDEX(_xlpm.sortedPairs,ROW()-1,1),"")),"")} | M80: {=IFERROR(_xlfn.LET(_xlpm.pairs,_xlfn._xlws.FILTER($A$2:$D$391,($A$2:$A$391<>"")*(TRIM($D$2:$D$391)<>"")),_xlpm.uniquePairs,_xlfn.UNIQUE(_xlfn.HSTACK(INDEX(_xlpm.pairs,,1),INDEX(_xlpm.pairs,,4))),_xlpm.sortedPairs,_xlfn._xlws.SORT(_xlpm.uniquePairs,1,1),IF(ROW()-1<=ROWS(_xlpm.sortedPairs),INDEX(_xlpm.sortedPairs,ROW()-1,2),"")),"")} | N80: {=IF(OR(L80="",M80=""),"",IFERROR(INDEX($E$2:$E$391,MATCH(1,($A$2:$A$391=L80)*($D$2:$D$391=M80),0)),""))} | O80: =IF(OR(L80="",M80=""),"",SUMIFS($J$2:$J$391,$A$2:$A$391,L80,$D$2:$D$391,M80))
A81: TIPA 312 MFG | B81: Ext. B | D81: =IF(C81="","",IFERROR(_xlfn.XLOOKUP(C81,HELPER!$A$2:$A$76,HELPER!$B$2:$B$76,""),D81)) | E81: =IFERROR(_xlfn.XLOOKUP(D81,HELPER!$B:$B,HELPER!$C:$C,""),"") | F81: =IFERROR(_xlfn.XLOOKUP(D81,HELPER!$B:$B,HELPER!$D:$D,""),"") | G81: 24 | I81: =IF(AND(H81<>"",IFERROR(_xlfn.XLOOKUP(D81,HELPER!$B:$B,HELPER!$E:$E,""),"")=""),"Missing price",IFERROR(_xlfn.XLOOKUP(D81,HELPER!$B:$B,HELPER!$E:$E,"")," ")) | J81: =IFERROR(H81*(IF(G81=8,I81*HELPER!$G$2,BOM!I81*HELPER!$G$3))," ") | L81: {=IFERROR(_xlfn.LET(_xlpm.pairs,_xlfn._xlws.FILTER($A$2:$D$391,($A$2:$A$391<>"")*(TRIM($D$2:$D$391)<>"")),_xlpm.uniquePairs,_xlfn.UNIQUE(_xlfn.HSTACK(INDEX(_xlpm.pairs,,1),INDEX(_xlpm.pairs,,4))),_xlpm.sortedPairs,_xlfn._xlws.SORT(_xlpm.uniquePairs,1,1),IF(ROW()-1<=ROWS(_xlpm.sortedPairs),INDEX(_xlpm.sortedPairs,ROW()-1,1),"")),"")} | M81: {=IFERROR(_xlfn.LET(_xlpm.pairs,_xlfn._xlws.FILTER($A$2:$D$391,($A$2:$A$391<>"")*(TRIM($D$2:$D$391)<>"")),_xlpm.uniquePairs,_xlfn.UNIQUE(_xlfn.HSTACK(INDEX(_xlpm.pairs,,1),INDEX(_xlpm.pairs,,4))),_xlpm.sortedPairs,_xlfn._xlws.SORT(_xlpm.uniquePairs,1,1),IF(ROW()-1<=ROWS(_xlpm.sortedPairs),INDEX(_xlpm.sortedPairs,ROW()-1,2),"")),"")} | N81: {=IF(OR(L81="",M81=""),"",IFERROR(INDEX($E$2:$E$391,MATCH(1,($A$2:$A$391=L81)*($D$2:$D$391=M81),0)),""))} | O81: =IF(OR(L81="",M81=""),"",SUMIFS($J$2:$J$391,$A$2:$A$391,L81,$D$2:$D$391,M81))
A82: TIPA 312 MFG | B82: Ext. C (In) | C82: PBSA | D82: =IF(C82="","",IFERROR(_xlfn.XLOOKUP(C82,HELPER!$A$2:$A$76,HELPER!$B$2:$B$76,""),D82)) | E82: =IFERROR(_xlfn.XLOOKUP(D82,HELPER!$B:$B,HELPER!$C:$C,""),"") | F82: =IFERROR(_xlfn.XLOOKUP(D82,HELPER!$B:$B,HELPER!$D:$D,""),"") | G82: 8 | H82: 0.805 | I82: =IF(AND(H82<>"",IFERROR(_xlfn.XLOOKUP(D82,HELPER!$B:$B,HELPER!$E:$E,""),"")=""),"Missing price",IFERROR(_xlfn.XLOOKUP(D82,HELPER!$B:$B,HELPER!$E:$E,"")," ")) | J82: =IFERROR(H82*(IF(G82=8,I82*HELPER!$G$2,BOM!I82*HELPER!$G$3))," ") | L82: {=IFERROR(_xlfn.LET(_xlpm.pairs,_xlfn._xlws.FILTER($A$2:$D$391,($A$2:$A$391<>"")*(TRIM($D$2:$D$391)<>"")),_xlpm.uniquePairs,_xlfn.UNIQUE(_xlfn.HSTACK(INDEX(_xlpm.pairs,,1),INDEX(_xlpm.pairs,,4))),_xlpm.sortedPairs,_xlfn._xlws.SORT(_xlpm.uniquePairs,1,1),IF(ROW()-1<=ROWS(_xlpm.sortedPairs),INDEX(_xlpm.sortedPairs,ROW()-1,1),"")),"")} | M82: {=IFERROR(_xlfn.LET(_xlpm.pairs,_xlfn._xlws.FILTER($A$2:$D$391,($A$2:$A$391<>"")*(TRIM($D$2:$D$391)<>"")),_xlpm.uniquePairs,_xlfn.UNIQUE(_xlfn.HSTACK(INDEX(_xlpm.pairs,,1),INDEX(_xlpm.pairs,,4))),_xlpm.sortedPairs,_xlfn._xlws.SORT(_xlpm.uniquePairs,1,1),IF(ROW()-1<=ROWS(_xlpm.sortedPairs),INDEX(_xlpm.sortedPairs,ROW()-1,2),"")),"")} | N82: {=IF(OR(L82="",M82=""),"",IFERROR(INDEX($E$2:$E$391,MATCH(1,($A$2:$A$391=L82)*($D$2:$D$391=M82),0)),""))} | O82: =IF(OR(L82="",M82=""),"",SUMIFS($J$2:$J$391,$A$2:$A$391,L82,$D$2:$D$391,M82))
A83: TIPA 312 MFG | B83: Ext. C (In) | C83: PLA | D83: =IF(C83="","",IFERROR(_xlfn.XLOOKUP(C83,HELPER!$A$2:$A$76,HELPER!$B$2:$B$76,""),D83)) | E83: =IFERROR(_xlfn.XLOOKUP(D83,HELPER!$B:$B,HELPER!$C:$C,""),"") | F83: =IFERROR(_xlfn.XLOOKUP(D83,HELPER!$B:$B,HELPER!$D:$D,""),"") | G83: 8 | H83: 0.142 | I83: =IF(AND(H83<>"",IFERROR(_xlfn.XLOOKUP(D83,HELPER!$B:$B,HELPER!$E:$E,""),"")=""),"Missing price",IFERROR(_xlfn.XLOOKUP(D83,HELPER!$B:$B,HELPER!$E:$E,"")," ")) | J83: =IFERROR(H83*(IF(G83=8,I83*HELPER!$G$2,BOM!I83*HELPER!$G$3))," ") | L83: {=IFERROR(_xlfn.LET(_xlpm.pairs,_xlfn._xlws.FILTER($A$2:$D$391,($A$2:$A$391<>"")*(TRIM($D$2:$D$391)<>"")),_xlpm.uniquePairs,_xlfn.UNIQUE(_xlfn.HSTACK(INDEX(_xlpm.pairs,,1),INDEX(_xlpm.pairs,,4))),_xlpm.sortedPairs,_xlfn._xlws.SORT(_xlpm.uniquePairs,1,1),IF(ROW()-1<=ROWS(_xlpm.sortedPairs),INDEX(_xlpm.sortedPairs,ROW()-1,1),"")),"")} | M83: {=IFERROR(_xlfn.LET(_xlpm.pairs,_xlfn._xlws.FILTER($A$2:$D$391,($A$2:$A$391<>"")*(TRIM($D$2:$D$391)<>"")),_xlpm.uniquePairs,_xlfn.UNIQUE(_xlfn.HSTACK(INDEX(_xlpm.pairs,,1),INDEX(_xlpm.pairs,,4))),_xlpm.sortedPairs,_xlfn._xlws.SORT(_xlpm.uniquePairs,1,1),IF(ROW()-1<=ROWS(_xlpm.sortedPairs),INDEX(_xlpm.sortedPairs,ROW()-1,2),"")),"")} | N83: {=IF(OR(L83="",M83=""),"",IFERROR(INDEX($E$2:$E$391,MATCH(1,($A$2:$A$391=L83)*($D$2:$D$391=M83),0)),""))} | O83: =IF(OR(L83="",M83=""),"",SUMIFS($J$2:$J$391,$A$2:$A$391,L83,$D$2:$D$391,M83))
A84: TIPA 312 MFG | B84: Ext. C (In) | C84: AB-PLA | D84: =IF(C84="","",IFERROR(_xlfn.XLOOKUP(C84,HELPER!$A$2:$A$76,HELPER!$B$2:$B$76,""),D84)) | E84: =IFERROR(_xlfn.XLOOKUP(D84,HELPER!$B:$B,HELPER!$C:$C,""),"") | F84: =IFERROR(_xlfn.XLOOKUP(D84,HELPER!$B:$B,HELPER!$D:$D,""),"") | G84: 8 | H84: 0.015 | I84: =IF(AND(H84<>"",IFERROR(_xlfn.XLOOKUP(D84,HELPER!$B:$B,HELPER!$E:$E,""),"")=""),"Missing price",IFERROR(_xlfn.XLOOKUP(D84,HELPER!$B:$B,HELPER!$E:$E,"")," ")) | J84: =IFERROR(H84*(IF(G84=8,I84*HELPER!$G$2,BOM!I84*HELPER!$G$3))," ") | L84: {=IFERROR(_xlfn.LET(_xlpm.pairs,_xlfn._xlws.FILTER($A$2:$D$391,($A$2:$A$391<>"")*(TRIM($D$2:$D$391)<>"")),_xlpm.uniquePairs,_xlfn.UNIQUE(_xlfn.HSTACK(INDEX(_xlpm.pairs,,1),INDEX(_xlpm.pairs,,4))),_xlpm.sortedPairs,_xlfn._xlws.SORT(_xlpm.uniquePairs,1,1),IF(ROW()-1<=ROWS(_xlpm.sortedPairs),INDEX(_xlpm.sortedPairs,ROW()-1,1),"")),"")} | M84: {=IFERROR(_xlfn.LET(_xlpm.pairs,_xlfn._xlws.FILTER($A$2:$D$391,($A$2:$A$391<>"")*(TRIM($D$2:$D$391)<>"")),_xlpm.uniquePairs,_xlfn.UNIQUE(_xlfn.HSTACK(INDEX(_xlpm.pairs,,1),INDEX(_xlpm.pairs,,4))),_xlpm.sortedPairs,_xlfn._xlws.SORT(_xlpm.uniquePairs,1,1),IF(ROW()-1<=ROWS(_xlpm.sortedPairs),INDEX(_xlpm.sortedPairs,ROW()-1,2),"")),"")} | N84: {=IF(OR(L84="",M84=""),"",IFERROR(INDEX($E$2:$E$391,MATCH(1,($A$2:$A$391=L84)*($D$2:$D$391=M84),0)),""))} | O84: =IF(OR(L84="",M84=""),"",SUMIFS($J$2:$J$391,$A$2:$A$391,L84,$D$2:$D$391,M84))
A85: TIPA 312 MFG | B85: Ext. C (In) | C85: AO-PBS | D85: =IF(C85="","",IFERROR(_xlfn.XLOOKUP(C85,HELPER!$A$2:$A$76,HELPER!$B$2:$B$76,""),D85)) | E85: =IFERROR(_xlfn.XLOOKUP(D85,HELPER!$B:$B,HELPER!$C:$C,""),"") | F85: =IFERROR(_xlfn.XLOOKUP(D85,HELPER!$B:$B,HELPER!$D:$D,""),"") | G85: 8 | H85: 0.015 | I85: =IF(AND(H85<>"",IFERROR(_xlfn.XLOOKUP(D85,HELPER!$B:$B,HELPER!$E:$E,""),"")=""),"Missing price",IFERROR(_xlfn.XLOOKUP(D85,HELPER!$B:$B,HELPER!$E:$E,"")," ")) | J85: =IFERROR(H85*(IF(G85=8,I85*HELPER!$G$2,BOM!I85*HELPER!$G$3))," ") | L85: {=IFERROR(_xlfn.LET(_xlpm.pairs,_xlfn._xlws.FILTER($A$2:$D$391,($A$2:$A$391<>"")*(TRIM($D$2:$D$391)<>"")),_xlpm.uniquePairs,_xlfn.UNIQUE(_xlfn.HSTACK(INDEX(_xlpm.pairs,,1),INDEX(_xlpm.pairs,,4))),_xlpm.sortedPairs,_xlfn._xlws.SORT(_xlpm.uniquePairs,1,1),IF(ROW()-1<=ROWS(_xlpm.sortedPairs),INDEX(_xlpm.sortedPairs,ROW()-1,1),"")),"")} | M85: {=IFERROR(_xlfn.LET(_xlpm.pairs,_xlfn._xlws.FILTER($A$2:$D$391,($A$2:$A$391<>"")*(TRIM($D$2:$D$391)<>"")),_xlpm.uniquePairs,_xlfn.UNIQUE(_xlfn.HSTACK(INDEX(_xlpm.pairs,,1),INDEX(_xlpm.pairs,,4))),_xlpm.sortedPairs,_xlfn._xlws.SORT(_xlpm.uniquePairs,1,1),IF(ROW()-1<=ROWS(_xlpm.sortedPairs),INDEX(_xlpm.sortedPairs,ROW()-1,2),"")),"")} | N85: {=IF(OR(L85="",M85=""),"",IFERROR(INDEX($E$2:$E$391,MATCH(1,($A$2:$A$391=L85)*($D$2:$D$391=M85),0)),""))} | O85: =IF(OR(L85="",M85=""),"",SUMIFS($J$2:$J$391,$A$2:$A$391,L85,$D$2:$D$391,M85))
A86: TIPA 312 MFG | B86: Ext. C (In) | C86: SLAB-PBSA | D86: =IF(C86="","",IFERROR(_xlfn.XLOOKUP(C86,HELPER!$A$2:$A$76,HELPER!$B$2:$B$76,""),D86)) | E86: =IFERROR(_xlfn.XLOOKUP(D86,HELPER!$B:$B,HELPER!$C:$C,""),"") | F86: =IFERROR(_xlfn.XLOOKUP(D86,HELPER!$B:$B,HELPER!$D:$D,""),"") | G86: 8 | H86: 0.023 | I86: =IF(AND(H86<>"",IFERROR(_xlfn.XLOOKUP(D86,HELPER!$B:$B,HELPER!$E:$E,""),"")=""),"Missing price",IFERROR(_xlfn.XLOOKUP(D86,HELPER!$B:$B,HELPER!$E:$E,"")," ")) | J86: =IFERROR(H86*(IF(G86=8,I86*HELPER!$G$2,BOM!I86*HELPER!$G$3))," ") | L86: {=IFERROR(_xlfn.LET(_xlpm.pairs,_xlfn._xlws.FILTER($A$2:$D$391,($A$2:$A$391<>"")*(TRIM($D$2:$D$391)<>"")),_xlpm.uniquePairs,_xlfn.UNIQUE(_xlfn.HSTACK(INDEX(_xlpm.pairs,,1),INDEX(_xlpm.pairs,,4))),_xlpm.sortedPairs,_xlfn._xlws.SORT(_xlpm.uniquePairs,1,1),IF(ROW()-1<=ROWS(_xlpm.sortedPairs),INDEX(_xlpm.sortedPairs,ROW()-1,1),"")),"")} | M86: {=IFERROR(_xlfn.LET(_xlpm.pairs,_xlfn._xlws.FILTER($A$2:$D$391,($A$2:$A$391<>"")*(TRIM($D$2:$D$391)<>"")),_xlpm.uniquePairs,_xlfn.UNIQUE(_xlfn.HSTACK(INDEX(_xlpm.pairs,,1),INDEX(_xlpm.pairs,,4))),_xlpm.sortedPairs,_xlfn._xlws.SORT(_xlpm.uniquePairs,1,1),IF(ROW()-1<=ROWS(_xlpm.sortedPairs),INDEX(_xlpm.sortedPairs,ROW()-1,2),"")),"")} | N86: {=IF(OR(L86="",M86=""),"",IFERROR(INDEX($E$2:$E$391,MATCH(1,($A$2:$A$391=L86)*($D$2:$D$391=M86),0)),""))} | O86: =IF(OR(L86="",M86=""),"",SUMIFS($J$2:$J$391,$A$2:$A$391,L86,$D$2:$D$391,M86))
A87: TIPA 312 MFG | B87: Ext. C (In) | D87: =IF(C87="","",IFERROR(_xlfn.XLOOKUP(C87,HELPER!$A$2:$A$76,HELPER!$B$2:$B$76,""),D87)) | E87: =IFERROR(_xlfn.XLOOKUP(D87,HELPER!$B:$B,HELPER!$C:$C,""),"") | F87: =IFERROR(_xlfn.XLOOKUP(D87,HELPER!$B:$B,HELPER!$D:$D,""),"") | G87: 8 | I87: =IF(AND(H87<>"",IFERROR(_xlfn.XLOOKUP(D87,HELPER!$B:$B,HELPER!$E:$E,""),"")=""),"Missing price",IFERROR(_xlfn.XLOOKUP(D87,HELPER!$B:$B,HELPER!$E:$E,"")," ")) | J87: =IFERROR(H87*(IF(G87=8,I87*HELPER!$G$2,BOM!I87*HELPER!$G$3))," ") | L87: {=IFERROR(_xlfn.LET(_xlpm.pairs,_xlfn._xlws.FILTER($A$2:$D$391,($A$2:$A$391<>"")*(TRIM($D$2:$D$391)<>"")),_xlpm.uniquePairs,_xlfn.UNIQUE(_xlfn.HSTACK(INDEX(_xlpm.pairs,,1),INDEX(_xlpm.pairs,,4))),_xlpm.sortedPairs,_xlfn._xlws.SORT(_xlpm.uniquePairs,1,1),IF(ROW()-1<=ROWS(_xlpm.sortedPairs),INDEX(_xlpm.sortedPairs,ROW()-1,1),"")),"")} | M87: {=IFERROR(_xlfn.LET(_xlpm.pairs,_xlfn._xlws.FILTER($A$2:$D$391,($A$2:$A$391<>"")*(TRIM($D$2:$D$391)<>"")),_xlpm.uniquePairs,_xlfn.UNIQUE(_xlfn.HSTACK(INDEX(_xlpm.pairs,,1),INDEX(_xlpm.pairs,,4))),_xlpm.sortedPairs,_xlfn._xlws.SORT(_xlpm.uniquePairs,1,1),IF(ROW()-1<=ROWS(_xlpm.sortedPairs),INDEX(_xlpm.sortedPairs,ROW()-1,2),"")),"")} | N87: {=IF(OR(L87="",M87=""),"",IFERROR(INDEX($E$2:$E$391,MATCH(1,($A$2:$A$391=L87)*($D$2:$D$391=M87),0)),""))} | O87: =IF(OR(L87="",M87=""),"",SUMIFS($J$2:$J$391,$A$2:$A$391,L87,$D$2:$D$391,M87))
A88: TIPA 312 MFG | B88: Ext. C (In) | D88: =IF(C88="","",IFERROR(_xlfn.XLOOKUP(C88,HELPER!$A$2:$A$76,HELPER!$B$2:$B$76,""),D88)) | E88: =IFERROR(_xlfn.XLOOKUP(D88,HELPER!$B:$B,HELPER!$C:$C,""),"") | F88: =IFERROR(_xlfn.XLOOKUP(D88,HELPER!$B:$B,HELPER!$D:$D,""),"") | G88: 8 | I88: =IF(AND(H88<>"",IFERROR(_xlfn.XLOOKUP(D88,HELPER!$B:$B,HELPER!$E:$E,""),"")=""),"Missing price",IFERROR(_xlfn.XLOOKUP(D88,HELPER!$B:$B,HELPER!$E:$E,"")," ")) | J88: =IFERROR(H88*(IF(G88=8,I88*HELPER!$G$2,BOM!I88*HELPER!$G$3))," ") | L88: {=IFERROR(_xlfn.LET(_xlpm.pairs,_xlfn._xlws.FILTER($A$2:$D$391,($A$2:$A$391<>"")*(TRIM($D$2:$D$391)<>"")),_xlpm.uniquePairs,_xlfn.UNIQUE(_xlfn.HSTACK(INDEX(_xlpm.pairs,,1),INDEX(_xlpm.pairs,,4))),_xlpm.sortedPairs,_xlfn._xlws.SORT(_xlpm.uniquePairs,1,1),IF(ROW()-1<=ROWS(_xlpm.sortedPairs),INDEX(_xlpm.sortedPairs,ROW()-1,1),"")),"")} | M88: {=IFERROR(_xlfn.LET(_xlpm.pairs,_xlfn._xlws.FILTER($A$2:$D$391,($A$2:$A$391<>"")*(TRIM($D$2:$D$391)<>"")),_xlpm.uniquePairs,_xlfn.UNIQUE(_xlfn.HSTACK(INDEX(_xlpm.pairs,,1),INDEX(_xlpm.pairs,,4))),_xlpm.sortedPairs,_xlfn._xlws.SORT(_xlpm.uniquePairs,1,1),IF(ROW()-1<=ROWS(_xlpm.sortedPairs),INDEX(_xlpm.sortedPairs,ROW()-1,2),"")),"")} | N88: {=IF(OR(L88="",M88=""),"",IFERROR(INDEX($E$2:$E$391,MATCH(1,($A$2:$A$391=L88)*($D$2:$D$391=M88),0)),""))} | O88: =IF(OR(L88="",M88=""),"",SUMIFS($J$2:$J$391,$A$2:$A$391,L88,$D$2:$D$391,M88))
A89: TIPA 312 MFG | B89: Ext. C (In) | D89: =IF(C89="","",IFERROR(_xlfn.XLOOKUP(C89,HELPER!$A$2:$A$76,HELPER!$B$2:$B$76,""),D89)) | E89: =IFERROR(_xlfn.XLOOKUP(D89,HELPER!$B:$B,HELPER!$C:$C,""),"") | F89: =IFERROR(_xlfn.XLOOKUP(D89,HELPER!$B:$B,HELPER!$D:$D,""),"") | G89: 8 | I89: =IF(AND(H89<>"",IFERROR(_xlfn.XLOOKUP(D89,HELPER!$B:$B,HELPER!$E:$E,""),"")=""),"Missing price",IFERROR(_xlfn.XLOOKUP(D89,HELPER!$B:$B,HELPER!$E:$E,"")," ")) | J89: =IFERROR(H89*(IF(G89=8,I89*HELPER!$G$2,BOM!I89*HELPER!$G$3))," ") | L89: {=IFERROR(_xlfn.LET(_xlpm.pairs,_xlfn._xlws.FILTER($A$2:$D$391,($A$2:$A$391<>"")*(TRIM($D$2:$D$391)<>"")),_xlpm.uniquePairs,_xlfn.UNIQUE(_xlfn.HSTACK(INDEX(_xlpm.pairs,,1),INDEX(_xlpm.pairs,,4))),_xlpm.sortedPairs,_xlfn._xlws.SORT(_xlpm.uniquePairs,1,1),IF(ROW()-1<=ROWS(_xlpm.sortedPairs),INDEX(_xlpm.sortedPairs,ROW()-1,1),"")),"")} | M89: {=IFERROR(_xlfn.LET(_xlpm.pairs,_xlfn._xlws.FILTER($A$2:$D$391,($A$2:$A$391<>"")*(TRIM($D$2:$D$391)<>"")),_xlpm.uniquePairs,_xlfn.UNIQUE(_xlfn.HSTACK(INDEX(_xlpm.pairs,,1),INDEX(_xlpm.pairs,,4))),_xlpm.sortedPairs,_xlfn._xlws.SORT(_xlpm.uniquePairs,1,1),IF(ROW()-1<=ROWS(_xlpm.sortedPairs),INDEX(_xlpm.sortedPairs,ROW()-1,2),"")),"")} | N89: {=IF(OR(L89="",M89=""),"",IFERROR(INDEX($E$2:$E$391,MATCH(1,($A$2:$A$391=L89)*($D$2:$D$391=M89),0)),""))} | O89: =IF(OR(L89="",M89=""),"",SUMIFS($J$2:$J$391,$A$2:$A$391,L89,$D$2:$D$391,M89))
A90: TIPA 312 MFG | B90: Ext. C (In) | D90: =IF(C90="","",IFERROR(_xlfn.XLOOKUP(C90,HELPER!$A$2:$A$76,HELPER!$B$2:$B$76,""),D90)) | E90: =IFERROR(_xlfn.XLOOKUP(D90,HELPER!$B:$B,HELPER!$C:$C,""),"") | F90: =IFERROR(_xlfn.XLOOKUP(D90,HELPER!$B:$B,HELPER!$D:$D,""),"") | G90: 8 | I90: =IF(AND(H90<>"",IFERROR(_xlfn.XLOOKUP(D90,HELPER!$B:$B,HELPER!$E:$E,""),"")=""),"Missing price",IFERROR(_xlfn.XLOOKUP(D90,HELPER!$B:$B,HELPER!$E:$E,"")," ")) | J90: =IFERROR(H90*(IF(G90=8,I90*HELPER!$G$2,BOM!I90*HELPER!$G$3))," ") | L90: {=IFERROR(_xlfn.LET(_xlpm.pairs,_xlfn._xlws.FILTER($A$2:$D$391,($A$2:$A$391<>"")*(TRIM($D$2:$D$391)<>"")),_xlpm.uniquePairs,_xlfn.UNIQUE(_xlfn.HSTACK(INDEX(_xlpm.pairs,,1),INDEX(_xlpm.pairs,,4))),_xlpm.sortedPairs,_xlfn._xlws.SORT(_xlpm.uniquePairs,1,1),IF(ROW()-1<=ROWS(_xlpm.sortedPairs),INDEX(_xlpm.sortedPairs,ROW()-1,1),"")),"")} | M90: {=IFERROR(_xlfn.LET(_xlpm.pairs,_xlfn._xlws.FILTER($A$2:$D$391,($A$2:$A$391<>"")*(TRIM($D$2:$D$391)<>"")),_xlpm.uniquePairs,_xlfn.UNIQUE(_xlfn.HSTACK(INDEX(_xlpm.pairs,,1),INDEX(_xlpm.pairs,,4))),_xlpm.sortedPairs,_xlfn._xlws.SORT(_xlpm.uniquePairs,1,1),IF(ROW()-1<=ROWS(_xlpm.sortedPairs),INDEX(_xlpm.sortedPairs,ROW()-1,2),"")),"")} | N90: {=IF(OR(L90="",M90=""),"",IFERROR(INDEX($E$2:$E$391,MATCH(1,($A$2:$A$391=L90)*($D$2:$D$391=M90),0)),""))} | O90: =IF(OR(L90="",M90=""),"",SUMIFS($J$2:$J$391,$A$2:$A$391,L90,$D$2:$D$391,M90))
A91: TIPA 312 MFG | B91: Ext. C (In) | D91: =IF(C91="","",IFERROR(_xlfn.XLOOKUP(C91,HELPER!$A$2:$A$76,HELPER!$B$2:$B$76,""),D91)) | E91: =IFERROR(_xlfn.XLOOKUP(D91,HELPER!$B:$B,HELPER!$C:$C,""),"") | F91: =IFERROR(_xlfn.XLOOKUP(D91,HELPER!$B:$B,HELPER!$D:$D,""),"") | G91: 8 | I91: =IF(AND(H91<>"",IFERROR(_xlfn.XLOOKUP(D91,HELPER!$B:$B,HELPER!$E:$E,""),"")=""),"Missing price",IFERROR(_xlfn.XLOOKUP(D91,HELPER!$B:$B,HELPER!$E:$E,"")," ")) | J91: =IFERROR(H91*(IF(G91=8,I91*HELPER!$G$2,BOM!I91*HELPER!$G$3))," ") | L91: {=IFERROR(_xlfn.LET(_xlpm.pairs,_xlfn._xlws.FILTER($A$2:$D$391,($A$2:$A$391<>"")*(TRIM($D$2:$D$391)<>"")),_xlpm.uniquePairs,_xlfn.UNIQUE(_xlfn.HSTACK(INDEX(_xlpm.pairs,,1),INDEX(_xlpm.pairs,,4))),_xlpm.sortedPairs,_xlfn._xlws.SORT(_xlpm.uniquePairs,1,1),IF(ROW()-1<=ROWS(_xlpm.sortedPairs),INDEX(_xlpm.sortedPairs,ROW()-1,1),"")),"")} | M91: {=IFERROR(_xlfn.LET(_xlpm.pairs,_xlfn._xlws.FILTER($A$2:$D$391,($A$2:$A$391<>"")*(TRIM($D$2:$D$391)<>"")),_xlpm.uniquePairs,_xlfn.UNIQUE(_xlfn.HSTACK(INDEX(_xlpm.pairs,,1),INDEX(_xlpm.pairs,,4))),_xlpm.sortedPairs,_xlfn._xlws.SORT(_xlpm.uniquePairs,1,1),IF(ROW()-1<=ROWS(_xlpm.sortedPairs),INDEX(_xlpm.sortedPairs,ROW()-1,2),"")),"")} | N91: {=IF(OR(L91="",M91=""),"",IFERROR(INDEX($E$2:$E$391,MATCH(1,($A$2:$A$391=L91)*($D$2:$D$391=M91),0)),""))} | O91: =IF(OR(L91="",M91=""),"",SUMIFS($J$2:$J$391,$A$2:$A$391,L91,$D$2:$D$391,M91))
A92: TIPA 312MFGW | B92: Ext. A (Out - Chillroll) | C92: PLA | D92: =IF(C92="","",IFERROR(_xlfn.XLOOKUP(C92,HELPER!$A$2:$A$76,HELPER!$B$2:$B$76,""),D92)) | E92: =IFERROR(_xlfn.XLOOKUP(D92,HELPER!$B:$B,HELPER!$C:$C,""),"") | F92: =IFERROR(_xlfn.XLOOKUP(D92,HELPER!$B:$B,HELPER!$D:$D,""),"") | G92: 8 | H92: 0.795 | I92: =IF(AND(H92<>"",IFERROR(_xlfn.XLOOKUP(D92,HELPER!$B:$B,HELPER!$E:$E,""),"")=""),"Missing price",IFERROR(_xlfn.XLOOKUP(D92,HELPER!$B:$B,HELPER!$E:$E,"")," ")) | J92: =IFERROR(H92*(IF(G92=8,I92*HELPER!$G$2,BOM!I92*HELPER!$G$3))," ") | L92: {=IFERROR(_xlfn.LET(_xlpm.pairs,_xlfn._xlws.FILTER($A$2:$D$391,($A$2:$A$391<>"")*(TRIM($D$2:$D$391)<>"")),_xlpm.uniquePairs,_xlfn.UNIQUE(_xlfn.HSTACK(INDEX(_xlpm.pairs,,1),INDEX(_xlpm.pairs,,4))),_xlpm.sortedPairs,_xlfn._xlws.SORT(_xlpm.uniquePairs,1,1),IF(ROW()-1<=ROWS(_xlpm.sortedPairs),INDEX(_xlpm.sortedPairs,ROW()-1,1),"")),"")} | M92: {=IFERROR(_xlfn.LET(_xlpm.pairs,_xlfn._xlws.FILTER($A$2:$D$391,($A$2:$A$391<>"")*(TRIM($D$2:$D$391)<>"")),_xlpm.uniquePairs,_xlfn.UNIQUE(_xlfn.HSTACK(INDEX(_xlpm.pairs,,1),INDEX(_xlpm.pairs,,4))),_xlpm.sortedPairs,_xlfn._xlws.SORT(_xlpm.uniquePairs,1,1),IF(ROW()-1<=ROWS(_xlpm.sortedPairs),INDEX(_xlpm.sortedPairs,ROW()-1,2),"")),"")} | N92: {=IF(OR(L92="",M92=""),"",IFERROR(INDEX($E$2:$E$391,MATCH(1,($A$2:$A$391=L92)*($D$2:$D$391=M92),0)),""))} | O92: =IF(OR(L92="",M92=""),"",SUMIFS($J$2:$J$391,$A$2:$A$391,L92,$D$2:$D$391,M92))
A93: TIPA 312MFGW | B93: Ext. A (Out - Chillroll) | C93: PCL | D93: =IF(C93="","",IFERROR(_xlfn.XLOOKUP(C93,HELPER!$A$2:$A$76,HELPER!$B$2:$B$76,""),D93)) | E93: =IFERROR(_xlfn.XLOOKUP(D93,HELPER!$B:$B,HELPER!$C:$C,""),"") | F93: =IFERROR(_xlfn.XLOOKUP(D93,HELPER!$B:$B,HELPER!$D:$D,""),"") | G93: 8 | H93: 0.19 | I93: =IF(AND(H93<>"",IFERROR(_xlfn.XLOOKUP(D93,HELPER!$B:$B,HELPER!$E:$E,""),"")=""),"Missing price",IFERROR(_xlfn.XLOOKUP(D93,HELPER!$B:$B,HELPER!$E:$E,"")," ")) | J93: =IFERROR(H93*(IF(G93=8,I93*HELPER!$G$2,BOM!I93*HELPER!$G$3))," ") | L93: {=IFERROR(_xlfn.LET(_xlpm.pairs,_xlfn._xlws.FILTER($A$2:$D$391,($A$2:$A$391<>"")*(TRIM($D$2:$D$391)<>"")),_xlpm.uniquePairs,_xlfn.UNIQUE(_xlfn.HSTACK(INDEX(_xlpm.pairs,,1),INDEX(_xlpm.pairs,,4))),_xlpm.sortedPairs,_xlfn._xlws.SORT(_xlpm.uniquePairs,1,1),IF(ROW()-1<=ROWS(_xlpm.sortedPairs),INDEX(_xlpm.sortedPairs,ROW()-1,1),"")),"")} | M93: {=IFERROR(_xlfn.LET(_xlpm.pairs,_xlfn._xlws.FILTER($A$2:$D$391,($A$2:$A$391<>"")*(TRIM($D$2:$D$391)<>"")),_xlpm.uniquePairs,_xlfn.UNIQUE(_xlfn.HSTACK(INDEX(_xlpm.pairs,,1),INDEX(_xlpm.pairs,,4))),_xlpm.sortedPairs,_xlfn._xlws.SORT(_xlpm.uniquePairs,1,1),IF(ROW()-1<=ROWS(_xlpm.sortedPairs),INDEX(_xlpm.sortedPairs,ROW()-1,2),"")),"")} | N93: {=IF(OR(L93="",M93=""),"",IFERROR(INDEX($E$2:$E$391,MATCH(1,($A$2:$A$391=L93)*($D$2:$D$391=M93),0)),""))} | O93: =IF(OR(L93="",M93=""),"",SUMIFS($J$2:$J$391,$A$2:$A$391,L93,$D$2:$D$391,M93))
A94: TIPA 312MFGW | B94: Ext. A (Out - Chillroll) | C94: AO-PBS | D94: =IF(C94="","",IFERROR(_xlfn.XLOOKUP(C94,HELPER!$A$2:$A$76,HELPER!$B$2:$B$76,""),D94)) | E94: =IFERROR(_xlfn.XLOOKUP(D94,HELPER!$B:$B,HELPER!$C:$C,""),"") | F94: =IFERROR(_xlfn.XLOOKUP(D94,HELPER!$B:$B,HELPER!$D:$D,""),"") | G94: 8 | H94: 0.015 | I94: =IF(AND(H94<>"",IFERROR(_xlfn.XLOOKUP(D94,HELPER!$B:$B,HELPER!$E:$E,""),"")=""),"Missing price",IFERROR(_xlfn.XLOOKUP(D94,HELPER!$B:$B,HELPER!$E:$E,"")," ")) | J94: =IFERROR(H94*(IF(G94=8,I94*HELPER!$G$2,BOM!I94*HELPER!$G$3))," ") | L94: {=IFERROR(_xlfn.LET(_xlpm.pairs,_xlfn._xlws.FILTER($A$2:$D$391,($A$2:$A$391<>"")*(TRIM($D$2:$D$391)<>"")),_xlpm.uniquePairs,_xlfn.UNIQUE(_xlfn.HSTACK(INDEX(_xlpm.pairs,,1),INDEX(_xlpm.pairs,,4))),_xlpm.sortedPairs,_xlfn._xlws.SORT(_xlpm.uniquePairs,1,1),IF(ROW()-1<=ROWS(_xlpm.sortedPairs),INDEX(_xlpm.sortedPairs,ROW()-1,1),"")),"")} | M94: {=IFERROR(_xlfn.LET(_xlpm.pairs,_xlfn._xlws.FILTER($A$2:$D$391,($A$2:$A$391<>"")*(TRIM($D$2:$D$391)<>"")),_xlpm.uniquePairs,_xlfn.UNIQUE(_xlfn.HSTACK(INDEX(_xlpm.pairs,,1),INDEX(_xlpm.pairs,,4))),_xlpm.sortedPairs,_xlfn._xlws.SORT(_xlpm.uniquePairs,1,1),IF(ROW()-1<=ROWS(_xlpm.sortedPairs),INDEX(_xlpm.sortedPairs,ROW()-1,2),"")),"")} | N94: {=IF(OR(L94="",M94=""),"",IFERROR(INDEX($E$2:$E$391,MATCH(1,($A$2:$A$391=L94)*($D$2:$D$391=M94),0)),""))} | O94: =IF(OR(L94="",M94=""),"",SUMIFS($J$2:$J$391,$A$2:$A$391,L94,$D$2:$D$391,M94))
A95: TIPA 312MFGW | B95: Ext. A (Out - Chillroll) | D95: =IF(C95="","",IFERROR(_xlfn.XLOOKUP(C95,HELPER!$A$2:$A$76,HELPER!$B$2:$B$76,""),D95)) | E95: =IFERROR(_xlfn.XLOOKUP(D95,HELPER!$B:$B,HELPER!$C:$C,""),"") | F95: =IFERROR(_xlfn.XLOOKUP(D95,HELPER!$B:$B,HELPER!$D:$D,""),"") | G95: 8 | I95: =IF(AND(H95<>"",IFERROR(_xlfn.XLOOKUP(D95,HELPER!$B:$B,HELPER!$E:$E,""),"")=""),"Missing price",IFERROR(_xlfn.XLOOKUP(D95,HELPER!$B:$B,HELPER!$E:$E,"")," ")) | J95: =IFERROR(H95*(IF(G95=8,I95*HELPER!$G$2,BOM!I95*HELPER!$G$3))," ") | L95: {=IFERROR(_xlfn.LET(_xlpm.pairs,_xlfn._xlws.FILTER($A$2:$D$391,($A$2:$A$391<>"")*(TRIM($D$2:$D$391)<>"")),_xlpm.uniquePairs,_xlfn.UNIQUE(_xlfn.HSTACK(INDEX(_xlpm.pairs,,1),INDEX(_xlpm.pairs,,4))),_xlpm.sortedPairs,_xlfn._xlws.SORT(_xlpm.uniquePairs,1,1),IF(ROW()-1<=ROWS(_xlpm.sortedPairs),INDEX(_xlpm.sortedPairs,ROW()-1,1),"")),"")} | M95: {=IFERROR(_xlfn.LET(_xlpm.pairs,_xlfn._xlws.FILTER($A$2:$D$391,($A$2:$A$391<>"")*(TRIM($D$2:$D$391)<>"")),_xlpm.uniquePairs,_xlfn.UNIQUE(_xlfn.HSTACK(INDEX(_xlpm.pairs,,1),INDEX(_xlpm.pairs,,4))),_xlpm.sortedPairs,_xlfn._xlws.SORT(_xlpm.uniquePairs,1,1),IF(ROW()-1<=ROWS(_xlpm.sortedPairs),INDEX(_xlpm.sortedPairs,ROW()-1,2),"")),"")} | N95: {=IF(OR(L95="",M95=""),"",IFERROR(INDEX($E$2:$E$391,MATCH(1,($A$2:$A$391=L95)*($D$2:$D$391=M95),0)),""))} | O95: =IF(OR(L95="",M95=""),"",SUMIFS($J$2:$J$391,$A$2:$A$391,L95,$D$2:$D$391,M95))
A96: TIPA 312MFGW | B96: Ext. A (Out - Chillroll) | D96: =IF(C96="","",IFERROR(_xlfn.XLOOKUP(C96,HELPER!$A$2:$A$76,HELPER!$B$2:$B$76,""),D96)) | E96: =IFERROR(_xlfn.XLOOKUP(D96,HELPER!$B:$B,HELPER!$C:$C,""),"") | F96: =IFERROR(_xlfn.XLOOKUP(D96,HELPER!$B:$B,HELPER!$D:$D,""),"") | G96: 8 | I96: =IF(AND(H96<>"",IFERROR(_xlfn.XLOOKUP(D96,HELPER!$B:$B,HELPER!$E:$E,""),"")=""),"Missing price",IFERROR(_xlfn.XLOOKUP(D96,HELPER!$B:$B,HELPER!$E:$E,"")," ")) | J96: =IFERROR(H96*(IF(G96=8,I96*HELPER!$G$2,BOM!I96*HELPER!$G$3))," ") | L96: {=IFERROR(_xlfn.LET(_xlpm.pairs,_xlfn._xlws.FILTER($A$2:$D$391,($A$2:$A$391<>"")*(TRIM($D$2:$D$391)<>"")),_xlpm.uniquePairs,_xlfn.UNIQUE(_xlfn.HSTACK(INDEX(_xlpm.pairs,,1),INDEX(_xlpm.pairs,,4))),_xlpm.sortedPairs,_xlfn._xlws.SORT(_xlpm.uniquePairs,1,1),IF(ROW()-1<=ROWS(_xlpm.sortedPairs),INDEX(_xlpm.sortedPairs,ROW()-1,1),"")),"")} | M96: {=IFERROR(_xlfn.LET(_xlpm.pairs,_xlfn._xlws.FILTER($A$2:$D$391,($A$2:$A$391<>"")*(TRIM($D$2:$D$391)<>"")),_xlpm.uniquePairs,_xlfn.UNIQUE(_xlfn.HSTACK(INDEX(_xlpm.pairs,,1),INDEX(_xlpm.pairs,,4))),_xlpm.sortedPairs,_xlfn._xlws.SORT(_xlpm.uniquePairs,1,1),IF(ROW()-1<=ROWS(_xlpm.sortedPairs),INDEX(_xlpm.sortedPairs,ROW()-1,2),"")),"")} | N96: {=IF(OR(L96="",M96=""),"",IFERROR(INDEX($E$2:$E$391,MATCH(1,($A$2:$A$391=L96)*($D$2:$D$391=M96),0)),""))} | O96: =IF(OR(L96="",M96=""),"",SUMIFS($J$2:$J$391,$A$2:$A$391,L96,$D$2:$D$391,M96))
A97: TIPA 312MFGW | B97: Ext. A (Out - Chillroll) | D97: =IF(C97="","",IFERROR(_xlfn.XLOOKUP(C97,HELPER!$A$2:$A$76,HELPER!$B$2:$B$76,""),D97)) | E97: =IFERROR(_xlfn.XLOOKUP(D97,HELPER!$B:$B,HELPER!$C:$C,""),"") | F97: =IFERROR(_xlfn.XLOOKUP(D97,HELPER!$B:$B,HELPER!$D:$D,""),"") | G97: 8 | I97: =IF(AND(H97<>"",IFERROR(_xlfn.XLOOKUP(D97,HELPER!$B:$B,HELPER!$E:$E,""),"")=""),"Missing price",IFERROR(_xlfn.XLOOKUP(D97,HELPER!$B:$B,HELPER!$E:$E,"")," ")) | J97: =IFERROR(H97*(IF(G97=8,I97*HELPER!$G$2,BOM!I97*HELPER!$G$3))," ") | L97: {=IFERROR(_xlfn.LET(_xlpm.pairs,_xlfn._xlws.FILTER($A$2:$D$391,($A$2:$A$391<>"")*(TRIM($D$2:$D$391)<>"")),_xlpm.uniquePairs,_xlfn.UNIQUE(_xlfn.HSTACK(INDEX(_xlpm.pairs,,1),INDEX(_xlpm.pairs,,4))),_xlpm.sortedPairs,_xlfn._xlws.SORT(_xlpm.uniquePairs,1,1),IF(ROW()-1<=ROWS(_xlpm.sortedPairs),INDEX(_xlpm.sortedPairs,ROW()-1,1),"")),"")} | M97: {=IFERROR(_xlfn.LET(_xlpm.pairs,_xlfn._xlws.FILTER($A$2:$D$391,($A$2:$A$391<>"")*(TRIM($D$2:$D$391)<>"")),_xlpm.uniquePairs,_xlfn.UNIQUE(_xlfn.HSTACK(INDEX(_xlpm.pairs,,1),INDEX(_xlpm.pairs,,4))),_xlpm.sortedPairs,_xlfn._xlws.SORT(_xlpm.uniquePairs,1,1),IF(ROW()-1<=ROWS(_xlpm.sortedPairs),INDEX(_xlpm.sortedPairs,ROW()-1,2),"")),"")} | N97: {=IF(OR(L97="",M97=""),"",IFERROR(INDEX($E$2:$E$391,MATCH(1,($A$2:$A$391=L97)*($D$2:$D$391=M97),0)),""))} | O97: =IF(OR(L97="",M97=""),"",SUMIFS($J$2:$J$391,$A$2:$A$391,L97,$D$2:$D$391,M97))
A98: TIPA 312MFGW | B98: Ext. A (Out - Chillroll) | D98: =IF(C98="","",IFERROR(_xlfn.XLOOKUP(C98,HELPER!$A$2:$A$76,HELPER!$B$2:$B$76,""),D98)) | E98: =IFERROR(_xlfn.XLOOKUP(D98,HELPER!$B:$B,HELPER!$C:$C,""),"") | F98: =IFERROR(_xlfn.XLOOKUP(D98,HELPER!$B:$B,HELPER!$D:$D,""),"") | G98: 8 | I98: =IF(AND(H98<>"",IFERROR(_xlfn.XLOOKUP(D98,HELPER!$B:$B,HELPER!$E:$E,""),"")=""),"Missing price",IFERROR(_xlfn.XLOOKUP(D98,HELPER!$B:$B,HELPER!$E:$E,"")," ")) | J98: =IFERROR(H98*(IF(G98=8,I98*HELPER!$G$2,BOM!I98*HELPER!$G$3))," ") | L98: {=IFERROR(_xlfn.LET(_xlpm.pairs,_xlfn._xlws.FILTER($A$2:$D$391,($A$2:$A$391<>"")*(TRIM($D$2:$D$391)<>"")),_xlpm.uniquePairs,_xlfn.UNIQUE(_xlfn.HSTACK(INDEX(_xlpm.pairs,,1),INDEX(_xlpm.pairs,,4))),_xlpm.sortedPairs,_xlfn._xlws.SORT(_xlpm.uniquePairs,1,1),IF(ROW()-1<=ROWS(_xlpm.sortedPairs),INDEX(_xlpm.sortedPairs,ROW()-1,1),"")),"")} | M98: {=IFERROR(_xlfn.LET(_xlpm.pairs,_xlfn._xlws.FILTER($A$2:$D$391,($A$2:$A$391<>"")*(TRIM($D$2:$D$391)<>"")),_xlpm.uniquePairs,_xlfn.UNIQUE(_xlfn.HSTACK(INDEX(_xlpm.pairs,,1),INDEX(_xlpm.pairs,,4))),_xlpm.sortedPairs,_xlfn._xlws.SORT(_xlpm.uniquePairs,1,1),IF(ROW()-1<=ROWS(_xlpm.sortedPairs),INDEX(_xlpm.sortedPairs,ROW()-1,2),"")),"")} | N98: {=IF(OR(L98="",M98=""),"",IFERROR(INDEX($E$2:$E$391,MATCH(1,($A$2:$A$391=L98)*($D$2:$D$391=M98),0)),""))} | O98: =IF(OR(L98="",M98=""),"",SUMIFS($J$2:$J$391,$A$2:$A$391,L98,$D$2:$D$391,M98))
A99: TIPA 312MFGW | B99: Ext. A (Out - Chillroll) | D99: =IF(C99="","",IFERROR(_xlfn.XLOOKUP(C99,HELPER!$A$2:$A$76,HELPER!$B$2:$B$76,""),D99)) | E99: =IFERROR(_xlfn.XLOOKUP(D99,HELPER!$B:$B,HELPER!$C:$C,""),"") | F99: =IFERROR(_xlfn.XLOOKUP(D99,HELPER!$B:$B,HELPER!$D:$D,""),"") | G99: 8 | I99: =IF(AND(H99<>"",IFERROR(_xlfn.XLOOKUP(D99,HELPER!$B:$B,HELPER!$E:$E,""),"")=""),"Missing price",IFERROR(_xlfn.XLOOKUP(D99,HELPER!$B:$B,HELPER!$E:$E,"")," ")) | J99: =IFERROR(H99*(IF(G99=8,I99*HELPER!$G$2,BOM!I99*HELPER!$G$3))," ") | L99: {=IFERROR(_xlfn.LET(_xlpm.pairs,_xlfn._xlws.FILTER($A$2:$D$391,($A$2:$A$391<>"")*(TRIM($D$2:$D$391)<>"")),_xlpm.uniquePairs,_xlfn.UNIQUE(_xlfn.HSTACK(INDEX(_xlpm.pairs,,1),INDEX(_xlpm.pairs,,4))),_xlpm.sortedPairs,_xlfn._xlws.SORT(_xlpm.uniquePairs,1,1),IF(ROW()-1<=ROWS(_xlpm.sortedPairs),INDEX(_xlpm.sortedPairs,ROW()-1,1),"")),"")} | M99: {=IFERROR(_xlfn.LET(_xlpm.pairs,_xlfn._xlws.FILTER($A$2:$D$391,($A$2:$A$391<>"")*(TRIM($D$2:$D$391)<>"")),_xlpm.uniquePairs,_xlfn.UNIQUE(_xlfn.HSTACK(INDEX(_xlpm.pairs,,1),INDEX(_xlpm.pairs,,4))),_xlpm.sortedPairs,_xlfn._xlws.SORT(_xlpm.uniquePairs,1,1),IF(ROW()-1<=ROWS(_xlpm.sortedPairs),INDEX(_xlpm.sortedPairs,ROW()-1,2),"")),"")} | N99: {=IF(OR(L99="",M99=""),"",IFERROR(INDEX($E$2:$E$391,MATCH(1,($A$2:$A$391=L99)*($D$2:$D$391=M99),0)),""))} | O99: =IF(OR(L99="",M99=""),"",SUMIFS($J$2:$J$391,$A$2:$A$391,L99,$D$2:$D$391,M99))
A100: TIPA 312MFGW | B100: Ext. A (Out - Chillroll) | D100: =IF(C100="","",IFERROR(_xlfn.XLOOKUP(C100,HELPER!$A$2:$A$76,HELPER!$B$2:$B$76,""),D100)) | E100: =IFERROR(_xlfn.XLOOKUP(D100,HELPER!$B:$B,HELPER!$C:$C,""),"") | F100: =IFERROR(_xlfn.XLOOKUP(D100,HELPER!$B:$B,HELPER!$D:$D,""),"") | G100: 8 | I100: =IF(AND(H100<>"",IFERROR(_xlfn.XLOOKUP(D100,HELPER!$B:$B,HELPER!$E:$E,""),"")=""),"Missing price",IFERROR(_xlfn.XLOOKUP(D100,HELPER!$B:$B,HELPER!$E:$E,"")," ")) | J100: =IFERROR(H100*(IF(G100=8,I100*HELPER!$G$2,BOM!I100*HELPER!$G$3))," ") | L100: {=IFERROR(_xlfn.LET(_xlpm.pairs,_xlfn._xlws.FILTER($A$2:$D$391,($A$2:$A$391<>"")*(TRIM($D$2:$D$391)<>"")),_xlpm.uniquePairs,_xlfn.UNIQUE(_xlfn.HSTACK(INDEX(_xlpm.pairs,,1),INDEX(_xlpm.pairs,,4))),_xlpm.sortedPairs,_xlfn._xlws.SORT(_xlpm.uniquePairs,1,1),IF(ROW()-1<=ROWS(_xlpm.sortedPairs),INDEX(_xlpm.sortedPairs,ROW()-1,1),"")),"")} | M100: {=IFERROR(_xlfn.LET(_xlpm.pairs,_xlfn._xlws.FILTER($A$2:$D$391,($A$2:$A$391<>"")*(TRIM($D$2:$D$391)<>"")),_xlpm.uniquePairs,_xlfn.UNIQUE(_xlfn.HSTACK(INDEX(_xlpm.pairs,,1),INDEX(_xlpm.pairs,,4))),_xlpm.sortedPairs,_xlfn._xlws.SORT(_xlpm.uniquePairs,1,1),IF(ROW()-1<=ROWS(_xlpm.sortedPairs),INDEX(_xlpm.sortedPairs,ROW()-1,2),"")),"")} | N100: {=IF(OR(L100="",M100=""),"",IFERROR(INDEX($E$2:$E$391,MATCH(1,($A$2:$A$391=L100)*($D$2:$D$391=M100),0)),""))} | O100: =IF(OR(L100="",M100=""),"",SUMIFS($J$2:$J$391,$A$2:$A$391,L100,$D$2:$D$391,M100))
...

Sheet Film Pricing
A1: Dropdown | B1: Manual | C1: Dropdown | W1: 0.2
A2: Film Type | B2: Width (mm) | C2: Thickness (µ) | D2: Density | E2: Weight (Kg) | F2: Weight Override | G2: Length (Mr) | H2: Total KG in one Meter | I2: Total Kg Produced | J2: Hourly rate | K2: 1Kg production cost | L2: RM cost in 1 Kg | M2: Total RM and Production | N2: Depreciation | O2: Total Cost and depreciation | P2: Thickness waste | Q2: Other costs | R2: Supplier | S2: Printing | T2: Printing Waste | U2: Setup | V2: Shiping Destination | W2: Shiping cost | X2: Total Cost | Y2: Margin | Z2: Sell Price | AF2: 📊 MARGIN | AG2: 0.225 | AJ2: 📊 MARGIN | AK2: 0.25 | AN2: 📊 MARGIN | AO2: 0.25 | AR2: 📊 MARGIN | AS2: 0.25 | AV2: 📊 MARGIN | AW2: 0.25 | AZ2: 📊 MARGIN | BA2: 0.25
A3: =AG4 | B3: =AG5 | C3: =AG6 | D3: =AG7 | E3: =IF(OR(A3="",A3="-"),"",IF(AND(G3<>"",H3<>""),G3*H3,"")) | F3: =IF($AG$22="By Length", $AG$23*H3, $AG$8) | G3: =AG9 | H3: =IF(OR(A3="",A3="-"),"",IF(AND(B3<>"",C3<>"",D3<>""),D3*(C3/1000)*(B3/1000),"")) | I3: =IF(OR(A3="",A3="-"),"",IF(F3<>"",F3,IF(AND(G3<>"",H3<>""),G3*H3,""))) | J3: =AG10 | K3: =IF(AND(I3<>"",I3<>0), J3/I3 + 0.2, "") | L3: =IFERROR(VLOOKUP(A3,BOM!$Q$2:$R$50,2,FALSE),0) | M3: =IFERROR((L3+K3),0) | N3: =IF(OR(I3="",I3=0),"",VLOOKUP(I3,HELPER!$AM$2:$AN$6,2,TRUE)) | O3: =IF(AND(M3<>"",N3<>""),M3*(1+N3),"") | P3: =IF(AND(Table1[[#This Row],[Thickness (µ)]]<>"",Table1[[#This Row],[RM cost in 1 Kg]]<>""), VLOOKUP(Table1[[#This Row],[Thickness (µ)]], HELPER!$BH$3:$BI$5, 2, TRUE) * Table1[[#This Row],[RM cost in 1 Kg]], "") | Q3: 0.3 | R3: Marma | S3: {=IF(OR(AG12="Not Printed",AG13=0,AG13="0"),0,_xlfn.LET(_xlpm.len,AG9,_xlpm.colors,AG13,_xlpm.colNum,IF(_xlpm.len<3000,1,IF(_xlpm.len<10000,2,IF(_xlpm.len<25000,3,IF(_xlpm.len<50000,4,IF(_xlpm.len<100000,5,IF(_xlpm.len<250000,6,IF(_xlpm.len<500000,7,8))))))),_xlpm.widthRow,IF(AG5<=760,0,5),_xlpm.colorOffset,IF(OR(_xlpm.colors=1,_xlpm.colors=2,_xlpm.colors="1-2"),1,IF(OR(_xlpm.colors=3,_xlpm.colors=4,_xlpm.colors="3-4"),2,IF(OR(_xlpm.colors>=5,_xlpm.colors="5-6",_xlpm.colors="5-8"),3,0))),_xlpm.supplierRow,IF(AG14="Marma",3,IF(AG14="Bastin",13,0)),IF(OR(_xlpm.supplierRow=0,_xlpm.colorOffset=0),0,INDEX('Lmntn & Prntng- Marma & Bastin '!$D:$K,_xlpm.supplierRow+_xlpm.widthRow+_xlpm.colorOffset,_xlpm.colNum))))} | T3: =IF($AG$12="Printed",$L3*0.028,0) | U3: =IF(Table1[[#This Row],[RM cost in 1 Kg]]>0,((1500+3000)/30000),0) | V3: =AG11 | W3: =IFERROR(IF(V3="Europe to Canada",IF(I3<1000,(I3/1000)*VLOOKUP(1000,HELPER!$AG$4:$AH$8,2,FALSE)/I3,VLOOKUP(I3,HELPER!$AG$4:$AH$8,2,TRUE)/I3),VLOOKUP(V3,HELPER!$AF$2:$AH$3,3,FALSE)),0) | X3: =IFERROR((Table1[[#This Row],[Total Cost and depreciation]]+Table1[[#This Row],[Thickness waste]]+Table1[[#This Row],[Other costs]]+Table1[[#This Row],[Setup]]+Table1[[#This Row],[Shiping cost]]+Table1[[#This Row],[Printing Waste]]+(Table1[[#This Row],[Printing]]*Table1[[#This Row],[Length (Mr)]]/Table1[[#This Row],[Weight Override]])),0) | Y3: =Table1[[#This Row],[Total Cost]]*($W$1) | Z3: =Table1[[#This Row],[Total Cost]]+Table1[[#This Row],[Margin]] | AF3: 🧮 CALCULATOR 1 | AJ3: 🧮 CALCULATOR 2 | AN3: 🧮 CALCULATOR 3 | AR3: 🧮 CALCULATOR 4 | AV3: 🧮 CALCULATOR 5 | AZ3: 🧮 CALCULATOR 6
A4: =AK4 | B4: =AK5 | C4: =AK6 | D4: =AK7 | E4: =IF(OR(A4="",A4="-"),"",IF(AND(G4<>"",H4<>""),G4*H4,"")) | F4: =IF($AK$22="By Length", $AK$23*H4, $AK$8) | G4: =AK9 | H4: =IF(OR(A4="",A4="-"),"",IF(AND(B4<>"",C4<>"",D4<>""),D4*(C4/1000)*(B4/1000),"")) | I4: =IF(OR(A4="",A4="-"),"",IF(F4<>"",F4,IF(AND(G4<>"",H4<>""),G4*H4,""))) | J4: =AK10 | K4: 1.22 | L4: =IFERROR(VLOOKUP(A4,BOM!$Q$2:$R$50,2,FALSE),0) | M4: =IFERROR((L4+K4),0) | N4: =IF(OR(I4="",I4=0),"",VLOOKUP(I4,HELPER!$AM$2:$AN$6,2,TRUE)) | O4: =IF(AND(M4<>"",N4<>""),M4*(1+N4),"") | P4: =IF(AND(Table1[[#This Row],[Thickness (µ)]]<>"",Table1[[#This Row],[RM cost in 1 Kg]]<>""), VLOOKUP(Table1[[#This Row],[Thickness (µ)]], HELPER!$BH$3:$BI$5, 2, TRUE) * Table1[[#This Row],[RM cost in 1 Kg]], "") | Q4: 0 | R4: =$AK$14 | S4: {=IF(OR(AK12="Not Printed",AK13=0,AK13="0"),0,_xlfn.LET(_xlpm.len,AK9,_xlpm.colors,AK13,_xlpm.colNum,IF(_xlpm.len<3000,1,IF(_xlpm.len<10000,2,IF(_xlpm.len<25000,3,IF(_xlpm.len<50000,4,IF(_xlpm.len<100000,5,IF(_xlpm.len<250000,6,IF(_xlpm.len<500000,7,8))))))),_xlpm.widthRow,IF(AK5<=760,0,5),_xlpm.colorOffset,IF(OR(_xlpm.colors=1,_xlpm.colors=2,_xlpm.colors="1-2"),1,IF(OR(_xlpm.colors=3,_xlpm.colors=4,_xlpm.colors="3-4"),2,IF(OR(_xlpm.colors>=5,_xlpm.colors="5-6",_xlpm.colors="5-8"),3,0))),_xlpm.supplierRow,IF(AK14="Marma",3,IF(AK14="Bastin",13,0)),IF(OR(_xlpm.supplierRow=0,_xlpm.colorOffset=0),0,INDEX('Lmntn & Prntng- Marma & Bastin '!$D:$K,_xlpm.supplierRow+_xlpm.widthRow+_xlpm.colorOffset,_xlpm.colNum))))} | T4: =IF($AK$12="Printed",$L4*0.028,0) | U4: =IF(Table1[[#This Row],[RM cost in 1 Kg]]>0,((1500+3000)/30000),0) | V4: =AK11 | W4: =IFERROR(IF(V4="Europe to Canada",IF(I4<1000,(I4/1000)*VLOOKUP(1000,HELPER!$AG$4:$AH$8,2,FALSE)/I4,VLOOKUP(I4,HELPER!$AG$4:$AH$8,2,TRUE)/I4),VLOOKUP(V4,HELPER!$AF$2:$AH$3,3,FALSE)),0) | X4: =IFERROR((Table1[[#This Row],[Total Cost and depreciation]]+Table1[[#This Row],[Thickness waste]]+Table1[[#This Row],[Other costs]]+Table1[[#This Row],[Setup]]+Table1[[#This Row],[Shiping cost]]+Table1[[#This Row],[Printing Waste]]+(Table1[[#This Row],[Printing]]*Table1[[#This Row],[Length (Mr)]]/Table1[[#This Row],[Weight Override]])),0) | Y4: =Table1[[#This Row],[Total Cost]]*($W$1) | Z4: =Table1[[#This Row],[Total Cost]]+Table1[[#This Row],[Margin]] | AF4: 🎬 Film Type | AG4: TIPA 302FG | AJ4: 🎬 Film Type | AK4: TIPA 302FG | AN4: 🎬 Film Type | AO4: TIPA 302FG | AR4: 🎬 Film Type | AS4: TIPA 302FG | AV4: 🎬 Film Type | AW4: TIPA 302FG | AZ4: 🎬 Film Type | BA4: TIPA 302FG
A5: =AO4 | B5: =AO5 | C5: =AO6 | D5: =AO7 | E5: =IF(OR(A5="",A5="-"),"",IF(AND(G5<>"",H5<>""),G5*H5,"")) | F5: =IF($AO$22="By Length", $AO$23*H5, $AO$8) | G5: =AO9 | H5: =IF(OR(A5="",A5="-"),"",IF(AND(B5<>"",C5<>"",D5<>""),D5*(C5/1000)*(B5/1000),"")) | I5: =IF(OR(A5="",A5="-"),"",IF(F5<>"",F5,IF(AND(G5<>"",H5<>""),G5*H5,""))) | J5: =AO10 | K5: 1.22 | L5: =IFERROR(VLOOKUP(A5,BOM!$Q$2:$R$50,2,FALSE),0) | M5: =IFERROR((L5+K5),0) | N5: =IF(OR(I5="",I5=0),"",VLOOKUP(I5,HELPER!$AM$2:$AN$6,2,TRUE)) | O5: =IF(AND(M5<>"",N5<>""),M5*(1+N5),"") | P5: =IF(AND(Table1[[#This Row],[Thickness (µ)]]<>"",Table1[[#This Row],[RM cost in 1 Kg]]<>""), VLOOKUP(Table1[[#This Row],[Thickness (µ)]], HELPER!$BH$3:$BI$5, 2, TRUE) * Table1[[#This Row],[RM cost in 1 Kg]], "") | Q5: 0 | R5: =$AO$14 | S5: {=IF(OR(AO12="Not Printed",AO13=0,AO13="0"),0,_xlfn.LET(_xlpm.len,AO9,_xlpm.colors,AO13,_xlpm.colNum,IF(_xlpm.len<3000,1,IF(_xlpm.len<10000,2,IF(_xlpm.len<25000,3,IF(_xlpm.len<50000,4,IF(_xlpm.len<100000,5,IF(_xlpm.len<250000,6,IF(_xlpm.len<500000,7,8))))))),_xlpm.widthRow,IF(AO5<=760,0,5),_xlpm.colorOffset,IF(OR(_xlpm.colors=1,_xlpm.colors=2,_xlpm.colors="1-2"),1,IF(OR(_xlpm.colors=3,_xlpm.colors=4,_xlpm.colors="3-4"),2,IF(OR(_xlpm.colors>=5,_xlpm.colors="5-6",_xlpm.colors="5-8"),3,0))),_xlpm.supplierRow,IF(AO14="Marma",3,IF(AO14="Bastin",13,0)),IF(OR(_xlpm.supplierRow=0,_xlpm.colorOffset=0),0,INDEX('Lmntn & Prntng- Marma & Bastin '!$D:$K,_xlpm.supplierRow+_xlpm.widthRow+_xlpm.colorOffset,_xlpm.colNum))))} | T5: =IF($AO$12="Printed",$L5*0.028,0) | U5: =IF(Table1[[#This Row],[RM cost in 1 Kg]]>0,((1500+3000)/30000),0) | V5: =AO11 | W5: =IFERROR(IF(V5="Europe to Canada",IF(I5<1000,(I5/1000)*VLOOKUP(1000,HELPER!$AG$4:$AH$8,2,FALSE)/I5,VLOOKUP(I5,HELPER!$AG$4:$AH$8,2,TRUE)/I5),VLOOKUP(V5,HELPER!$AF$2:$AH$3,3,FALSE)),0) | X5: =IFERROR((Table1[[#This Row],[Total Cost and depreciation]]+Table1[[#This Row],[Thickness waste]]+Table1[[#This Row],[Other costs]]+Table1[[#This Row],[Setup]]+Table1[[#This Row],[Shiping cost]]+Table1[[#This Row],[Printing Waste]]+(Table1[[#This Row],[Printing]]*Table1[[#This Row],[Length (Mr)]]/Table1[[#This Row],[Weight Override]])),0) | Y5: =Table1[[#This Row],[Total Cost]]*($W$1) | Z5: =Table1[[#This Row],[Total Cost]]+Table1[[#This Row],[Margin]] | AF5: 📐 Width | AG5: 1800 | AH5: mm | AJ5: 📐 Width | AK5: 406 | AL5: mm | AN5: 📐 Width | AO5: 406 | AP5: mm | AR5: 📐 Width | AS5: 406 | AT5: mm | AV5: 📐 Width | AW5: 406 | AX5: mm | AZ5: 📐 Width | BA5: 406 | BB5: mm
A6: =AS4 | B6: =AS5 | C6: =AS6 | D6: =AS7 | E6: =IF(OR(A6="",A6="-"),"",IF(AND(G6<>"",H6<>""),G6*H6,"")) | F6: =IF($AS$22="By Length", $AS$23*H6, $AS$8) | G6: =AS9 | H6: =IF(OR(A6="",A6="-"),"",IF(AND(B6<>"",C6<>"",D6<>""),D6*(C6/1000)*(B6/1000),"")) | I6: =IF(OR(A6="",A6="-"),"",IF(F6<>"",F6,IF(AND(G6<>"",H6<>""),G6*H6,""))) | J6: =AS10 | K6: 1.22 | L6: =IFERROR(VLOOKUP(A6,BOM!$Q$2:$R$50,2,FALSE),0) | M6: =IFERROR((L6+K6),0) | N6: =IF(OR(I6="",I6=0),"",VLOOKUP(I6,HELPER!$AM$2:$AN$6,2,TRUE)) | O6: =IF(AND(M6<>"",N6<>""),M6*(1+N6),"") | P6: =IF(AND(Table1[[#This Row],[Thickness (µ)]]<>"",Table1[[#This Row],[RM cost in 1 Kg]]<>""), VLOOKUP(Table1[[#This Row],[Thickness (µ)]], HELPER!$BH$3:$BI$5, 2, TRUE) * Table1[[#This Row],[RM cost in 1 Kg]], "") | Q6: 0 | R6: =$AS$14 | S6: {=IF(OR(AS12="Not Printed",AS13=0,AS13="0"),0,_xlfn.LET(_xlpm.len,AS9,_xlpm.colors,AS13,_xlpm.colNum,IF(_xlpm.len<3000,1,IF(_xlpm.len<10000,2,IF(_xlpm.len<25000,3,IF(_xlpm.len<50000,4,IF(_xlpm.len<100000,5,IF(_xlpm.len<250000,6,IF(_xlpm.len<500000,7,8))))))),_xlpm.widthRow,IF(AS5<=760,0,5),_xlpm.colorOffset,IF(OR(_xlpm.colors=1,_xlpm.colors=2,_xlpm.colors="1-2"),1,IF(OR(_xlpm.colors=3,_xlpm.colors=4,_xlpm.colors="3-4"),2,IF(OR(_xlpm.colors>=5,_xlpm.colors="5-6",_xlpm.colors="5-8"),3,0))),_xlpm.supplierRow,IF(AS14="Marma",3,IF(AS14="Bastin",13,0)),IF(OR(_xlpm.supplierRow=0,_xlpm.colorOffset=0),0,INDEX('Lmntn & Prntng- Marma & Bastin '!$D:$K,_xlpm.supplierRow+_xlpm.widthRow+_xlpm.colorOffset,_xlpm.colNum))))} | T6: =IF($AS$12="Printed",$L6*0.028,0) | U6: =IF(Table1[[#This Row],[RM cost in 1 Kg]]>0,((1500+3000)/30000),0) | V6: =AS11 | W6: =IFERROR(IF(V6="Europe to Canada",IF(I6<1000,(I6/1000)*VLOOKUP(1000,HELPER!$AG$4:$AH$8,2,FALSE)/I6,VLOOKUP(I6,HELPER!$AG$4:$AH$8,2,TRUE)/I6),VLOOKUP(V6,HELPER!$AF$2:$AH$3,3,FALSE)),0) | X6: =IFERROR((Table1[[#This Row],[Total Cost and depreciation]]+Table1[[#This Row],[Thickness waste]]+Table1[[#This Row],[Other costs]]+Table1[[#This Row],[Setup]]+Table1[[#This Row],[Shiping cost]]+Table1[[#This Row],[Printing Waste]]+(Table1[[#This Row],[Printing]]*Table1[[#This Row],[Length (Mr)]]/Table1[[#This Row],[Weight Override]])),0) | Y6: =Table1[[#This Row],[Total Cost]]*($W$1) | Z6: =Table1[[#This Row],[Total Cost]]+Table1[[#This Row],[Margin]] | AF6: 📏 Thickness | AG6: 20 | AH6: µ | AJ6: 📏 Thickness | AK6: 20 | AL6: µ | AN6: 📏 Thickness | AO6: 20 | AP6: µ | AR6: 📏 Thickness | AS6: 20 | AT6: µ | AV6: 📏 Thickness | AW6: 20 | AX6: µ | AZ6: 📏 Thickness | BA6: 20 | BB6: µ
A7: =AW4 | B7: =AW5 | C7: =AW6 | D7: =AW7 | E7: =IF(OR(A7="",A7="-"),"",IF(AND(G7<>"",H7<>""),G7*H7,"")) | F7: =IF($AW$22="By Length", $AW$23*H7, $AW$8) | G7: =AW9 | H7: =IF(OR(A7="",A7="-"),"",IF(AND(B7<>"",C7<>"",D7<>""),D7*(C7/1000)*(B7/1000),"")) | I7: =IF(OR(A7="",A7="-"),"",IF(F7<>"",F7,IF(AND(G7<>"",H7<>""),G7*H7,""))) | J7: =AW10 | K7: 1.22 | L7: =IFERROR(VLOOKUP(A7,BOM!$Q$2:$R$50,2,FALSE),0) | M7: =IFERROR((L7+K7),0) | N7: =IF(OR(I7="",I7=0),"",VLOOKUP(I7,HELPER!$AM$2:$AN$6,2,TRUE)) | O7: =IF(AND(M7<>"",N7<>""),M7*(1+N7),"") | P7: =IF(AND(Table1[[#This Row],[Thickness (µ)]]<>"",Table1[[#This Row],[RM cost in 1 Kg]]<>""), VLOOKUP(Table1[[#This Row],[Thickness (µ)]], HELPER!$BH$3:$BI$5, 2, TRUE) * Table1[[#This Row],[RM cost in 1 Kg]], "") | Q7: 0 | R7: =$AW$14 | S7: {=IF(OR(AW12="Not Printed",AW13=0,AW13="0"),0,_xlfn.LET(_xlpm.len,AW9,_xlpm.colors,AW13,_xlpm.colNum,IF(_xlpm.len<3000,1,IF(_xlpm.len<10000,2,IF(_xlpm.len<25000,3,IF(_xlpm.len<50000,4,IF(_xlpm.len<100000,5,IF(_xlpm.len<250000,6,IF(_xlpm.len<500000,7,8))))))),_xlpm.widthRow,IF(AW5<=760,0,5),_xlpm.colorOffset,IF(OR(_xlpm.colors=1,_xlpm.colors=2,_xlpm.colors="1-2"),1,IF(OR(_xlpm.colors=3,_xlpm.colors=4,_xlpm.colors="3-4"),2,IF(OR(_xlpm.colors>=5,_xlpm.colors="5-6",_xlpm.colors="5-8"),3,0))),_xlpm.supplierRow,IF(AW14="Marma",3,IF(AW14="Bastin",13,0)),IF(OR(_xlpm.supplierRow=0,_xlpm.colorOffset=0),0,INDEX('Lmntn & Prntng- Marma & Bastin '!$D:$K,_xlpm.supplierRow+_xlpm.widthRow+_xlpm.colorOffset,_xlpm.colNum))))} | T7: =IF($AW$12="Printed",$L7*0.028,0) | U7: =IF(Table1[[#This Row],[RM cost in 1 Kg]]>0,((1500+3000)/30000),0) | V7: =AW11 | W7: =IFERROR(IF(V7="Europe to Canada",IF(I7<1000,(I7/1000)*VLOOKUP(1000,HELPER!$AG$4:$AH$8,2,FALSE)/I7,VLOOKUP(I7,HELPER!$AG$4:$AH$8,2,TRUE)/I7),VLOOKUP(V7,HELPER!$AF$2:$AH$3,3,FALSE)),0) | X7: =IFERROR((Table1[[#This Row],[Total Cost and depreciation]]+Table1[[#This Row],[Thickness waste]]+Table1[[#This Row],[Other costs]]+Table1[[#This Row],[Setup]]+Table1[[#This Row],[Shiping cost]]+Table1[[#This Row],[Printing Waste]]+(Table1[[#This Row],[Printing]]*Table1[[#This Row],[Length (Mr)]]/Table1[[#This Row],[Weight Override]])),0) | Y7: =Table1[[#This Row],[Total Cost]]*($W$1) | Z7: =Table1[[#This Row],[Total Cost]]+Table1[[#This Row],[Margin]] | AF7: ⚖️ Density | AG7: 1.25 | AH7: g/cm³ | AJ7: ⚖️ Density | AK7: 1.25 | AL7: g/cm³ | AN7: ⚖️ Density | AO7: 1.25 | AP7: g/cm³ | AR7: ⚖️ Density | AS7: 1.25 | AT7: g/cm³ | AV7: ⚖️ Density | AW7: 1.25 | AX7: g/cm³ | AZ7: ⚖️ Density | BA7: 1.25 | BB7: g/cm³
A8: =BA4 | B8: =BA5 | C8: =BA6 | D8: =BA7 | E8: =IF(OR(A8="",A8="-"),"",IF(AND(G8<>"",H8<>""),G8*H8,"")) | F8: =IF($BA$22="By Length", $BA$23*H8, $BA$8) | G8: =BA9 | H8: =IF(OR(A8="",A8="-"),"",IF(AND(B8<>"",C8<>"",D8<>""),D8*(C8/1000)*(B8/1000),"")) | I8: =IF(OR(A8="",A8="-"),"",IF(F8<>"",F8,IF(AND(G8<>"",H8<>""),G8*H8,""))) | J8: =BA10 | K8: 1.22 | L8: =IFERROR(VLOOKUP(A8,BOM!$Q$2:$R$50,2,FALSE),0) | M8: =IFERROR((L8+K8),0) | N8: =IF(OR(I8="",I8=0),"",VLOOKUP(I8,HELPER!$AM$2:$AN$6,2,TRUE)) | O8: =IF(AND(M8<>"",N8<>""),M8*(1+N8),"") | P8: =IF(AND(Table1[[#This Row],[Thickness (µ)]]<>"",Table1[[#This Row],[RM cost in 1 Kg]]<>""), VLOOKUP(Table1[[#This Row],[Thickness (µ)]], HELPER!$BH$3:$BI$5, 2, TRUE) * Table1[[#This Row],[RM cost in 1 Kg]], "") | Q8: 0 | R8: =$BA$14 | S8: {=IF(OR(BA12="Not Printed",BA13=0,BA13="0"),0,_xlfn.LET(_xlpm.len,BA9,_xlpm.colors,BA13,_xlpm.colNum,IF(_xlpm.len<3000,1,IF(_xlpm.len<10000,2,IF(_xlpm.len<25000,3,IF(_xlpm.len<50000,4,IF(_xlpm.len<100000,5,IF(_xlpm.len<250000,6,IF(_xlpm.len<500000,7,8))))))),_xlpm.widthRow,IF(BA5<=760,0,5),_xlpm.colorOffset,IF(OR(_xlpm.colors=1,_xlpm.colors=2,_xlpm.colors="1-2"),1,IF(OR(_xlpm.colors=3,_xlpm.colors=4,_xlpm.colors="3-4"),2,IF(OR(_xlpm.colors>=5,_xlpm.colors="5-6",_xlpm.colors="5-8"),3,0))),_xlpm.supplierRow,IF(BA14="Marma",3,IF(BA14="Bastin",13,0)),IF(OR(_xlpm.supplierRow=0,_xlpm.colorOffset=0),0,INDEX('Lmntn & Prntng- Marma & Bastin '!$D:$K,_xlpm.supplierRow+_xlpm.widthRow+_xlpm.colorOffset,_xlpm.colNum))))} | T8: =IF($BA$12="Printed",$L8*0.028,0) | U8: =IF(Table1[[#This Row],[RM cost in 1 Kg]]>0,((1500+3000)/30000),0) | V8: =BA11 | W8: =IFERROR(IF(V8="Europe to Canada",IF(I8<1000,(I8/1000)*VLOOKUP(1000,HELPER!$AG$4:$AH$8,2,FALSE)/I8,VLOOKUP(I8,HELPER!$AG$4:$AH$8,2,TRUE)/I8),VLOOKUP(V8,HELPER!$AF$2:$AH$3,3,FALSE)),0) | X8: =IFERROR((Table1[[#This Row],[Total Cost and depreciation]]+Table1[[#This Row],[Thickness waste]]+Table1[[#This Row],[Other costs]]+Table1[[#This Row],[Setup]]+Table1[[#This Row],[Shiping cost]]+Table1[[#This Row],[Printing Waste]]+(Table1[[#This Row],[Printing]]*Table1[[#This Row],[Length (Mr)]]/Table1[[#This Row],[Weight Override]])),0) | Y8: =Table1[[#This Row],[Total Cost]]*($W$1) | Z8: =Table1[[#This Row],[Total Cost]]+Table1[[#This Row],[Margin]] | AF8: 📦 Weight | AG8: 500 | AH8: Kg | AJ8: 📦 Weight | AK8: 1000 | AL8: Kg | AN8: 📦 Weight | AO8: 2000 | AP8: Kg | AR8: 📦 Weight | AS8: 3000 | AT8: Kg | AV8: 📦 Weight | AW8: 4000 | AX8: Kg | AZ8: 📦 Weight | BA8: 5000 | BB8: Kg
AF9: 📏 Length | AG9: =IF(AG22="By Length", IF(AG23="",0,AG23), IFERROR(AG8/H4,0)) | AH9: Mr | AJ9: 📏 Length | AK9: =IF(AK22="By Length", IF(AK23="",0,AK23), IFERROR(AK8/H5,0)) | AL9: Mr | AN9: 📏 Length | AO9: =IF(AO22="By Length", IF(AO23="",0,AO23), IFERROR(AO8/H6,0)) | AP9: Mr | AR9: 📏 Length | AS9: =IF(AS22="By Length", IF(AS23="",0,AS23), IFERROR(AS8/H7,0)) | AT9: Mr | AV9: 📏 Length | AW9: =IF(AW22="By Length", IF(AW23="",0,AW23), IFERROR(AW8/H8,0)) | AX9: Mr | AZ9: 📏 Length | BA9: =IF(BA22="By Length", IF(BA23="",0,BA23), IFERROR(BA8/#REF!,0)) | BB9: Mr
AF10: ⏱️ Hourly Rate | AG10: 510 | AH10: € | AJ10: ⏱️ Hourly Rate | AK10: 510 | AL10: € | AN10: ⏱️ Hourly Rate | AO10: 510 | AP10: € | AR10: ⏱️ Hourly Rate | AS10: 510 | AT10: € | AV10: ⏱️ Hourly Rate | AW10: 510 | AX10: € | AZ10: ⏱️ Hourly Rate | BA10: 0.15 | BB10: €
AF11: 🚚 Shipping | AG11: Europe to US | AJ11: 🚚 Shipping | AK11: Europe to Europe | AN11: 🚚 Shipping | AO11: Europe to US | AR11: 🚚 Shipping | AS11: Europe to Europe | AV11: 🚚 Shipping | AW11: Europe to Canada | AZ11: 🚚 Shipping | BA11: Europe to Canada
AF12: 🖨️ PR/NonPR | AG12: Not Printed | AJ12: 🖨️ PR/NonPR | AK12: Printed | AN12: 🖨️ PR/NonPR | AO12: Printed | AR12: 🖨️ PR/NonPR | AS12: Printed | AV12: 🖨️ PR/NonPR | AW12: Not Printed | AZ12: 🖨️ PR/NonPR | BA12: Not Printed
AF13: 🎨 No of colors | AG13: 0 | AJ13: 🎨 No of colors | AK13: 5-8 | AN13: 🎨 No of colors | AO13: 3-4 | AR13: 🎨 No of colors | AS13: 5-8 | AV13: 🎨 No of colors | AW13: 0 | AZ13: 🎨 No of colors | BA13: 0
AF14: 💼 Supplier | AG14: Bastin | AJ14: 💼 Supplier | AK14: Bastin | AN14: 💼 Supplier | AO14: Marma | AR14: 💼 Supplier | AS14: Bastin | AV14: 💼 Supplier | AW14: Bastin | AZ14: 💼 Supplier | BA14: Bastin
AF15: 💰 Total Cost/Kg | AG15: =X3 | AJ15: 💰 Total Cost/Kg | AK15: =X4 | AN15: 💰 Total Cost/Kg | AO15: =X5 | AR15: 💰 Total Cost/Kg | AS15: =X6 | AV15: 💰 Total Cost/Kg | AW15: =X7 | AZ15: 💰 Total Cost/Kg | BA15: =IFERROR(X8,0)
AF17: 💵 SELL PRICE | AJ17: 💵 SELL PRICE | AN17: 💵 SELL PRICE | AR17: 💵 SELL PRICE | AV17: 💵 SELL PRICE | AZ17: 💵 SELL PRICE
AF18: =AG15*(1+AG2) | AJ18: =AK15*(1+AK2) | AN18: =AO15*(1+AO2) | AR18: =AS15*(1+AS2) | AV18: =AW15*(1+AW2) | AZ18: =BA15*(1+BA2)
AF20: 💵 SELL PRICE (USD) | AG20: =AF18*HELPER!$AK$2 | AH20: $ | AJ20: 💵 SELL PRICE (USD) | AK20: =AJ18*HELPER!$AK$2 | AL20: $ | AN20: 💵 SELL PRICE (USD) | AO20: =AN18*HELPER!$AK$2 | AP20: $ | AR20: 💵 SELL PRICE (USD) | AS20: =AR18*HELPER!$AK$2 | AT20: $ | AV20: 💵 SELL PRICE (USD) | AW20: =AV18*HELPER!$AK$2 | AX20: $ | AZ20: 💵 SELL PRICE (USD) | BA20: =AZ18*HELPER!$AK$2 | BB20: $
AF22: ⚙️ Input Mode | AG22: By Weight | AJ22: ⚙️ Input Mode | AK22: By Weight | AN22: ⚙️ Input Mode | AO22: By Weight | AR22: ⚙️ Input Mode | AS22: By Weight | AV22: ⚙️ Input Mode | AW22: By Weight | AZ22: ⚙️ Input Mode | BA22: By Weight
AF23: 📏 Length Input | AG23: 49000 | AH23: Mr | AJ23: 📏 Length Input | AL23: Mr | AN23: 📏 Length Input | AP23: Mr | AR23: 📏 Length Input | AT23: Mr | AV23: 📏 Length Input | AX23: Mr | AZ23: 📏 Length Input | BB23: Mr
AF24: =IF(AND(AG22="By Weight", AG5>HELPER!$BN$2), HELPER!$BO$2, "") | AJ24: =IF(AND(AK22="By Weight", AK5>HELPER!$BN$2), HELPER!$BO$2, "") | AN24: =IF(AND(AO22="By Weight", AO5>HELPER!$BN$2), HELPER!$BO$2, "") | AR24: =IF(AND(AS22="By Weight", AS5>HELPER!$BN$2), HELPER!$BO$2, "") | AV24: =IF(AND(AW22="By Weight", AW5>HELPER!$BN$2), HELPER!$BO$2, "") | AZ24: =IF(AND(BA22="By Weight", BA5>HELPER!$BN$2), HELPER!$BO$2, "")

Sheet Bags Calculator
P2: µ | AC2: 0.25
A3: Dropdown List | B3: Dropdown list | C3: Manual | D3: Manual | E3: Manual | F3: Manual | G3: Manual | H3: Dropdown List | I3: Dropdown List | J3: Dropdown List | K3: Dropdown List | L3: Manual | M3: Dropdown List | N3: Calculation | O3: Calculation | P3: Calculation | Q3: Dropdown | R3: Calculation | S3: Calculation | T3: Calculation | U3: Dropdown List | V3: Dropdown List | W3: Calculation | X3: Calculation | Y3: Calculation | Z3: Manual | AA3: Calculation | AB3: Calculation | AC3: Calculation | AD3: Calculation
A4: Bag Type | B4: Film Type | C4: Bags amount | D4: Height (mm) | E4: Repeat = Width (mm) | F4: Flap | G4: Bottom Gusset | H4: Film | I4: Cast/ Blown | J4: PR/ Non PR | K4: Number of colors | L4: Total film Width (mm) | M4: Thickness (µ) | N4: Bag's Weight (kg) | O4: Bag's Weight + Fall out (kg) | P4: Raw material cost (per kg) | Q4: Shipment Destination | R4: Shipment costs | S4: Raw material cost per bag | T4: Length (m) | U4: Set up waste | V4: Print waste | W4: Zipper waste | X4: Total waste | Y4: Converting cost | Z4: Converting cost - Manual alternative | AA4: Zipper | AB4: Total cost | AC4: Price for customer | AD4: Profit | AF4: Price for customer-USD
A5: Zipper bag | B5: TIPA 302FG | C5: 56000 | D5: 330 | E5: 300 | F5: 30 | G5: 0 | H5: TIPA 302FG | I5: Cast | J5: Printed | K5: 5-8 | L5: =IFERROR(IF(OR(D5=HELPER!Q4,D5=HELPER!$Q$5),D5*2+F5+G5*2,D5*2+G5*2)," ") | M5: 40 | N5: =(E5/1000)*(L5/1000)*(M5/1000)*1.25 | O5: =N5*(1+X5) | P5: =IFERROR(VLOOKUP(B5,BOM!$Q$1:$R$12,2,FALSE),"") | Q5: Europe to US | R5: =IFERROR(IF(Q5="Europe to Canada",IF(C5*O5<1000,(C5*O5/1000)*VLOOKUP(1000,HELPER!$AG$4:$AH$8,2,FALSE)/(C5*O5),VLOOKUP(C5*O5,HELPER!$AG$4:$AH$8,2,TRUE)/(C5*O5)),VLOOKUP(Q5,HELPER!$AF$2:$AH$3,3,FALSE)),0) | S5: =IFERROR(Table6[[#This Row],[Bag''s Weight + Fall out (kg)]]*(Table6[[#This Row],[Raw material cost (per kg)]]+Table6[[#This Row],[Shipment costs]])," ") | T5: =C5*E5/1000 | U5: 300 | V5: 300 | W5: =IFERROR((0.05+SUM(U5,V5)/T5)," ") | X5: =IFERROR((0.075+SUM(U5+V5)/T5+W5),"no data yet") | Y5: =IF(OR(C5="",C5=0),"",((D5*E5)/1000000)*0.175*VLOOKUP(C5,HELPER!$AS$3:$AT$7,2,TRUE)*1.2*1.15*IF((D5+E5)*2>=1200,1.5,1)) | AA5: =IF(A5=HELPER!$Q$2,HELPER!$AD$2,0) | AB5: =IFERROR((P5+U5+V5+W5+X5+IF(Z5<>"",Z5,Y5)+AA5),0) | AC5: =IFERROR(AB5/(1-$AC$2)," ") | AD5: =AC5-AB5 | AF5: =Table6[[#This Row],[Price for customer]]*HELPER!$AK$2
A6: Open Bag | B6: TIPA 312 FG | L6: =IFERROR(IF(OR(D6=HELPER!Q5,D6=HELPER!$Q$5),D6*2+F6+G6*2,D6*2+G6*2)," ") | N6: =(E6/1000)*(L6/1000)*(M6/1000)*1.25 | O6: =N6*(1+X6) | P6: =IFERROR(VLOOKUP(B6,BOM!$Q$1:$R$12,2,FALSE),"") | R6: =IFERROR(IF(Q6="Europe to Canada",IF(C6*O6<1000,(C6*O6/1000)*VLOOKUP(1000,HELPER!$AG$4:$AH$8,2,FALSE)/(C6*O6),VLOOKUP(C6*O6,HELPER!$AG$4:$AH$8,2,TRUE)/(C6*O6)),VLOOKUP(Q6,HELPER!$AF$2:$AH$3,3,FALSE)),0) | S6: =IFERROR(Table6[[#This Row],[Bag''s Weight + Fall out (kg)]]*(Table6[[#This Row],[Raw material cost (per kg)]]+Table6[[#This Row],[Shipment costs]])," ") | W6: =IFERROR((0.05+SUM(U6,V6)/T6)," ") | Y6: =IF(OR(C6="",C6=0),"",((D6*E6)/1000000)*0.175*VLOOKUP(C6,HELPER!$AS$3:$AT$7,2,TRUE)*1.2*1.15*IF((D6+E6)*2>=1200,1.5,1)) | AA6: =IF(A6=HELPER!$Q$2,HELPER!$AD$2,0) | AB6: =IFERROR((P6+U6+V6+W6+X6+IF(Z6<>"",Z6,Y6)+AA6),0) | AC6: =IFERROR(AB6/(1-$AC$2)," ") | AF6: =Table6[[#This Row],[Price for customer]]*HELPER!$AK$2
L7: =IFERROR(IF(OR(D7=HELPER!Q6,D7=HELPER!$Q$5),D7*2+F7+G7*2,D7*2+G7*2)," ") | N7: =(E7/1000)*(L7/1000)*(M7/1000)*1.25 | O7: =N7*(1+X7) | P7: =IFERROR(VLOOKUP(B7,BOM!$Q$1:$R$12,2,FALSE),"") | R7: =IFERROR(IF(Q7="Europe to Canada",IF(C7*O7<1000,(C7*O7/1000)*VLOOKUP(1000,HELPER!$AG$4:$AH$8,2,FALSE)/(C7*O7),VLOOKUP(C7*O7,HELPER!$AG$4:$AH$8,2,TRUE)/(C7*O7)),VLOOKUP(Q7,HELPER!$AF$2:$AH$3,3,FALSE)),0) | S7: =IFERROR(Table6[[#This Row],[Bag''s Weight + Fall out (kg)]]*(Table6[[#This Row],[Raw material cost (per kg)]]+Table6[[#This Row],[Shipment costs]])," ") | W7: =IFERROR((0.05+SUM(U7,V7)/T7)," ") | Y7: =IF(OR(C7="",C7=0),"",((D7*E7)/1000000)*0.175*VLOOKUP(C7,HELPER!$AS$3:$AT$7,2,TRUE)*1.2*1.15*IF((D7+E7)*2>=1200,1.5,1)) | AA7: =IF(A7=HELPER!$Q$2,HELPER!$AD$2,0) | AB7: =IFERROR((P7+U7+V7+W7+X7+IF(Z7<>"",Z7,Y7)+AA7),0) | AC7: =IFERROR(AB7/(1-$AC$2)," ") | AF7: =Table6[[#This Row],[Price for customer]]*HELPER!$AK$2
L8: =IFERROR(IF(OR(D8=HELPER!Q7,D8=HELPER!$Q$5),D8*2+F8+G8*2,D8*2+G8*2)," ") | N8: =(E8/1000)*(L8/1000)*(M8/1000)*1.25 | O8: =N8*(1+X8) | P8: =IFERROR(VLOOKUP(B8,BOM!$Q$1:$R$12,2,FALSE),"") | R8: =IFERROR(IF(Q8="Europe to Canada",IF(C8*O8<1000,(C8*O8/1000)*VLOOKUP(1000,HELPER!$AG$4:$AH$8,2,FALSE)/(C8*O8),VLOOKUP(C8*O8,HELPER!$AG$4:$AH$8,2,TRUE)/(C8*O8)),VLOOKUP(Q8,HELPER!$AF$2:$AH$3,3,FALSE)),0) | S8: =IFERROR(Table6[[#This Row],[Bag''s Weight + Fall out (kg)]]*(Table6[[#This Row],[Raw material cost (per kg)]]+Table6[[#This Row],[Shipment costs]])," ") | W8: =IFERROR((0.05+SUM(U8,V8)/T8)," ") | Y8: =IF(OR(C8="",C8=0),"",((D8*E8)/1000000)*0.175*VLOOKUP(C8,HELPER!$AS$3:$AT$7,2,TRUE)*1.2*1.15*IF((D8+E8)*2>=1200,1.5,1)) | AA8: =IF(A8=HELPER!$Q$2,HELPER!$AD$2,0) | AB8: =IFERROR((P8+U8+V8+W8+X8+IF(Z8<>"",Z8,Y8)+AA8),0) | AC8: =IFERROR(AB8/(1-$AC$2)," ") | AF8: =Table6[[#This Row],[Price for customer]]*HELPER!$AK$2
L9: =IFERROR(IF(OR(D9=HELPER!Q8,D9=HELPER!$Q$5),D9*2+F9+G9*2,D9*2+G9*2)," ") | N9: =(E9/1000)*(L9/1000)*(M9/1000)*1.25 | O9: =N9*(1+X9) | P9: =IFERROR(VLOOKUP(B9,BOM!$Q$1:$R$12,2,FALSE),"") | R9: =IFERROR(IF(Q9="Europe to Canada",IF(C9*O9<1000,(C9*O9/1000)*VLOOKUP(1000,HELPER!$AG$4:$AH$8,2,FALSE)/(C9*O9),VLOOKUP(C9*O9,HELPER!$AG$4:$AH$8,2,TRUE)/(C9*O9)),VLOOKUP(Q9,HELPER!$AF$2:$AH$3,3,FALSE)),0) | S9: =IFERROR(Table6[[#This Row],[Bag''s Weight + Fall out (kg)]]*(Table6[[#This Row],[Raw material cost (per kg)]]+Table6[[#This Row],[Shipment costs]])," ") | W9: =IFERROR((0.05+SUM(U9,V9)/T9)," ") | Y9: =IF(OR(C9="",C9=0),"",((D9*E9)/1000000)*0.175*VLOOKUP(C9,HELPER!$AS$3:$AT$7,2,TRUE)*1.2*1.15*IF((D9+E9)*2>=1200,1.5,1)) | AA9: =IF(A9=HELPER!$Q$2,HELPER!$AD$2,0) | AB9: =IFERROR((P9+U9+V9+W9+X9+IF(Z9<>"",Z9,Y9)+AA9),0) | AC9: =IFERROR(AB9/(1-$AC$2)," ") | AF9: =Table6[[#This Row],[Price for customer]]*HELPER!$AK$2
L10: =IFERROR(IF(OR(D10=HELPER!Q9,D10=HELPER!$Q$5),D10*2+F10+G10*2,D10*2+G10*2)," ") | N10: =(E10/1000)*(L10/1000)*(M10/1000)*1.25 | O10: =N10*(1+X10) | P10: =IFERROR(VLOOKUP(B10,BOM!$Q$1:$R$12,2,FALSE),"") | R10: =IFERROR(IF(Q10="Europe to Canada",IF(C10*O10<1000,(C10*O10/1000)*VLOOKUP(1000,HELPER!$AG$4:$AH$8,2,FALSE)/(C10*O10),VLOOKUP(C10*O10,HELPER!$AG$4:$AH$8,2,TRUE)/(C10*O10)),VLOOKUP(Q10,HELPER!$AF$2:$AH$3,3,FALSE)),0) | S10: =IFERROR(Table6[[#This Row],[Bag''s Weight + Fall out (kg)]]*(Table6[[#This Row],[Raw material cost (per kg)]]+Table6[[#This Row],[Shipment costs]])," ") | W10: =IFERROR((0.05+SUM(U10,V10)/T10)," ") | Y10: =IF(OR(C10="",C10=0),"",((D10*E10)/1000000)*0.175*VLOOKUP(C10,HELPER!$AS$3:$AT$7,2,TRUE)*1.2*1.15*IF((D10+E10)*2>=1200,1.5,1)) | AA10: =IF(A10=HELPER!$Q$2,HELPER!$AD$2,0) | AB10: =IFERROR((P10+U10+V10+W10+X10+IF(Z10<>"",Z10,Y10)+AA10),0) | AC10: =IFERROR(AB10/(1-$AC$2)," ") | AF10: =Table6[[#This Row],[Price for customer]]*HELPER!$AK$2
L11: =IFERROR(IF(OR(D11=HELPER!Q10,D11=HELPER!$Q$5),D11*2+F11+G11*2,D11*2+G11*2)," ") | N11: =(E11/1000)*(L11/1000)*(M11/1000)*1.25 | O11: =N11*(1+X11) | P11: =IFERROR(VLOOKUP(B11,BOM!$Q$1:$R$12,2,FALSE),"") | R11: =IFERROR(IF(Q11="Europe to Canada",IF(C11*O11<1000,(C11*O11/1000)*VLOOKUP(1000,HELPER!$AG$4:$AH$8,2,FALSE)/(C11*O11),VLOOKUP(C11*O11,HELPER!$AG$4:$AH$8,2,TRUE)/(C11*O11)),VLOOKUP(Q11,HELPER!$AF$2:$AH$3,3,FALSE)),0) | S11: =IFERROR(Table6[[#This Row],[Bag''s Weight + Fall out (kg)]]*(Table6[[#This Row],[Raw material cost (per kg)]]+Table6[[#This Row],[Shipment costs]])," ") | W11: =IFERROR((0.05+SUM(U11,V11)/T11)," ") | Y11: =IF(OR(C11="",C11=0),"",((D11*E11)/1000000)*0.175*VLOOKUP(C11,HELPER!$AS$3:$AT$7,2,TRUE)*1.2*1.15*IF((D11+E11)*2>=1200,1.5,1)) | AA11: =IF(A11=HELPER!$Q$2,HELPER!$AD$2,0) | AB11: =IFERROR((P11+U11+V11+W11+X11+IF(Z11<>"",Z11,Y11)+AA11),0) | AC11: =IFERROR(AB11/(1-$AC$2)," ") | AF11: =Table6[[#This Row],[Price for customer]]*HELPER!$AK$2
L12: =IFERROR(IF(OR(D12=HELPER!Q11,D12=HELPER!$Q$5),D12*2+F12+G12*2,D12*2+G12*2)," ") | N12: =(E12/1000)*(L12/1000)*(M12/1000)*1.25 | O12: =N12*(1+X12) | P12: =IFERROR(VLOOKUP(B12,BOM!$Q$1:$R$12,2,FALSE),"") | R12: =IFERROR(IF(Q12="Europe to Canada",IF(C12*O12<1000,(C12*O12/1000)*VLOOKUP(1000,HELPER!$AG$4:$AH$8,2,FALSE)/(C12*O12),VLOOKUP(C12*O12,HELPER!$AG$4:$AH$8,2,TRUE)/(C12*O12)),VLOOKUP(Q12,HELPER!$AF$2:$AH$3,3,FALSE)),0) | S12: =IFERROR(Table6[[#This Row],[Bag''s Weight + Fall out (kg)]]*(Table6[[#This Row],[Raw material cost (per kg)]]+Table6[[#This Row],[Shipment costs]])," ") | W12: =IFERROR((0.05+SUM(U12,V12)/T12)," ") | Y12: =IF(OR(C12="",C12=0),"",((D12*E12)/1000000)*0.175*VLOOKUP(C12,HELPER!$AS$3:$AT$7,2,TRUE)*1.2*1.15*IF((D12+E12)*2>=1200,1.5,1)) | AA12: =IF(A12=HELPER!$Q$2,HELPER!$AD$2,0) | AB12: =IFERROR((P12+U12+V12+W12+X12+IF(Z12<>"",Z12,Y12)+AA12),0) | AC12: =IFERROR(AB12/(1-$AC$2)," ") | AF12: =Table6[[#This Row],[Price for customer]]*HELPER!$AK$2
L13: =IFERROR(IF(OR(D13=HELPER!Q12,D13=HELPER!$Q$5),D13*2+F13+G13*2,D13*2+G13*2)," ") | N13: =(E13/1000)*(L13/1000)*(M13/1000)*1.25 | O13: =N13*(1+X13) | P13: =IFERROR(VLOOKUP(B13,BOM!$Q$1:$R$12,2,FALSE),"") | R13: =IFERROR(IF(Q13="Europe to Canada",IF(C13*O13<1000,(C13*O13/1000)*VLOOKUP(1000,HELPER!$AG$4:$AH$8,2,FALSE)/(C13*O13),VLOOKUP(C13*O13,HELPER!$AG$4:$AH$8,2,TRUE)/(C13*O13)),VLOOKUP(Q13,HELPER!$AF$2:$AH$3,3,FALSE)),0) | S13: =IFERROR(Table6[[#This Row],[Bag''s Weight + Fall out (kg)]]*(Table6[[#This Row],[Raw material cost (per kg)]]+Table6[[#This Row],[Shipment costs]])," ") | W13: =IFERROR((0.05+SUM(U13,V13)/T13)," ") | Y13: =IF(OR(C13="",C13=0),"",((D13*E13)/1000000)*0.175*VLOOKUP(C13,HELPER!$AS$3:$AT$7,2,TRUE)*1.2*1.15*IF((D13+E13)*2>=1200,1.5,1)) | AA13: =IF(A13=HELPER!$Q$2,HELPER!$AD$2,0) | AB13: =IFERROR((P13+U13+V13+W13+X13+IF(Z13<>"",Z13,Y13)+AA13),0) | AC13: =IFERROR(AB13/(1-$AC$2)," ") | AF13: =Table6[[#This Row],[Price for customer]]*HELPER!$AK$2
L14: =IFERROR(IF(OR(D14=HELPER!Q13,D14=HELPER!$Q$5),D14*2+F14+G14*2,D14*2+G14*2)," ") | N14: =(E14/1000)*(L14/1000)*(M14/1000)*1.25 | O14: =N14*(1+X14) | P14: =IFERROR(VLOOKUP(B14,BOM!$Q$1:$R$12,2,FALSE),"") | R14: =IFERROR(IF(Q14="Europe to Canada",IF(C14*O14<1000,(C14*O14/1000)*VLOOKUP(1000,HELPER!$AG$4:$AH$8,2,FALSE)/(C14*O14),VLOOKUP(C14*O14,HELPER!$AG$4:$AH$8,2,TRUE)/(C14*O14)),VLOOKUP(Q14,HELPER!$AF$2:$AH$3,3,FALSE)),0) | S14: =IFERROR(Table6[[#This Row],[Bag''s Weight + Fall out (kg)]]*(Table6[[#This Row],[Raw material cost (per kg)]]+Table6[[#This Row],[Shipment costs]])," ") | W14: =IFERROR((0.05+SUM(U14,V14)/T14)," ") | Y14: =IF(OR(C14="",C14=0),"",((D14*E14)/1000000)*0.175*VLOOKUP(C14,HELPER!$AS$3:$AT$7,2,TRUE)*1.2*1.15*IF((D14+E14)*2>=1200,1.5,1)) | AA14: =IF(A14=HELPER!$Q$2,HELPER!$AD$2,0) | AB14: =IFERROR((P14+U14+V14+W14+X14+IF(Z14<>"",Z14,Y14)+AA14),0) | AC14: =IFERROR(AB14/(1-$AC$2)," ") | AF14: =Table6[[#This Row],[Price for customer]]*HELPER!$AK$2

Sheet Laminates
A1: Dropdown | B1: Manual | C1: Dropdown | D1: Dependant | E1: Manual | F1: Manual | G1: Calc (Based on A & B) | H1: Dependent | I1: Dependent | J1: Dependent on column C | K1: to recheck | N1: to recheck | O1: Dropdown | P1: Dependent, Manual if needed | S1: Dropdown | T1: Dependent on column T | U1: Dependent on column T | V1: Dependent on column T | W1: Calculation | X1: Calculation | Y1: Calculation | AC1: 📊 MARGIN | AD1: 0.2 | AG1: 📊 MARGIN | AH1: 0.2 | AK1: 📊 MARGIN | AL1: 0.25
A2: Measurement | B2: Amount | C2: Laminate | D2: Laminate structure | E2: Width of reel | F2: Length of impression | G2: Laminate length (m) width asked | H2: PR/ NonPR | I2: No of colors | J2: Lemination Width (mm) | K2: Thickness (µ) | L2: Density | M2: Weight (kg) | N2: Raw material Cost | O2: Shipment Destination | P2: Shipment costs | Q2: Cost (€) | R2: Cost Per KG(€) | S2: Supplier | T2: Lamination | U2: Printing | V2: Slitiing | W2: Waste | X2: Printing waste | Y2: Total Cost | AC2: 📊 LAMINATE CALCULATOR 1 | AG2: 📊 LAMINATE CALCULATOR 2 | AK2: 📊 LAMINATE CALCULATOR 3
